Workbook

Sheet Leia-me
A1: Sprout — Modelo financeiro 2027–2031
A2: Gerado por docs/business-plan/modelo/build_model.py a partir de pressupostos.json · data de referência 13-10-2026 · euros correntes, sem IVA
A4: Resultados-chave (ligados à folha Cenários)
A5: Indicador | B5: Unidade | C5: Pessimista | D5: Base | E5: Otimista | F5: Recomendado
A6: EBITDA 2031 | B6: € | C6: =Cenários!G66 -> -931281.49 | D6: =Cenários!G67 -> -1219975.9 | E6: =Cenários!G68 -> -906159.63 | F6: =Cenários!G69 -> -529540.38
A7: Resultado líquido 2031 | B7: € | C7: =Cenários!G70 -> -953731.49 | D7: =Cenários!G71 -> -1261509.2 | E7: =Cenários!G72 -> -967992.97 | F7: =Cenários!G73 -> -569323.71
A8: GMV 2031 | B8: € | C8: =Cenários!G10 -> 2823480 | D8: =Cenários!G11 -> 11142350 | E8: =Cenários!G12 -> 17469500 | F8: =Cenários!G13 -> 22483000
A9: Cash flow acumulado para o acionista, 2027–2031 | B9: € | C9: =Cenários!G78 -> -4277080.6 | D9: =Cenários!G79 -> -5213753.7 | E9: =Cenários!G80 -> -4836437.5 | F9: =Cenários!G81 -> -3726708.2
A10: Necessidade de capital próprio (pico no horizonte) | B10: € | C10: =Cenários!C109 -> 4572080.6 | D10: =Cenários!D109 -> 5508753.7 | E10: =Cenários!E109 -> 5131437.5 | F10: =Cenários!F109 -> 4021708.2
A11: Break-even do EBITDA | B11: mês | C11: =Cenários!C113 -> não atinge até 2031 | D11: =Cenários!D113 -> não atinge até 2031 | E11: =Cenários!E113 -> não atinge até 2031 | F11: =Cenários!F113 -> não atinge até 2031
A12: 1.º ano com cash flow para o acionista ≥ 0 | B12: ano | C12: =Cenários!C115 -> não atinge até 2031 | D12: =Cenários!D115 -> não atinge até 2031 | E12: =Cenários!E115 -> não atinge até 2031 | F12: =Cenários!F115 -> não atinge até 2031
A13: Verificações do modelo (Cenários, secção 5) | C13: =Cenários!C150 -> OK
A16: Para que serve | B16: Testar, com números rastreáveis, se a tese do documento-fonte (marketplace B2B de azeite, água e café com desconto de 10–15%, captura de 80–90% da margem do embalador e investidores a 18 meses) fecha, e qual é o caminho para a viabilidade que a investigação aponta.
B17: Leitores: fundadores, Gonçalo Almeida (jurídico), Pedro Marques (operações, Lagar do Val) e investidores qualificados. Não é uma oferta de investimento.
A19: Resposta curta | B19: Os três cenários do documento-fonte, com as 53 correções verificadas e sem ajustes, não chegam ao break-even até 2031: a margem por kg não paga a estrutura.
B20: O cenário Recomendado (reestruturado) muda o produto, os canais e os custos como a investigação recomenda. O resultado está na tabela acima e na folha Cenários; não foi ajustado para dar break-even. A folha Sensibilidade mostra o caso com todas as alavancas no topo dos intervalos da investigação.
A22: Estrutura | B22: Pressupostos — todos os inputs, por cenário, com fonte; seletor do cenário ativo em C4.
B23: Unit economics — lotes-tipo de ponta a ponta (HoReCa 20 t, distribuidores 30 t, granel 100 t, água 20 paletes) nos quatro cenários; bolo de intermediação; teste da tese literal; risco de preço; piloto de 2027.
B24: Volumes, Receitas, Pessoal, Custos, DR, Cash flow, Capital & financiamento — o cenário ativo, ano a ano.
B25: Cenários — os quatro cenários lado a lado; o que tem de ser verdade; o que muda no Recomendado; verificações.
B26: Sensibilidade — desconto 10/12,5/15%, volumes ±30%, preço do AOVE −30% e topo dos intervalos (motor completo por caso), para o Base e o Recomendado; grelha captura × desconto da tese literal; perda no stock com choque de preço.
B27: Fontes — origem de cada pressuposto e registo de verificação. Motor — o cálculo em blocos fixos por cenário e caso (não editar).
A29: Como mudar de cenário | B29: Pressupostos!C4: escolher Pessimista, Base, Otimista ou Recomendado. Mudam as folhas de detalhe. Cenários, Unit economics e Sensibilidade mostram sempre cenários fixos.
B30: Para alterar um pressuposto: mudar a célula azul em Pressupostos (o livro recalcula). Para que a alteração passe aos PDF, mudar pressupostos.json e voltar a correr build_model.py, que regrava resultados.json.
A32: Código de cores | B32: Azul = input (editar só estas células). Preto = fórmula. Verde = ligação a outra folha. Amarelo = seletor de cenário.
A34: Convenções | B34: Preços das mercadorias constantes ao nível de out. 2026 (compra back-to-back, neutra ao nível de preço); salários +3%/ano; opex +2%/ano e 5% de contingência.
B35: Capital de giro = nível médio do ano por prazos médios (stock, recebimento, pagamento ao produtor a 30 dias). Obrigações = % do capital de giro ÷ utilização; 0% em 2027 (CSC art. 348.º/2 [L]).
B36: EBITDA inclui o cupão das obrigações como custo direto do lote (a SPV financia stock lote a lote), como no 01 e em calculo_referencia.py; a DR mostra também o EBITDA sem cupão.
B37: IRC com taxa PME, derramas municipal e estadual e reporte de prejuízos a 65% [L]. Imposto pago no próprio ano (simplificação).
B38: Break-even em mês = cruzamento do EBITDA mensal com zero, interpolando linearmente entre os pontos médios dos anos (estimativa).
A40: Avisos | B40: Itens [L] (CSC, RGICSF, PRIIPs, IRC, TSU, retenções) estão por confirmar pelo advogado e pelo contabilista certificado: o acesso a fontes primárias (DRE, EUR-Lex, Portal das Finanças) estava bloqueado na verificação.
B41: Itens NV (referência HoReCa, preço de saída do embalador, comissões, custos de custódia e 3PL) são hipóteses a medir no piloto, não promessas comerciais.
B42: Não existem futuros de azeite (MFAO extinto). Deter stock 18 meses sem cobertura arrisca perdas de 50–70% do lote (carry 19,8% + VaR95 37–57% − margem).

Sheet Pressupostos
A1: Pressupostos
A2: Todos os inputs do modelo (azul). Valores lidos de docs/business-plan/modelo/pressupostos.json em 13-10-2026. Etiquetas: [F] facto com fonte; [L] referência legal a confirmar; [E] estimativa; [I] inferência; NV não verificado.
A4: Cenário ativo (escolher na lista) | C4: Base | D4: índice | E4: =MATCH($C$4,$C$8:$F$8,0) -> 2
A5: Muda as folhas Volumes, Receitas, Pessoal, Custos, DR, Cash flow e Capital & financiamento. Cenários, Unit economics e Sensibilidade mostram cenários fixos (folha Motor).
A7: A. Pressupostos escalares por cenário
A8: Parâmetro | B8: Unidade | C8: Pessimista | D8: Base | E8: Otimista | F8: Recomendado | G8: Ativo | H8: Fonte / racional
A9: Azeite: preço do granel e prémios de origem
A10: Índice do granel AOVE (média 2 semanas SIMA + Poolred) | B10: €/kg | C10: 3.5 | D10: 3.5 | E10: 3.5 | F10: 3.5 | G10: =CHOOSE($E$4,C10,D10,E10,F10) -> 3.5 | H10: [F] SIMA 3,40–3,80 e Poolred 3,34 (out. 2026); 3,50 arredondado para cima; constante (compra back-to-back). 00 §1.2
A11: Prémio de origem pago ao lagar — HoReCa/gourmet | B11: €/kg | C11: 0.15 | D11: 0.1 | E11: 0.05 | F11: 0.15 | G11: =CHOOSE($E$4,C11,D11,E11,F11) -> 0.1 | H11: [E] lote individualizado com ficha analítica; Recomendado 0,15 (DOP/monovarietal, o prémio mais alto do conjunto verificado)
A12: Prémio de origem pago ao lagar — distribuidores/exportação | B12: €/kg | C12: 0.15 | D12: 0.1 | E12: 0.05 | F12: 0.1 | G12: =CHOOSE($E$4,C12,D12,E12,F12) -> 0.1 | H12: [E] igual ao HoReCa nos cenários do documento-fonte (calculo_referencia.py usa um só prémio)
A13: Prémio de origem pago ao lagar — granel certificado | B13: €/kg | C13: 0 | D13: 0 | E13: 0 | F13: 0 | G13: =CHOOSE($E$4,C13,D13,E13,F13) -> 0 | H13: [E] granel comprado ao índice: o lagar ganha prazo (≤ 30 dias por SCT Inst), não preço
A14: Azeite: canal HoReCa/gourmet
A15: Referência do comprador (cotação documentada do equivalente, s/ IVA) | B15: €/kg | C15: 5.4 | D15: 5.65 | E15: 6 | F15: 6 | G15: =CHOOSE($E$4,C15,D15,E15,F15) -> 5.65 | H15: [E, NV] equivalente de retalho standard 5,3–6,0; 6,00 só com origem identificada documentada (gate: ≥ 20 cotações). 00 §1.4; 01 §2.1
A16: Desconto ao comprador sobre a referência | B16: % | C16: 0.1 | D16: 0.1 | E16: 0.1 | F16: 0.1 | G16: =CHOOSE($E$4,C16,D16,E16,F16) -> 0.1 | H16: Documento-fonte 10–15%; 10% porque 15% leva a margem para ~1,4%. 01 §2.5
A17: Prazo médio de recebimento | B17: dias | C17: 45 | D17: 35 | E17: 30 | F17: 35 | G17: =CHOOSE($E$4,C17,D17,E17,F17) -> 35 | H17: [F] restauração: 30 dias de atraso médio, 11% paga a horas (Informa D&B mai. 2026); 35 dias com SDD B2B
A18: Provisão de crédito | B18: % vendas | C18: 0.008 | D18: 0.006 | E18: 0.005 | F18: 0.006 | G18: =CHOOSE($E$4,C18,D18,E18,F18) -> 0.006 | H18: [E] SDD B2B sem direito a reembolso + limites por cliente
A19: Azeite: canal distribuidores/exportação
A20: Referência = preço de saída do embalador | B20: €/kg | C20: 4.2 | D20: 4.35 | E20: 4.5 | F20: 4.35 | G20: =CHOOSE($E$4,C20,D20,E20,F20) -> 4.35 | H20: [E, NV] granel 3,50 + embalamento 0,47–0,51 + margem do embalador 0,19–0,50 = 4,16–4,51. 00 §1.4
A21: Prémio de origem verificada pago pelo comprador | B21: €/kg | C21: 0 | D21: 0 | E21: 0 | F21: 0.1 | G21: =CHOOSE($E$4,C21,D21,E21,F21) -> 0 | H21: [E] 0 no documento-fonte; Recomendado 0,10 = limite inferior da condição para a seed (0,10–0,20). 01 §5.4
A22: Desconto ao comprador | B22: % | C22: 0 | D22: 0 | E22: 0 | F22: 0 | G22: =CHOOSE($E$4,C22,D22,E22,F22) -> 0 | H22: 0%: qualquer desconto põe o canal abaixo do break-even (4,29 €/kg). 01 §2.5
A23: Stock médio | B23: dias | C23: 35 | D23: 30 | E23: 25 | F23: 30 | G23: =CHOOSE($E$4,C23,D23,E23,F23) -> 30 | H23: [E] paletes levantadas em ~60 dias
A24: Prazo médio de recebimento | B24: dias | C24: 55 | D24: 45 | E24: 40 | F24: 55 | G24: =CHOOSE($E$4,C24,D24,E24,F24) -> 45 | H24: [E] Recomendado 55 dias (mais exportação embalada; valor do pessimista)
A25: Provisão de crédito | B25: % vendas | C25: 0.005 | D25: 0.003 | E25: 0.003 | F25: 0.003 | G25: =CHOOSE($E$4,C25,D25,E25,F25) -> 0.003 | H25: [E]
A26: Outros pressupostos por cenário
A27: Água: comissão de agente sobre o GMV | B27: % | C27: 0.01 | D27: 0.02 | E27: 0.03 | F27: 0.02 | G27: =CHOOSE($E$4,C27,D27,E27,F27) -> 0.02 | H27: [E, NV] banda 0,5–3%; 4–5% só com cotação real de um engarrafador. 01 §6.1
A28: Café: ano de início | B28: ano | C28: 2029 | D28: 2029 | E28: 2028 | F28: 2030 | G28: =CHOOSE($E$4,C28,D28,E28,F28) -> 2029 | H28: [F] EUDR aplicável a 30-12-2026 (grandes/médios) e 30-06-2027 (micro/pequenos); Recomendado adia para 2030
A29: Café: custo de cobertura (forward EUR/USD; ICE > 50–100 t/ano) | B29: % compras | C29: 0 | D29: 0 | E29: 0 | F29: 0.003 | G29: =CHOOSE($E$4,C29,D29,E29,F29) -> 0 | H29: [E/NV] forward 0,1–0,5%; ICE < 0,5% do nocional por semestre. 40 §2.3–2.4
A30: Verificação para terceiros: parte dos custos suportada pela Sprout | B30: % | C30: 1 | D30: 1 | E30: 1 | F30: 0 | G30: =CHOOSE($E$4,C30,D30,E30,F30) -> 1 | H30: 1 = Sprout paga collateral manager e análises; 0 = banco/mutuário paga (alternativa da nota de custos)
A31: Utilização média do capital levantado nas séries | B31: % | C31: 0.7 | D31: 0.8 | E31: 0.85 | F31: 0.8 | G31: =CHOOSE($E$4,C31,D31,E31,F31) -> 0.8 | H31: [E] capital levantado a 12–18 meses vs. rotação do stock de 2–4 meses. 40 §5.1
A32: Ronda pré-seed (recebida até 31-01-2027) | B32: € | C32: 1100000 | D32: 1100000 | E32: 1100000 | F32: 1100000 | G32: =CHOOSE($E$4,C32,D32,E32,F32) -> 1100000 | H32: 01 §5.5 e §7.3: 1,1 M€ (ou 0,8 M€ + bridge firme de 0,3 M€)
A34: B. Constantes (iguais em todos os cenários)
A35: Parâmetro | B35: Unidade | C35: Valor | G35: Ativo | H35: Fonte / racional
A36: Azeite: canal HoReCa/gourmet (constantes)
A37: Embalamento no lagar (5 L PET/BIB e vidro) | B37: €/kg | C37: 0.55 | G37: =C37 -> 0.55 | H37: [F] Observatorio 0,47–0,51 €/kg + 0,05 pelo mix com vidro. 00 §1.4
A38: Armazém logístico (3PL) e picking | B38: €/kg | C38: 0.06 | G38: =C38 -> 0.06 | H38: [E, NV] encomendas de 20–50 kg a ~2–4 € cada
A39: Dimensão do lote-tipo | B39: t | C39: 20 | G39: =C39 -> 20 | H39: 01 §2.2
A40: Análises por lote (entrada + intermédia) | B40: n.º | C40: 2 | G40: =C40 -> 2 | H40: 40 §5.2
A41: Custódia (collateral manager) por lote | B41: €/lote | C41: 2000 | G41: =C41 -> 2000 | H41: [E, NV] 300–500 € por visita: entrada + ~3 tranches + fecho
A42: Pagamentos bancários (SEPA) | B42: €/kg | C42: 0.01 | G42: =C42 -> 0.01 | H42: [E] comissões por operação; KYC e faturação no custo fixo de tecnologia
A43: Azeite: canal distribuidores/exportação (constantes)
A44: Embalamento no lagar (paletes de 5 L) | B44: €/kg | C44: 0.45 | G44: =C44 -> 0.45 | H44: [F] Observatorio 0,47–0,51 €/kg
A45: Armazém logístico (3PL) | B45: €/kg | C45: 0 | G45: =C45 -> 0 | H45: Levantamento no lagar
A46: Dimensão do lote-tipo | B46: t | C46: 30 | G46: =C46 -> 30 | H46: 01 §2.5
A47: Análises por lote | B47: n.º | C47: 2 | G47: =C47 -> 2 | H47: 40 §5.2
A48: Custódia por lote | B48: €/lote | C48: 1200 | G48: =C48 -> 1200 | H48: [E, NV]
A49: Pagamentos bancários | B49: €/kg | C49: 0.005 | G49: =C49 -> 0.005 | H49: [E]
A50: Azeite: canal granel certificado (só o Recomendado tem volume)
A51: Preço de venda = índice + prémio de certificação | B51: €/kg | C51: 0.15 | G51: =C51 -> 0.15 | H51: [E] JSON: granel = índice + ≤ 0,15 €/kg, margem 0–0,10; 40 §1.3: margem bruta de trading 0,15–0,30. Usa-se 0,15
A52: Desconto ao comprador | B52: % | C52: 0 | G52: =C52 -> 0 | H52: Venda ao índice + prémio
A53: Embalamento | B53: €/kg | C53: 0 | G53: =C53 -> 0 | H53: IBC/cisterna, sem embalamento
A54: Logística (cisterna até ao embalador/exportador) | B54: €/kg | C54: 0.04 | G54: =C54 -> 0.04 | H54: [E, NV] ~1.000 € por cisterna de 24 t na Ibéria
A55: Armazém logístico (3PL) | B55: €/kg | C55: 0 | G55: =C55 -> 0 | H55: —
A56: Stock médio (back-to-back) | B56: dias | C56: 15 | G56: =C56 -> 15 | H56: [E] lote sai do tanque em ~30 dias
A57: Prazo médio de recebimento | B57: dias | C57: 45 | G57: =C57 -> 45 | H57: [E] igual aos distribuidores no base; Dir. 2019/633: ≤ 60 dias para não perecíveis
A58: Dimensão do lote | B58: t | C58: 100 | G58: =C58 -> 100 | H58: Igual à verificação para terceiros (lote de 100 t)
A59: Análises por lote | B59: n.º | C59: 2 | G59: =C59 -> 2 | H59: 600 € por lote de 100 t
A60: Custódia por lote | B60: €/lote | C60: 1200 | G60: =C60 -> 1200 | H60: 1.200 € por lote de 100 t
A61: Pagamentos bancários | B61: €/kg | C61: 0.001 | G61: =C61 -> 0.001 | H61: [E] poucas operações de valor alto
A62: Provisão de crédito | B62: % vendas | C62: 0.003 | G62: =C62 -> 0.003 | H62: [E] igual aos distribuidores
A63: Azeite: custos físicos, custódia e cobertura
A64: Armazenagem no lagar | B64: €/t/mês | C64: 4 | G64: =C64 -> 4 | H64: [E] método de custo, 2–8 €/t/mês. 40 §1.5
A65: Seguro do stock | B65: %/ano | C65: 0.002 | G65: =C65 -> 0.002 | H65: [E, NV] 0,1–0,3%/ano. 40 §4.5
A66: Análise físico-química completa + painel | B66: € | C66: 300 | G66: =C66 -> 300 | H66: [E, NV] 40 §5.2
A67: Perdas físicas (uma vez) | B67: % valor | C67: 0.005 | G67: =C67 -> 0.005 | H67: [E] 40 §5.2
A68: Probabilidade de desclassificação por trimestre | B68: % | C68: 0.03 | G68: =C68 -> 0.03 | H68: [E] 3%/5%/15%/30% a 3/6/12/18 meses. 40 §5.2
A69: Penalização por desclassificação | B69: €/kg | C69: 0.3 | G69: =C69 -> 0.3 | H69: [F] diferencial AOVE–lampante 0,24 (2026); 0,75 um ano antes
A70: Prazo de pagamento ao produtor | B70: dias | C70: 30 | G70: =C70 -> 30 | H70: [F] Dir. (UE) 2019/633 e DL 118/2010 (DL 76/2021): ≤ 30/60 dias; política Sprout 30 dias
A71: Custo explícito de cobertura do azeite | B71: % vendas | C71: 0 | G71: =C71 -> 0 | H71: [F] sem futuros de azeite: MFAO extinto (MIC XSRM expirado em jan. 2017); cobertura = back-to-back, indexação, offtake
A72: Azeite: mercado
A73: Consumo por cliente HoReCa/gourmet | B73: t/ano | C73: 0.205 | G73: =C73 -> 0.205 | H73: [E] 150–300 L/ano = 137–275 kg. 10 §5
A74: Produção de azeite em Portugal (referência) | B74: kt | C74: 175 | G74: =C74 -> 175 | H74: [E] ~175 kt (160 Olivum; 179 Governo). 00 §1.1
A75: Água (modelo agente; lote de comparação)
A76: Litros por palete | B76: L | C76: 750 | G76: =C76 -> 750 | H76: [E] 500 garrafas de 1,5 L
A77: Garrafas por palete | B77: n.º | C77: 500 | G77: =C77 -> 500 | H77: [E]
A78: Preço B2B de referência | B78: €/L | C78: 0.4 | G78: =C78 -> 0.4 | H78: [E, NV] hipótese 0,30–0,60 €/L. 10 §2.3
A79: Desconto ao comprador | B79: % | C79: 0.1 | G79: =C79 -> 0.1 | H79: Documento-fonte
A80: Prazo de recebimento da comissão | B80: dias | C80: 30 | G80: =C80 -> 30 | H80: [E]
A81: Preço ex-fábrica médio (lote principal) | B81: €/L | C81: 0.24 | G81: =C81 -> 0.24 | H81: [I] DGEG 2025: 479 M€ / ~2.000 M L
A82: Depósito SDR por embalagem < 3 L | B82: € | C82: 0.1 | G82: =C82 -> 0.1 | H82: [F] SDR desde 10-04-2026
A83: Lote-tipo de água | B83: paletes | C83: 20 | G83: =C83 -> 20 | H83: 01 §2.7
A84: Desconto alternativo no lote principal | B84: % | C84: 0.15 | G84: =C84 -> 0.15 | H84: 01 §2.7
A85: Logística troncal por lote (principal) | B85: €/lote | C85: 200 | G85: =C85 -> 200 | H85: 01 §2.7 [E]
A86: Entrega por litro (principal) | B86: €/L | C86: 0.05 | G86: =C86 -> 0.05 | H86: 01 §2.7 [E]
A87: Operação e pagamentos por lote (principal) | B87: €/lote | C87: 150 | G87: =C87 -> 150 | H87: 01 §2.7 [E]
A88: Dias de financiamento do stock e do SDR (principal) | B88: dias | C88: 30 | G88: =C88 -> 30 | H88: 01 §2.7 [E]
A89: Café verde (principal; compra a importador UE)
A90: Preço de compra (EUR, preço fixo, importador UE operador EUDR) | B90: €/kg | C90: 7 | G90: =C90 -> 7 | H90: [E, NV] KC 2,85 USD/lb = 5,46 €/kg a 1,15 + ~1,5 €/kg de diferencial, importação e logística
A91: Preço de venda a microtorrefatores | B91: €/kg | C91: 7.85 | G91: =C91 -> 7.85 | H91: [E] NV, sem comparável verificado (margem bruta ~11%)
A92: Logística | B92: €/kg | C92: 0.15 | G92: =C92 -> 0.15 | H92: [E]
A93: Stock médio | B93: dias | C93: 45 | G93: =C93 -> 45 | H93: [E]
A94: Prazo de recebimento | B94: dias | C94: 30 | G94: =C94 -> 30 | H94: [E]
A95: Prazo de pagamento ao importador | B95: dias | C95: 30 | G95: =C95 -> 30 | H95: [E]
A96: Provisão de crédito | B96: % vendas | C96: 0.006 | G96: =C96 -> 0.006 | H96: [E]
A97: Operações e pagamentos | B97: €/kg | C97: 0.03 | G97: =C97 -> 0.03 | H97: [E]
A98: Serviços: verificação e financiamento de stock de terceiros
A99: Comissão de verificação por utilização | B99: % carteira | C99: 0.0075 | G99: =C99 -> 0.0075 | H99: [E] estruturação/verificação 1–2% do lote financiado. 50 §12.2
A100: Rotações da carteira por ano | B100: n.º | C100: 2 | G100: =C100 -> 2 | H100: [E]
A101: Comissão de monitorização anual | B101: % carteira | C101: 0.005 | G101: =C101 -> 0.005 | H101: [E]
A102: Custo de verificação por kg verificado | B102: €/kg | C102: 0.018 | G102: =C102 -> 0.018 | H102: [E] collateral manager 1.200 € + análises 600 € por lote de 100 t
A103: Valor do colateral | B103: €/kg | C103: 3.5 | G103: =C103 -> 3.5 | H103: Índice do granel
...

Sheet Unit economics
A1: Unit economics
A2: Lotes-tipo de ponta a ponta, por cenário (independente do seletor). Valores por kg lidos do Motor no ano de regime; lote = €/kg × dimensão do lote.
A3: Ano de regime dos lotes-tipo | C3: =Pressupostos!$C$187 -> 2029 | D3: =C3-2026 -> 3 | E3: ← índice do ano (1 = 2027); mude o ano em Pressupostos
A5: A. Lote de azeite HoReCa/gourmet (origem identificada; 5 L PET/BIB e vidro)
A6: Ponta a ponta no ano de regime (por lote e por kg)
A7: Rubrica | B7: Unidade | C7: Pessimista: € / lote | D7: Pessimista: €/kg | E7: Base: € / lote | F7: Base: €/kg | G7: Otimista: € / lote | H7: Otimista: €/kg | I7: Recomendado: € / lote | J7: Recomendado: €/kg | K7: Notas
A8: Dimensão do lote | B8: kg | C8: =Pressupostos!$C$39*1000 -> 20000 | E8: =Pressupostos!$C$39*1000 -> 20000 | G8: =Pressupostos!$C$39*1000 -> 20000 | I8: =Pressupostos!$C$39*1000 -> 20000
A9: Preço de referência do comprador (mercado) | B9: € | C9: =D9*$C$8 -> 108000 | D9: =INDEX(Motor!$C$28:$G$28,1,$D$3) -> 5.4 | E9: =F9*$E$8 -> 113000 | F9: =INDEX(Motor!$C$338:$G$338,1,$D$3) -> 5.65 | G9: =H9*$G$8 -> 120000 | H9: =INDEX(Motor!$C$648:$G$648,1,$D$3) -> 6 | I9: =J9*$I$8 -> 120000 | J9: =INDEX(Motor!$C$958:$G$958,1,$D$3) -> 6
A10: Desconto ao comprador | B10: € | C10: =D10*$C$8 -> -10800 | D10: =-(INDEX(Motor!$C$28:$G$28,1,$D$3)-INDEX(Motor!$C$29:$G$29,1,$D$3)) -> -0.54 | E10: =F10*$E$8 -> -11300 | F10: =-(INDEX(Motor!$C$338:$G$338,1,$D$3)-INDEX(Motor!$C$339:$G$339,1,$D$3)) -> -0.565 | G10: =H10*$G$8 -> -12000 | H10: =-(INDEX(Motor!$C$648:$G$648,1,$D$3)-INDEX(Motor!$C$649:$G$649,1,$D$3)) -> -0.6 | I10: =J10*$I$8 -> -12000 | J10: =-(INDEX(Motor!$C$958:$G$958,1,$D$3)-INDEX(Motor!$C$959:$G$959,1,$D$3)) -> -0.6
A11: Receita Sprout (preço de venda) | B11: € | C11: =D11*$C$8 -> 97200 | D11: =INDEX(Motor!$C$29:$G$29,1,$D$3) -> 4.86 | E11: =F11*$E$8 -> 101700 | F11: =INDEX(Motor!$C$339:$G$339,1,$D$3) -> 5.085 | G11: =H11*$G$8 -> 108000 | H11: =INDEX(Motor!$C$649:$G$649,1,$D$3) -> 5.4 | I11: =J11*$I$8 -> 108000 | J11: =INDEX(Motor!$C$959:$G$959,1,$D$3) -> 5.4
A12: Preço ao produtor (índice + prémio; pago ≤ 30 dias) | B12: € | C12: =D12*$C$8 -> -73000 | D12: =-INDEX(Motor!$C$27:$G$27,1,$D$3) -> -3.65 | E12: =F12*$E$8 -> -72000 | F12: =-INDEX(Motor!$C$337:$G$337,1,$D$3) -> -3.6 | G12: =H12*$G$8 -> -71000 | H12: =-INDEX(Motor!$C$647:$G$647,1,$D$3) -> -3.55 | I12: =J12*$I$8 -> -73000 | J12: =-INDEX(Motor!$C$957:$G$957,1,$D$3) -> -3.65
A13: Embalamento no lagar | B13: € | C13: =D13*$C$8 -> -11000 | D13: =-INDEX(Motor!$C$30:$G$30,1,$D$3) -> -0.55 | E13: =F13*$E$8 -> -11000 | F13: =-INDEX(Motor!$C$340:$G$340,1,$D$3) -> -0.55 | G13: =H13*$G$8 -> -11000 | H13: =-INDEX(Motor!$C$650:$G$650,1,$D$3) -> -0.55 | I13: =J13*$I$8 -> -11000 | J13: =-INDEX(Motor!$C$960:$G$960,1,$D$3) -> -0.55
A14: Logística | B14: € | C14: =D14*$C$8 -> -6200 | D14: =-INDEX(Motor!$C$31:$G$31,1,$D$3) -> -0.31 | E14: =F14*$E$8 -> -5600 | F14: =-INDEX(Motor!$C$341:$G$341,1,$D$3) -> -0.28 | G14: =H14*$G$8 -> -5200 | H14: =-INDEX(Motor!$C$651:$G$651,1,$D$3) -> -0.26 | I14: =J14*$I$8 -> -5600 | J14: =-INDEX(Motor!$C$961:$G$961,1,$D$3) -> -0.28
A15: Armazém logístico (3PL) e picking | B15: € | C15: =D15*$C$8 -> -1200 | D15: =-INDEX(Motor!$C$32:$G$32,1,$D$3) -> -0.06 | E15: =F15*$E$8 -> -1200 | F15: =-INDEX(Motor!$C$342:$G$342,1,$D$3) -> -0.06 | G15: =H15*$G$8 -> -1200 | H15: =-INDEX(Motor!$C$652:$G$652,1,$D$3) -> -0.06 | I15: =J15*$I$8 -> -1200 | J15: =-INDEX(Motor!$C$962:$G$962,1,$D$3) -> -0.06
A16: Armazenagem | B16: € | C16: =D16*$C$8 -> -480 | D16: =-INDEX(Motor!$C$35:$G$35,1,$D$3) -> -0.024 | E16: =F16*$E$8 -> -120 | F16: =-INDEX(Motor!$C$345:$G$345,1,$D$3) -> -0.006 | G16: =H16*$G$8 -> -120 | H16: =-INDEX(Motor!$C$655:$G$655,1,$D$3) -> -0.006 | I16: =J16*$I$8 -> -120 | J16: =-INDEX(Motor!$C$965:$G$965,1,$D$3) -> -0.006
A17: Seguro do stock | B17: € | C17: =D17*$C$8 -> -72 | D17: =-INDEX(Motor!$C$36:$G$36,1,$D$3) -> -0.0036 | E17: =F17*$E$8 -> -17.753425 | F17: =-INDEX(Motor!$C$346:$G$346,1,$D$3) -> -0.00088767123 | G17: =H17*$G$8 -> -17.506849 | H17: =-INDEX(Motor!$C$656:$G$656,1,$D$3) -> -0.00087534247 | I17: =J17*$I$8 -> -18 | J17: =-INDEX(Motor!$C$966:$G$966,1,$D$3) -> -0.0009
A18: Análises físico-químicas e painel (testes de qualidade) | B18: € | C18: =D18*$C$8 -> -600 | D18: =-INDEX(Motor!$C$37:$G$37,1,$D$3) -> -0.03 | E18: =F18*$E$8 -> -600 | F18: =-INDEX(Motor!$C$347:$G$347,1,$D$3) -> -0.03 | G18: =H18*$G$8 -> -600 | H18: =-INDEX(Motor!$C$657:$G$657,1,$D$3) -> -0.03 | I18: =J18*$I$8 -> -600 | J18: =-INDEX(Motor!$C$967:$G$967,1,$D$3) -> -0.03
A19: Perdas físicas | B19: € | C19: =D19*$C$8 -> -365 | D19: =-INDEX(Motor!$C$38:$G$38,1,$D$3) -> -0.01825 | E19: =F19*$E$8 -> -360 | F19: =-INDEX(Motor!$C$348:$G$348,1,$D$3) -> -0.018 | G19: =H19*$G$8 -> -355 | H19: =-INDEX(Motor!$C$658:$G$658,1,$D$3) -> -0.01775 | I19: =J19*$I$8 -> -365 | J19: =-INDEX(Motor!$C$968:$G$968,1,$D$3) -> -0.01825
A20: Desclassificação esperada | B20: € | C20: =D20*$C$8 -> -360 | D20: =-INDEX(Motor!$C$39:$G$39,1,$D$3) -> -0.018 | E20: =F20*$E$8 -> -90 | F20: =-INDEX(Motor!$C$349:$G$349,1,$D$3) -> -0.0045 | G20: =H20*$G$8 -> -90 | H20: =-INDEX(Motor!$C$659:$G$659,1,$D$3) -> -0.0045 | I20: =J20*$I$8 -> -90 | J20: =-INDEX(Motor!$C$969:$G$969,1,$D$3) -> -0.0045
A21: Custódia independente (collateral manager) | B21: € | C21: =D21*$C$8 -> -2000 | D21: =-INDEX(Motor!$C$40:$G$40,1,$D$3) -> -0.1 | E21: =F21*$E$8 -> -2000 | F21: =-INDEX(Motor!$C$350:$G$350,1,$D$3) -> -0.1 | G21: =H21*$G$8 -> -2000 | H21: =-INDEX(Motor!$C$660:$G$660,1,$D$3) -> -0.1 | I21: =J21*$I$8 -> -2000 | J21: =-INDEX(Motor!$C$970:$G$970,1,$D$3) -> -0.1
A22: Pagamentos bancários (SEPA; KYC/KYB no custo fixo) | B22: € | C22: =D22*$C$8 -> -200 | D22: =-INDEX(Motor!$C$41:$G$41,1,$D$3) -> -0.01 | E22: =F22*$E$8 -> -200 | F22: =-INDEX(Motor!$C$351:$G$351,1,$D$3) -> -0.01 | G22: =H22*$G$8 -> -200 | H22: =-INDEX(Motor!$C$661:$G$661,1,$D$3) -> -0.01 | I22: =J22*$I$8 -> -200 | J22: =-INDEX(Motor!$C$971:$G$971,1,$D$3) -> -0.01
A23: Provisão de crédito | B23: € | C23: =D23*$C$8 -> -777.6 | D23: =-INDEX(Motor!$C$42:$G$42,1,$D$3) -> -0.03888 | E23: =F23*$E$8 -> -610.2 | F23: =-INDEX(Motor!$C$352:$G$352,1,$D$3) -> -0.03051 | G23: =H23*$G$8 -> -540 | H23: =-INDEX(Motor!$C$662:$G$662,1,$D$3) -> -0.027 | I23: =J23*$I$8 -> -648 | J23: =-INDEX(Motor!$C$972:$G$972,1,$D$3) -> -0.0324
A24: Cobertura de preço explícita (azeite: sem futuros) | B24: € | C24: =D24*$C$8 -> 0 | D24: =-INDEX(Motor!$C$43:$G$43,1,$D$3) -> 0 | E24: =F24*$E$8 -> 0 | F24: =-INDEX(Motor!$C$353:$G$353,1,$D$3) -> 0 | G24: =H24*$G$8 -> 0 | H24: =-INDEX(Motor!$C$663:$G$663,1,$D$3) -> 0 | I24: =J24*$I$8 -> 0 | J24: =-INDEX(Motor!$C$973:$G$973,1,$D$3) -> 0
A25: Cupão das obrigações (retorno do investidor no ciclo) | B25: € | C25: =D25*$C$8 -> -4904.3836 | D25: =-INDEX(Motor!$C$44:$G$44,1,$D$3) -> -0.24521918 | E25: =F25*$E$8 -> -959.33219 | F25: =-INDEX(Motor!$C$354:$G$354,1,$D$3) -> -0.04796661 | G25: =H25*$G$8 -> -749.29895 | H25: =-INDEX(Motor!$C$664:$G$664,1,$D$3) -> -0.037464948 | I25: =J25*$I$8 -> -970.89041 | J25: =-INDEX(Motor!$C$974:$G$974,1,$D$3) -> -0.048544521
A26: Margem de contribuição do Sprout (spread da plataforma) | B26: € | C26: =D26*$C$8 -> -3958.9836 | D26: =INDEX(Motor!$C$46:$G$46,1,$D$3) -> -0.19794918 | E26: =F26*$E$8 -> 6942.7144 | F26: =INDEX(Motor!$C$356:$G$356,1,$D$3) -> 0.34713572 | G26: =H26*$G$8 -> 14928.194 | H26: =INDEX(Motor!$C$666:$G$666,1,$D$3) -> 0.74640971 | I26: =J26*$I$8 -> 12188.11 | J26: =INDEX(Motor!$C$976:$G$976,1,$D$3) -> 0.60940548
A27: Margem em % da receita | B27: % | D27: =IF(D11>0,D26/D11,0) -> -0.040730284 | F27: =IF(F11>0,F26/F11,0) -> 0.068266611 | H27: =IF(H11>0,H26/H11,0) -> 0.13822402 | J27: =IF(J11>0,J26/J11,0) -> 0.11285287
A28: Lado do investidor e almofada
A29: Capital imobilizado no lote (granel + embalamento) | B29: € | C29: =(INDEX(Motor!$C$27:$G$27,1,$D$3)+INDEX(Motor!$C$30:$G$30,1,$D$3))*$C$8 -> 84000 | E29: =(INDEX(Motor!$C$337:$G$337,1,$D$3)+INDEX(Motor!$C$340:$G$340,1,$D$3))*$E$8 -> 83000 | G29: =(INDEX(Motor!$C$647:$G$647,1,$D$3)+INDEX(Motor!$C$650:$G$650,1,$D$3))*$G$8 -> 82000 | I29: =(INDEX(Motor!$C$957:$G$957,1,$D$3)+INDEX(Motor!$C$960:$G$960,1,$D$3))*$I$8 -> 84000
A30: Ciclo líquido do capital (stock + recebimento − pagamento) | B30: dias | C30: =INDEX(Motor!$C$33:$G$33,1,$D$3)+INDEX(Motor!$C$34:$G$34,1,$D$3)-Pressupostos!$C$70 -> 195 | E30: =INDEX(Motor!$C$343:$G$343,1,$D$3)+INDEX(Motor!$C$344:$G$344,1,$D$3)-Pressupostos!$C$70 -> 50 | G30: =INDEX(Motor!$C$653:$G$653,1,$D$3)+INDEX(Motor!$C$654:$G$654,1,$D$3)-Pressupostos!$C$70 -> 45 | I30: =INDEX(Motor!$C$963:$G$963,1,$D$3)+INDEX(Motor!$C$964:$G$964,1,$D$3)-Pressupostos!$C$70 -> 50
A31: Parte do capital de giro financiada por obrigações | B31: % | C31: =INDEX(Pressupostos!$C$276:$G$276,1,$D$3) -> 0.85 | E31: =INDEX(Pressupostos!$C$277:$G$277,1,$D$3) -> 0.9 | G31: =INDEX(Pressupostos!$C$278:$G$278,1,$D$3) -> 0.9 | I31: =INDEX(Pressupostos!$C$279:$G$279,1,$D$3) -> 0.9
A32: Obrigações afetas ao lote (capital levantado = financiado ÷ utilização) | B32: € | C32: =INDEX(Pressupostos!$C$276:$G$276,1,$D$3)*(INDEX(Motor!$C$27:$G$27,1,$D$3)+INDEX(Motor!$C$30:$G$30,1,$D$3))*$C$8/Pressupostos!$C$31 -> 102000 | E32: =INDEX(Pressupostos!$C$277:$G$277,1,$D$3)*(INDEX(Motor!$C$337:$G$337,1,$D$3)+INDEX(Motor!$C$340:$G$340,1,$D$3))*$E$8/Pressupostos!$D$31 -> 93375 | G32: =INDEX(Pressupostos!$C$278:$G$278,1,$D$3)*(INDEX(Motor!$C$647:$G$647,1,$D$3)+INDEX(Motor!$C$650:$G$650,1,$D$3))*$G$8/Pressupostos!$E$31 -> 86823.529 | I32: =INDEX(Pressupostos!$C$279:$G$279,1,$D$3)*(INDEX(Motor!$C$957:$G$957,1,$D$3)+INDEX(Motor!$C$960:$G$960,1,$D$3))*$I$8/Pressupostos!$F$31 -> 94500
A33: Capital próprio do patrocinador no lote (subordinado) | B33: € | C33: =(1-INDEX(Pressupostos!$C$276:$G$276,1,$D$3))*(INDEX(Motor!$C$27:$G$27,1,$D$3)+INDEX(Motor!$C$30:$G$30,1,$D$3))*$C$8 -> 12600 | E33: =(1-INDEX(Pressupostos!$C$277:$G$277,1,$D$3))*(INDEX(Motor!$C$337:$G$337,1,$D$3)+INDEX(Motor!$C$340:$G$340,1,$D$3))*$E$8 -> 8300 | G33: =(1-INDEX(Pressupostos!$C$278:$G$278,1,$D$3))*(INDEX(Motor!$C$647:$G$647,1,$D$3)+INDEX(Motor!$C$650:$G$650,1,$D$3))*$G$8 -> 8200 | I33: =(1-INDEX(Pressupostos!$C$279:$G$279,1,$D$3))*(INDEX(Motor!$C$957:$G$957,1,$D$3)+INDEX(Motor!$C$960:$G$960,1,$D$3))*$I$8 -> 8400
A34: Cupão bruto anual | B34: % | C34: =INDEX(Pressupostos!$C$282:$G$282,1,$D$3) -> 0.09 | E34: =INDEX(Pressupostos!$C$283:$G$283,1,$D$3) -> 0.075 | G34: =INDEX(Pressupostos!$C$284:$G$284,1,$D$3) -> 0.07 | I34: =INDEX(Pressupostos!$C$285:$G$285,1,$D$3) -> 0.075
A35: Retorno líquido anual de um particular residente (retenção de 28%) | B35: % | C35: =INDEX(Pressupostos!$C$282:$G$282,1,$D$3)*(1-Pressupostos!$C$109) -> 0.0648 | E35: =INDEX(Pressupostos!$C$283:$G$283,1,$D$3)*(1-Pressupostos!$C$109) -> 0.054 | G35: =INDEX(Pressupostos!$C$284:$G$284,1,$D$3)*(1-Pressupostos!$C$109) -> 0.0504 | I35: =INDEX(Pressupostos!$C$285:$G$285,1,$D$3)*(1-Pressupostos!$C$109) -> 0.054
A36: Cupão pago no ciclo do lote | B36: € | C36: =INDEX(Motor!$C$44:$G$44,1,$D$3)*$C$8 -> 4904.3836 | E36: =INDEX(Motor!$C$354:$G$354,1,$D$3)*$E$8 -> 959.33219 | G36: =INDEX(Motor!$C$664:$G$664,1,$D$3)*$G$8 -> 749.29895 | I36: =INDEX(Motor!$C$974:$G$974,1,$D$3)*$I$8 -> 970.89041
A37: Retorno bruto do investidor no ciclo (% das obrigações afetas ao lote) | B37: % | C37: =IF(INDEX(Pressupostos!$C$276:$G$276,1,$D$3)>0,INDEX(Motor!$C$44:$G$44,1,$D$3)*$C$8/(INDEX(Pressupostos!$C$276:$G$276,1,$D$3)*(INDEX(Motor!$C$27:$G$27,1,$D$3)+INDEX(Motor!$C$30:$G$30,1,$D$3))*$C$8/Pressupostos!$C$31),0) -> 0.048082192 | E37: =IF(INDEX(Pressupostos!$C$277:$G$277,1,$D$3)>0,INDEX(Motor!$C$354:$G$354,1,$D$3)*$E$8/(INDEX(Pressupostos!$C$277:$G$277,1,$D$3)*(INDEX(Motor!$C$337:$G$337,1,$D$3)+INDEX(Motor!$C$340:$G$340,1,$D$3))*$E$8/Pressupostos!$D$31),0) -> 0.010273973 | G37: =IF(INDEX(Pressupostos!$C$278:$G$278,1,$D$3)>0,INDEX(Motor!$C$664:$G$664,1,$D$3)*$G$8/(INDEX(Pressupostos!$C$278:$G$278,1,$D$3)*(INDEX(Motor!$C$647:$G$647,1,$D$3)+INDEX(Motor!$C$650:$G$650,1,$D$3))*$G$8/Pressupostos!$E$31),0) -> 0.008630137 | I37: =IF(INDEX(Pressupostos!$C$279:$G$279,1,$D$3)>0,INDEX(Motor!$C$974:$G$974,1,$D$3)*$I$8/(INDEX(Pressupostos!$C$279:$G$279,1,$D$3)*(INDEX(Motor!$C$957:$G$957,1,$D$3)+INDEX(Motor!$C$960:$G$960,1,$D$3))*$I$8/Pressupostos!$F$31),0) -> 0.010273973
A38: Retida na reserva de primeira perda (30% da margem; teto 5% das obrigações do lote) | B38: € | C38: =MAX(0,MIN(Pressupostos!$C$108*INDEX(Motor!$C$46:$G$46,1,$D$3)*$C$8,Pressupostos!$C$107*INDEX(Pressupostos!$C$276:$G$276,1,$D$3)*(INDEX(Motor!$C$27:$G$27,1,$D$3)+INDEX(Motor!$C$30:$G$30,1,$D$3))*$C$8/Pressupostos!$C$31)) -> 0 | E38: =MAX(0,MIN(Pressupostos!$C$108*INDEX(Motor!$C$356:$G$356,1,$D$3)*$E$8,Pressupostos!$C$107*INDEX(Pressupostos!$C$277:$G$277,1,$D$3)*(INDEX(Motor!$C$337:$G$337,1,$D$3)+INDEX(Motor!$C$340:$G$340,1,$D$3))*$E$8/Pressupostos!$D$31)) -> 2082.8143 | G38: =MAX(0,MIN(Pressupostos!$C$108*INDEX(Motor!$C$666:$G$666,1,$D$3)*$G$8,Pressupostos!$C$107*INDEX(Pressupostos!$C$278:$G$278,1,$D$3)*(INDEX(Motor!$C$647:$G$647,1,$D$3)+INDEX(Motor!$C$650:$G$650,1,$D$3))*$G$8/Pressupostos!$E$31)) -> 4341.1765 | I38: =MAX(0,MIN(Pressupostos!$C$108*INDEX(Motor!$C$976:$G$976,1,$D$3)*$I$8,Pressupostos!$C$107*INDEX(Pressupostos!$C$279:$G$279,1,$D$3)*(INDEX(Motor!$C$957:$G$957,1,$D$3)+INDEX(Motor!$C$960:$G$960,1,$D$3))*$I$8/Pressupostos!$F$31)) -> 3656.4329
A39: Margem livre para a OpCo depois da reserva | B39: € | C39: =INDEX(Motor!$C$46:$G$46,1,$D$3)*$C$8-C38 -> -3958.9836 | E39: =INDEX(Motor!$C$356:$G$356,1,$D$3)*$E$8-E38 -> 4859.9001 | G39: =INDEX(Motor!$C$666:$G$666,1,$D$3)*$G$8-G38 -> 10587.018 | I39: =INDEX(Motor!$C$976:$G$976,1,$D$3)*$I$8-I38 -> 8531.6767
A40: Memo: KYC/KYB e screening das contrapartes do lote (no custo fixo de tecnologia) | B40: € | C40: =$C$8/(Pressupostos!$C$73*1000)*(Pressupostos!$C$119+12*Pressupostos!$C$120) -> 1268.2927 | E40: =$E$8/(Pressupostos!$C$73*1000)*(Pressupostos!$C$119+12*Pressupostos!$C$120) -> 1268.2927 | G40: =$G$8/(Pressupostos!$C$73*1000)*(Pressupostos!$C$119+12*Pressupostos!$C$120) -> 1268.2927 | I40: =$I$8/(Pressupostos!$C$73*1000)*(Pressupostos!$C$119+12*Pressupostos!$C$120) -> 1268.2927
A41: Memo: custo nocional do capital próprio (8%/ano; fora do EBITDA) | B41: € | C41: =Pressupostos!$C$111*(1-INDEX(Pressupostos!$C$276:$G$276,1,$D$3))*(INDEX(Motor!$C$27:$G$27,1,$D$3)+INDEX(Motor!$C$30:$G$30,1,$D$3))*(INDEX(Motor!$C$33:$G$33,1,$D$3)+INDEX(Motor!$C$34:$G$34,1,$D$3)-Pressupostos!$C$70)/365*$C$8 -> 538.52055 | E41: =Pressupostos!$C$111*(1-INDEX(Pressupostos!$C$277:$G$277,1,$D$3))*(INDEX(Motor!$C$337:$G$337,1,$D$3)+INDEX(Motor!$C$340:$G$340,1,$D$3))*(INDEX(Motor!$C$343:$G$343,1,$D$3)+INDEX(Motor!$C$344:$G$344,1,$D$3)-Pressupostos!$C$70)/365*$E$8 -> 90.958904 | G41: =Pressupostos!$C$111*(1-INDEX(Pressupostos!$C$278:$G$278,1,$D$3))*(INDEX(Motor!$C$647:$G$647,1,$D$3)+INDEX(Motor!$C$650:$G$650,1,$D$3))*(INDEX(Motor!$C$653:$G$653,1,$D$3)+INDEX(Motor!$C$654:$G$654,1,$D$3)-Pressupostos!$C$70)/365*$G$8 -> 80.876712 | I41: =Pressupostos!$C$111*(1-INDEX(Pressupostos!$C$279:$G$279,1,$D$3))*(INDEX(Motor!$C$957:$G$957,1,$D$3)+INDEX(Motor!$C$960:$G$960,1,$D$3))*(INDEX(Motor!$C$963:$G$963,1,$D$3)+INDEX(Motor!$C$964:$G$964,1,$D$3)-Pressupostos!$C$70)/365*$I$8 -> 92.054795
A43: Bolo de intermediação (Π = referência − granel − embalamento − logística) e repartição
A44: Rubrica | B44: Unidade | C44: Pessimista | D44: Base | E44: Otimista | F44: Recomendado | K44: Notas
A45: Π por kg | B45: €/kg | C45: =D9+D12+D13+D14 -> 0.89 | D45: =F9+F12+F13+F14 -> 1.22 | E45: =H9+H12+H13+H14 -> 1.64 | F45: =J9+J12+J13+J14 -> 1.52
A46: Comprador: desconto | B46: % de Π | C46: =IF(C45>0,-D10/C45,0) -> 0.60674157 | D46: =IF(D45>0,-F10/D45,0) -> 0.46311475 | E46: =IF(E45>0,-H10/E45,0) -> 0.36585366 | F46: =IF(F45>0,-J10/F45,0) -> 0.39473684
A47: Investidores: cupão | B47: % de Π | C47: =IF(C45>0,-D25/C45,0) -> 0.27552717 | D47: =IF(D45>0,-F25/D45,0) -> 0.039316893 | E47: =IF(E45>0,-H25/E45,0) -> 0.02284448 | F47: =IF(F45>0,-J25/F45,0) -> 0.031937185
A48: Custos diretos (3PL, custódia, qualidade, crédito, pagamentos, armazenagem) | B48: % de Π | C48: =IF(C45>0,-(D15+D16+D17+D18+D19+D20+D21+D22+D23+D24)/C45,0) -> 0.34014607 | D48: =IF(D45>0,-(F15+F16+F17+F18+F19+F20+F21+F22+F23+F24)/D45,0) -> 0.21303088 | E48: =IF(E45>0,-(H15+H16+H17+H18+H19+H20+H21+H22+H23+H24)/E45,0) -> 0.15617399 | F48: =IF(F45>0,-(J15+J16+J17+J18+J19+J20+J21+J22+J23+J24)/F45,0) -> 0.17240132
A49: Sprout: margem de contribuição | B49: % de Π | C49: =IF(C45>0,D26/C45,0) -> -0.22241481 | D49: =IF(D45>0,F26/D45,0) -> 0.28453747 | E49: =IF(E45>0,H26/E45,0) -> 0.45512787 | F49: =IF(F45>0,J26/F45,0) -> 0.40092466
A51: Teste da tese literal do documento-fonte (lote HoReCa, por kg): captura de 80–90% da margem do embalador + desconto de 10–15%
A52: Rubrica | B52: Unidade | C52: Pessimista | D52: Base | E52: Otimista | F52: Recomendado | K52: Notas
A53: Margem líquida do embalador (média de 3 campanhas do Observatorio) | B53: €/kg | C53: =Pressupostos!$C$197 -> 0.297 | D53: =Pressupostos!$C$197 -> 0.297 | E53: =Pressupostos!$C$197 -> 0.297 | F53: =Pressupostos!$C$197 -> 0.297
A54: Captura de 85% (ponto médio de 80–90%) | B54: €/kg | C54: =Pressupostos!$C$200*C53 -> 0.25245 | D54: =Pressupostos!$C$200*D53 -> 0.25245 | E54: =Pressupostos!$C$200*E53 -> 0.25245 | F54: =Pressupostos!$C$200*F53 -> 0.25245
A55: Custo do desconto ao comprador (desconto × referência) | B55: €/kg | C55: =D10 -> -0.54 | D55: =F10 -> -0.565 | E55: =H10 -> -0.6 | F55: =J10 -> -0.6
A56: Retorno do investidor (cupão do ciclo) | B56: €/kg | C56: =D25 -> -0.24521918 | D56: =F25 -> -0.04796661 | E56: =H25 -> -0.037464948 | F56: =J25 -> -0.048544521
A57: Custos diretos da plataforma (sem granel, embalamento e logística) | B57: €/kg | C57: =D15+D16+D17+D18+D19+D20+D21+D22+D23+D24 -> -0.30273 | D57: =F15+F16+F17+F18+F19+F20+F21+F22+F23+F24 -> -0.25989767 | E57: =H15+H16+H17+H18+H19+H20+H21+H22+H23+H24 -> -0.25612534 | F57: =J15+J16+J17+J18+J19+J20+J21+J22+J23+J24 -> -0.26205
A58: Spread que sobra para a plataforma | B58: €/kg | C58: =C54+C55+C56+C57 -> -0.83549918 | D58: =D54+D55+D56+D57 -> -0.62041428 | E58: =E54+E55+E56+E57 -> -0.64114029 | F58: =F54+F55+F56+F57 -> -0.65814452 | K58: Negativo = a tese literal não fecha: o desconto custa mais do que a margem capturada
A59: Desconto ÷ captura (vezes) | B59: x | C59: =IF(C54>0,-C55/C54,0) -> 2.1390374 | D59: =IF(D54>0,-D55/D54,0) -> 2.2380669 | E59: =IF(E54>0,-E55/E54,0) -> 2.3767083 | F59: =IF(F54>0,-F55/F54,0) -> 2.3767083
A60: Veredicto | C60: =IF(C58<0,"não fecha","fecha") -> não fecha | D60: =IF(D58<0,"não fecha","fecha") -> não fecha | E60: =IF(E58<0,"não fecha","fecha") -> não fecha | F60: =IF(F58<0,"não fecha","fecha") -> não fecha
A62: Risco de preço do lote HoReCa (por que só back-to-back)
A63: Rubrica | B63: Unidade | C63: Pessimista | D63: Base | E63: Otimista | F63: Recomendado | K63: Notas
A64: Valor do stock ao custo (granel + embalamento) | B64: € | C64: =C29 -> 84000 | D64: =E29 -> 83000 | E64: =G29 -> 82000 | F64: =I29 -> 84000
A65: Choque de −30% no preço: perda com 100% do lote em aberto | B65: € | C65: =Pressupostos!$C$195*C64 -> -25200 | D65: =Pressupostos!$C$195*D64 -> -24900 | E65: =Pressupostos!$C$195*E64 -> -24600 | F65: =Pressupostos!$C$195*F64 -> -25200
A66: Idem com 15% em aberto (política back-to-back) | B66: € | C66: =Pressupostos!$C$186*C65 -> -3780 | D66: =Pressupostos!$C$186*D65 -> -3735 | E66: =Pressupostos!$C$186*E65 -> -3690 | F66: =Pressupostos!$C$186*F65 -> -3780
A67: Perda com 100% em aberto ÷ margem do lote | B67: x | C67: =IF(C26>0,-C65/C26,0) -> 0 | D67: =IF(E26>0,-D65/E26,0) -> 3.5864935 | E67: =IF(G26>0,-E65/G26,0) -> 1.6478885 | F67: =IF(I26>0,-F65/I26,0) -> 2.0675889
A68: Detenção de 18 meses sem cobertura: carry + VaR95 (σ 23%) − margem | B68: % do lote | C68: =Pressupostos!$C$183+Pressupostos!$C$184-D27 -> 0.60873028 | D68: =Pressupostos!$C$183+Pressupostos!$C$184-F27 -> 0.49973339 | E68: =Pressupostos!$C$183+Pressupostos!$C$184-H27 -> 0.42977598 | F68: =Pressupostos!$C$183+Pressupostos!$C$184-J27 -> 0.45514713 | K68: 40 §5.2 e §1.3; 01 §2.6. Não há futuros de azeite para cobrir esta perda.
A69: Idem com σ 42% | B69: % do lote | C69: =Pressupostos!$C$183+Pressupostos!$C$185-D27 -> 0.80873028 | D69: =Pressupostos!$C$183+Pressupostos!$C$185-F27 -> 0.69973339 | E69: =Pressupostos!$C$183+Pressupostos!$C$185-H27 -> 0.62977598 | F69: =Pressupostos!$C$183+Pressupostos!$C$185-J27 -> 0.65514713
A71: Piloto de 2027 (sem obrigações: stock em capital próprio)
A72: Rubrica | B72: Unidade | C72: Pessimista | D72: Base | E72: Otimista | F72: Recomendado | K72: Notas
A73: HoReCa/gourmet: preço de venda | B73: €/kg | C73: =Motor!$C$29 -> 4.86 | D73: =Motor!$C$339 -> 5.085 | E73: =Motor!$C$649 -> 5.4 | F73: =Motor!$C$959 -> 5.4
A74: HoReCa/gourmet: custo direto | B74: €/kg | C74: =Motor!$C$45 -> 4.82273 | D74: =Motor!$C$355 -> 4.7440607 | E74: =Motor!$C$665 -> 4.6902514 | F74: =Motor!$C$975 -> 4.79625
A75: HoReCa/gourmet: margem de contribuição | B75: €/kg | C75: =Motor!$C$46 -> 0.03727 | D75: =Motor!$C$356 -> 0.34093932 | E75: =Motor!$C$666 -> 0.70974863 | F75: =Motor!$C$976 -> 0.60375
A76: HoReCa/gourmet: margem em % | B76: % | C76: =Motor!$C$47 -> 0.0076687243 | D76: =Motor!$C$357 -> 0.067048046 | E76: =Motor!$C$667 -> 0.13143493 | F76: =Motor!$C$977 -> 0.11180556
A77: Distribuidores/exportação: preço de venda | B77: €/kg | C77: =Motor!$C$52 -> 4.2 | D77: =Motor!$C$362 -> 4.35 | E77: =Motor!$C$672 -> 4.5 | F77: =Motor!$C$982 -> 4.45
A78: Distribuidores/exportação: custo direto | B78: €/kg | C78: =Motor!$C$68 -> 4.3231167 | D78: =Motor!$C$378 -> 4.2536418 | E78: =Motor!$C$688 -> 4.2025696 | F78: =Motor!$C$998 -> 4.2539418
A79: Distribuidores/exportação: margem de contribuição | B79: €/kg | C79: =Motor!$C$69 -> -0.12311667 | D79: =Motor!$C$379 -> 0.096358219 | E79: =Motor!$C$689 -> 0.29743037 | F79: =Motor!$C$999 -> 0.19605822
A80: Distribuidores/exportação: margem em % | B80: % | C80: =Motor!$C$70 -> -0.029313492 | D80: =Motor!$C$380 -> 0.022151315 | E80: =Motor!$C$690 -> 0.066095637 | F80: =Motor!$C$1000 -> 0.044058027
A82: B. Lote de azeite para distribuidores/exportação (paletes de 5 L; preço de saída do embalador)
A83: Ponta a ponta no ano de regime (por lote e por kg)
A84: Rubrica | B84: Unidade | C84: Pessimista: € / lote | D84: Pessimista: €/kg | E84: Base: € / lote | F84: Base: €/kg | G84: Otimista: € / lote | H84: Otimista: €/kg | I84: Recomendado: € / lote | J84: Recomendado: €/kg | K84: Notas
A85: Dimensão do lote | B85: kg | C85: =Pressupostos!$C$46*1000 -> 30000 | E85: =Pressupostos!$C$46*1000 -> 30000 | G85: =Pressupostos!$C$46*1000 -> 30000 | I85: =Pressupostos!$C$46*1000 -> 30000
A86: Preço de referência do comprador (mercado) | B86: € | C86: =D86*$C$85 -> 126000 | D86: =INDEX(Motor!$C$51:$G$51,1,$D$3) -> 4.2 | E86: =F86*$E$85 -> 130500 | F86: =INDEX(Motor!$C$361:$G$361,1,$D$3) -> 4.35 | G86: =H86*$G$85 -> 135000 | H86: =INDEX(Motor!$C$671:$G$671,1,$D$3) -> 4.5 | I86: =J86*$I$85 -> 133500 | J86: =INDEX(Motor!$C$981:$G$981,1,$D$3) -> 4.45
A87: Desconto ao comprador | B87: € | C87: =D87*$C$85 -> 0 | D87: =-(INDEX(Motor!$C$51:$G$51,1,$D$3)-INDEX(Motor!$C$52:$G$52,1,$D$3)) -> 0 | E87: =F87*$E$85 -> 0 | F87: =-(INDEX(Motor!$C$361:$G$361,1,$D$3)-INDEX(Motor!$C$362:$G$362,1,$D$3)) -> 0 | G87: =H87*$G$85 -> 0 | H87: =-(INDEX(Motor!$C$671:$G$671,1,$D$3)-INDEX(Motor!$C$672:$G$672,1,$D$3)) -> 0 | I87: =J87*$I$85 -> 0 | J87: =-(INDEX(Motor!$C$981:$G$981,1,$D$3)-INDEX(Motor!$C$982:$G$982,1,$D$3)) -> 0
A88: Receita Sprout (preço de venda) | B88: € | C88: =D88*$C$85 -> 126000 | D88: =INDEX(Motor!$C$52:$G$52,1,$D$3) -> 4.2 | E88: =F88*$E$85 -> 130500 | F88: =INDEX(Motor!$C$362:$G$362,1,$D$3) -> 4.35 | G88: =H88*$G$85 -> 135000 | H88: =INDEX(Motor!$C$672:$G$672,1,$D$3) -> 4.5 | I88: =J88*$I$85 -> 133500 | J88: =INDEX(Motor!$C$982:$G$982,1,$D$3) -> 4.45
A89: Preço ao produtor (índice + prémio; pago ≤ 30 dias) | B89: € | C89: =D89*$C$85 -> -109500 | D89: =-INDEX(Motor!$C$50:$G$50,1,$D$3) -> -3.65 | E89: =F89*$E$85 -> -108000 | F89: =-INDEX(Motor!$C$360:$G$360,1,$D$3) -> -3.6 | G89: =H89*$G$85 -> -106500 | H89: =-INDEX(Motor!$C$670:$G$670,1,$D$3) -> -3.55 | I89: =J89*$I$85 -> -108000 | J89: =-INDEX(Motor!$C$980:$G$980,1,$D$3) -> -3.6
A90: Embalamento no lagar | B90: € | C90: =D90*$C$85 -> -13500 | D90: =-INDEX(Motor!$C$53:$G$53,1,$D$3) -> -0.45 | E90: =F90*$E$85 -> -13500 | F90: =-INDEX(Motor!$C$363:$G$363,1,$D$3) -> -0.45 | G90: =H90*$G$85 -> -13500 | H90: =-INDEX(Motor!$C$673:$G$673,1,$D$3) -> -0.45 | I90: =J90*$I$85 -> -13500 | J90: =-INDEX(Motor!$C$983:$G$983,1,$D$3) -> -0.45
A91: Logística | B91: € | C91: =D91*$C$85 -> -3300 | D91: =-INDEX(Motor!$C$54:$G$54,1,$D$3) -> -0.11 | E91: =F91*$E$85 -> -2700 | F91: =-INDEX(Motor!$C$364:$G$364,1,$D$3) -> -0.09 | G91: =H91*$G$85 -> -2400 | H91: =-INDEX(Motor!$C$674:$G$674,1,$D$3) -> -0.08 | I91: =J91*$I$85 -> -2700 | J91: =-INDEX(Motor!$C$984:$G$984,1,$D$3) -> -0.09
A92: Armazém logístico (3PL) e picking | B92: € | C92: =D92*$C$85 -> 0 | D92: =-INDEX(Motor!$C$55:$G$55,1,$D$3) -> 0 | E92: =F92*$E$85 -> 0 | F92: =-INDEX(Motor!$C$365:$G$365,1,$D$3) -> 0 | G92: =H92*$G$85 -> 0 | H92: =-INDEX(Motor!$C$675:$G$675,1,$D$3) -> 0 | I92: =J92*$I$85 -> 0 | J92: =-INDEX(Motor!$C$985:$G$985,1,$D$3) -> 0
A93: Armazenagem | B93: € | C93: =D93*$C$85 -> -140 | D93: =-INDEX(Motor!$C$58:$G$58,1,$D$3) -> -0.0046666667 | E93: =F93*$E$85 -> -120 | F93: =-INDEX(Motor!$C$368:$G$368,1,$D$3) -> -0.004 | G93: =H93*$G$85 -> -100 | H93: =-INDEX(Motor!$C$678:$G$678,1,$D$3) -> -0.0033333333 | I93: =J93*$I$85 -> -120 | J93: =-INDEX(Motor!$C$988:$G$988,1,$D$3) -> -0.004
A94: Seguro do stock | B94: € | C94: =D94*$C$85 -> -21 | D94: =-INDEX(Motor!$C$59:$G$59,1,$D$3) -> -0.0007 | E94: =F94*$E$85 -> -17.753425 | F94: =-INDEX(Motor!$C$369:$G$369,1,$D$3) -> -0.00059178082 | G94: =H94*$G$85 -> -14.589041 | H94: =-INDEX(Motor!$C$679:$G$679,1,$D$3) -> -0.00048630137 | I94: =J94*$I$85 -> -17.753425 | J94: =-INDEX(Motor!$C$989:$G$989,1,$D$3) -> -0.00059178082
A95: Análises físico-químicas e painel (testes de qualidade) | B95: € | C95: =D95*$C$85 -> -600 | D95: =-INDEX(Motor!$C$60:$G$60,1,$D$3) -> -0.02 | E95: =F95*$E$85 -> -600 | F95: =-INDEX(Motor!$C$370:$G$370,1,$D$3) -> -0.02 | G95: =H95*$G$85 -> -600 | H95: =-INDEX(Motor!$C$680:$G$680,1,$D$3) -> -0.02 | I95: =J95*$I$85 -> -600 | J95: =-INDEX(Motor!$C$990:$G$990,1,$D$3) -> -0.02
A96: Perdas físicas | B96: € | C96: =D96*$C$85 -> -547.5 | D96: =-INDEX(Motor!$C$61:$G$61,1,$D$3) -> -0.01825 | E96: =F96*$E$85 -> -540 | F96: =-INDEX(Motor!$C$371:$G$371,1,$D$3) -> -0.018 | G96: =H96*$G$85 -> -532.5 | H96: =-INDEX(Motor!$C$681:$G$681,1,$D$3) -> -0.01775 | I96: =J96*$I$85 -> -540 | J96: =-INDEX(Motor!$C$991:$G$991,1,$D$3) -> -0.018
A97: Desclassificação esperada | B97: € | C97: =D97*$C$85 -> -105 | D97: =-INDEX(Motor!$C$62:$G$62,1,$D$3) -> -0.0035 | E97: =F97*$E$85 -> -90 | F97: =-INDEX(Motor!$C$372:$G$372,1,$D$3) -> -0.003 | G97: =H97*$G$85 -> -75 | H97: =-INDEX(Motor!$C$682:$G$682,1,$D$3) -> -0.0025 | I97: =J97*$I$85 -> -90 | J97: =-INDEX(Motor!$C$992:$G$992,1,$D$3) -> -0.003
A98: Custódia independente (collateral manager) | B98: € | C98: =D98*$C$85 -> -1200 | D98: =-INDEX(Motor!$C$63:$G$63,1,$D$3) -> -0.04 | E98: =F98*$E$85 -> -1200 | F98: =-INDEX(Motor!$C$373:$G$373,1,$D$3) -> -0.04 | G98: =H98*$G$85 -> -1200 | H98: =-INDEX(Motor!$C$683:$G$683,1,$D$3) -> -0.04 | I98: =J98*$I$85 -> -1200 | J98: =-INDEX(Motor!$C$993:$G$993,1,$D$3) -> -0.04
A99: Pagamentos bancários (SEPA; KYC/KYB no custo fixo) | B99: € | C99: =D99*$C$85 -> -150 | D99: =-INDEX(Motor!$C$64:$G$64,1,$D$3) -> -0.005 | E99: =F99*$E$85 -> -150 | F99: =-INDEX(Motor!$C$374:$G$374,1,$D$3) -> -0.005 | G99: =H99*$G$85 -> -150 | H99: =-INDEX(Motor!$C$684:$G$684,1,$D$3) -> -0.005 | I99: =J99*$I$85 -> -150 | J99: =-INDEX(Motor!$C$994:$G$994,1,$D$3) -> -0.005
A100: Provisão de crédito | B100: € | C100: =D100*$C$85 -> -630 | D100: =-INDEX(Motor!$C$65:$G$65,1,$D$3) -> -0.021 | E100: =F100*$E$85 -> -391.5 | F100: =-INDEX(Motor!$C$375:$G$375,1,$D$3) -> -0.01305 | G100: =H100*$G$85 -> -405 | H100: =-INDEX(Motor!$C$685:$G$685,1,$D$3) -> -0.0135 | I100: =J100*$I$85 -> -400.5 | J100: =-INDEX(Motor!$C$995:$G$995,1,$D$3) -> -0.01335
A101: Cobertura de preço explícita (azeite: sem futuros) | B101: € | C101: =D101*$C$85 -> 0 | D101: =-INDEX(Motor!$C$66:$G$66,1,$D$3) -> 0 | E101: =F101*$E$85 -> 0 | F101: =-INDEX(Motor!$C$376:$G$376,1,$D$3) -> 0 | G101: =H101*$G$85 -> 0 | H101: =-INDEX(Motor!$C$686:$G$686,1,$D$3) -> 0 | I101: =J101*$I$85 -> 0 | J101: =-INDEX(Motor!$C$996:$G$996,1,$D$3) -> 0
A102: Cupão das obrigações (retorno do investidor no ciclo) | B102: € | C102: =D102*$C$85 -> -2209.6673 | D102: =-INDEX(Motor!$C$67:$G$67,1,$D$3) -> -0.073655577 | E102: =F102*$E$85 -> -1263.8913 | F102: =-INDEX(Motor!$C$377:$G$377,1,$D$3) -> -0.042129709 | G102: =H102*$G$85 -> -852.8606 | H102: =-INDEX(Motor!$C$687:$G$687,1,$D$3) -> -0.028428687 | I102: =J102*$I$85 -> -1544.756 | J102: =-INDEX(Motor!$C$997:$G$997,1,$D$3) -> -0.051491866
A103: Margem de contribuição do Sprout (spread da plataforma) | B103: € | C103: =D103*$C$85 -> -5903.1673 | D103: =INDEX(Motor!$C$69:$G$69,1,$D$3) -> -0.19677224 | E103: =F103*$E$85 -> 1926.8553 | F103: =INDEX(Motor!$C$379:$G$379,1,$D$3) -> 0.06422851 | G103: =H103*$G$85 -> 8670.0504 | H103: =INDEX(Motor!$C$689:$G$689,1,$D$3) -> 0.28900168 | I103: =J103*$I$85 -> 4636.9906 | J103: =INDEX(Motor!$C$999:$G$999,1,$D$3) -> 0.15456635
A104: Margem em % da receita | B104: % | D104: =IF(D88>0,D103/D88,0) -> -0.046850534 | F104: =IF(F88>0,F103/F88,0) -> 0.014765175 | H104: =IF(H88>0,H103/H88,0) -> 0.064222595 | J104: =IF(J88>0,J103/J88,0) -> 0.034734012
A105: Lado do investidor e almofada
A106: Capital imobilizado no lote (granel + embalamento) | B106: € | C106: =(INDEX(Motor!$C$50:$G$50,1,$D$3)+INDEX(Motor!$C$53:$G$53,1,$D$3))*$C$85 -> 123000 | E106: =(INDEX(Motor!$C$360:$G$360,1,$D$3)+INDEX(Motor!$C$363:$G$363,1,$D$3))*$E$85 -> 121500 | G106: =(INDEX(Motor!$C$670:$G$670,1,$D$3)+INDEX(Motor!$C$673:$G$673,1,$D$3))*$G$85 -> 120000 | I106: =(INDEX(Motor!$C$980:$G$980,1,$D$3)+INDEX(Motor!$C$983:$G$983,1,$D$3))*$I$85 -> 121500
...

Sheet Volumes
A1: Volumes
A2: Volumes físicos por mercadoria e canal, clientes e carteira de terceiros (cenário ativo).
A3: ="Cenário ativo: "&Pressupostos!$C$4&" · euros correntes, sem IVA" -> Cenário ativo: Base · euros correntes, sem IVA
A4: Rubrica | B4: Unidade | C4: 2027 | D4: 2028 | E4: 2029 | F4: 2030 | G4: 2031 | H4: Notas
A5: Calendário
A6: Ano | C6: 2027 | D6: 2028 | E6: 2029 | F6: 2030 | G6: 2031
A8: Azeite (t)
A9: Clientes HoReCa/gourmet ativos (média anual) | B9: n.º | C9: =Pressupostos!$C$211 -> 40 | D9: =Pressupostos!$D$211 -> 180 | E9: =Pressupostos!$E$211 -> 650 | F9: =Pressupostos!$F$211 -> 1300 | G9: =Pressupostos!$G$211 -> 2000
A10: Azeite HoReCa/gourmet | B10: t | C10: =Pressupostos!$C$217 -> 8 | D10: =Pressupostos!$D$217 -> 37 | E10: =Pressupostos!$E$217 -> 133 | F10: =Pressupostos!$F$217 -> 267 | G10: =Pressupostos!$G$217 -> 410
A11: Azeite distribuidores/exportação (offtake) | B11: t | C11: =Pressupostos!$C$223 -> 52 | D11: =Pressupostos!$D$223 -> 363 | E11: =Pressupostos!$E$223 -> 717 | F11: =Pressupostos!$F$223 -> 1183 | G11: =Pressupostos!$G$223 -> 1790
A12: Azeite granel certificado | B12: t | C12: =Pressupostos!$C$229 -> 0 | D12: =Pressupostos!$D$229 -> 0 | E12: =Pressupostos!$E$229 -> 0 | F12: =Pressupostos!$F$229 -> 0 | G12: =Pressupostos!$G$229 -> 0
A13: Azeite total | B13: t | C13: =C10+C11+C12 -> 60 | D13: =D10+D11+D12 -> 400 | E13: =E10+E11+E12 -> 850 | F13: =F10+F11+F12 -> 1450 | G13: =G10+G11+G12 -> 2200
A14: Peso da HoReCa/gourmet no volume | B14: % | C14: =IF(C13>0,C10/C13,0) -> 0.13333333 | D14: =IF(D13>0,D10/D13,0) -> 0.0925 | E14: =IF(E13>0,E10/E13,0) -> 0.15647059 | F14: =IF(F13>0,F10/F13,0) -> 0.18413793 | G14: =IF(G13>0,G10/G13,0) -> 0.18636364
A15: Quota da produção portuguesa | B15: % | C15: =C13/(Pressupostos!$C$74*1000) -> 0.00034285714 | D15: =D13/(Pressupostos!$C$74*1000) -> 0.0022857143 | E15: =E13/(Pressupostos!$C$74*1000) -> 0.0048571429 | F15: =F13/(Pressupostos!$C$74*1000) -> 0.0082857143 | G15: =G13/(Pressupostos!$C$74*1000) -> 0.012571429
A16: Lotes-tipo equivalentes | B16: n.º | C16: =C10/Pressupostos!$C$39+C11/Pressupostos!$C$46+C12/Pressupostos!$C$58 -> 2.1333333 | D16: =D10/Pressupostos!$C$39+D11/Pressupostos!$C$46+D12/Pressupostos!$C$58 -> 13.95 | E16: =E10/Pressupostos!$C$39+E11/Pressupostos!$C$46+E12/Pressupostos!$C$58 -> 30.55 | F16: =F10/Pressupostos!$C$39+F11/Pressupostos!$C$46+F12/Pressupostos!$C$58 -> 52.783333 | G16: =G10/Pressupostos!$C$39+G11/Pressupostos!$C$46+G12/Pressupostos!$C$58 -> 80.166667
A18: Água (modelo agente)
A19: Água | B19: paletes | C19: =Pressupostos!$C$255 -> 150 | D19: =Pressupostos!$D$255 -> 600 | E19: =Pressupostos!$E$255 -> 1000 | F19: =Pressupostos!$F$255 -> 1400 | G19: =Pressupostos!$G$255 -> 1800
A20: Água | B20: L | C20: =C19*Pressupostos!$C$76 -> 112500 | D20: =D19*Pressupostos!$C$76 -> 450000 | E20: =E19*Pressupostos!$C$76 -> 750000 | F20: =F19*Pressupostos!$C$76 -> 1050000 | G20: =G19*Pressupostos!$C$76 -> 1350000
A22: Café verde
A23: Café verde (0 antes do ano de início) | B23: t | C23: =IF(C6<Pressupostos!$G$28,0,Pressupostos!$C$261) -> 0 | D23: =IF(D6<Pressupostos!$G$28,0,Pressupostos!$D$261) -> 0 | E23: =IF(E6<Pressupostos!$G$28,0,Pressupostos!$E$261) -> 30 | F23: =IF(F6<Pressupostos!$G$28,0,Pressupostos!$F$261) -> 60 | G23: =IF(G6<Pressupostos!$G$28,0,Pressupostos!$G$261) -> 100
A25: Verificação para terceiros (banco parceiro)
A26: Carteira média financiada pelo banco parceiro | B26: € | C26: =Pressupostos!$C$267 -> 0 | D26: =Pressupostos!$D$267 -> 500000 | E26: =Pressupostos!$E$267 -> 1500000 | F26: =Pressupostos!$F$267 -> 3000000 | G26: =Pressupostos!$G$267 -> 5000000
A27: Azeite verificado para terceiros | B27: t | C27: =C26/(Pressupostos!$C$103*Pressupostos!$C$104)*Pressupostos!$C$100/1000 -> 0 | D27: =D26/(Pressupostos!$C$103*Pressupostos!$C$104)*Pressupostos!$C$100/1000 -> 457.14286 | E27: =E26/(Pressupostos!$C$103*Pressupostos!$C$104)*Pressupostos!$C$100/1000 -> 1371.4286 | F27: =F26/(Pressupostos!$C$103*Pressupostos!$C$104)*Pressupostos!$C$100/1000 -> 2742.8571 | G27: =G26/(Pressupostos!$C$103*Pressupostos!$C$104)*Pressupostos!$C$100/1000 -> 4571.4286

Sheet Receitas
A1: Receitas
A2: Receitas por fluxo, GMV, capital de lotes financiado e margem de contribuição por fluxo (cenário ativo).
A3: ="Cenário ativo: "&Pressupostos!$C$4&" · euros correntes, sem IVA" -> Cenário ativo: Base · euros correntes, sem IVA
A4: Rubrica | B4: Unidade | C4: 2027 | D4: 2028 | E4: 2029 | F4: 2030 | G4: 2031 | H4: Notas
A5: Receitas por fluxo (€)
A6: Vendas de azeite: HoReCa/gourmet | B6: € | C6: =Volumes!C10*1000*Custos!C8 -> 40680 | D6: =Volumes!D10*1000*Custos!D8 -> 188145 | E6: =Volumes!E10*1000*Custos!E8 -> 676305 | F6: =Volumes!F10*1000*Custos!F8 -> 1357695 | G6: =Volumes!G10*1000*Custos!G8 -> 2084850
A7: Vendas de azeite: distribuidores/exportação | B7: € | C7: =Volumes!C11*1000*Custos!C32 -> 226200 | D7: =Volumes!D11*1000*Custos!D32 -> 1579050 | E7: =Volumes!E11*1000*Custos!E32 -> 3118950 | F7: =Volumes!F11*1000*Custos!F32 -> 5146050 | G7: =Volumes!G11*1000*Custos!G32 -> 7786500
A8: Vendas de azeite: granel certificado | B8: € | C8: =Volumes!C12*1000*Custos!C56 -> 0 | D8: =Volumes!D12*1000*Custos!D56 -> 0 | E8: =Volumes!E12*1000*Custos!E56 -> 0 | F8: =Volumes!F12*1000*Custos!F56 -> 0 | G8: =Volumes!G12*1000*Custos!G56 -> 0
A9: Vendas de azeite | B9: € | C9: =C6+C7+C8 -> 266880 | D9: =D6+D7+D8 -> 1767195 | E9: =E6+E7+E8 -> 3795255 | F9: =F6+F7+F8 -> 6503745 | G9: =G6+G7+G8 -> 9871350
A10: Vendas de café verde | B10: € | C10: =Volumes!C23*1000*Pressupostos!$C$91 -> 0 | D10: =Volumes!D23*1000*Pressupostos!$C$91 -> 0 | E10: =Volumes!E23*1000*Pressupostos!$C$91 -> 235500 | F10: =Volumes!F23*1000*Pressupostos!$C$91 -> 471000 | G10: =Volumes!G23*1000*Pressupostos!$C$91 -> 785000
A11: Memo: GMV de água (faturado pelo engarrafador) | B11: € | C11: =Volumes!C20*Pressupostos!$C$78*(1-Pressupostos!$C$79) -> 40500 | D11: =Volumes!D20*Pressupostos!$C$78*(1-Pressupostos!$C$79) -> 162000 | E11: =Volumes!E20*Pressupostos!$C$78*(1-Pressupostos!$C$79) -> 270000 | F11: =Volumes!F20*Pressupostos!$C$78*(1-Pressupostos!$C$79) -> 378000 | G11: =Volumes!G20*Pressupostos!$C$78*(1-Pressupostos!$C$79) -> 486000
A12: Comissões de agente: água | B12: € | C12: =C11*Pressupostos!$G$27 -> 810 | D12: =D11*Pressupostos!$G$27 -> 3240 | E12: =E11*Pressupostos!$G$27 -> 5400 | F12: =F11*Pressupostos!$G$27 -> 7560 | G12: =G11*Pressupostos!$G$27 -> 9720
A13: Comissões de originação e verificação (terceiros) | B13: € | C13: =Volumes!C26*(Pressupostos!$C$99*Pressupostos!$C$100+Pressupostos!$C$101) -> 0 | D13: =Volumes!D26*(Pressupostos!$C$99*Pressupostos!$C$100+Pressupostos!$C$101) -> 10000 | E13: =Volumes!E26*(Pressupostos!$C$99*Pressupostos!$C$100+Pressupostos!$C$101) -> 30000 | F13: =Volumes!F26*(Pressupostos!$C$99*Pressupostos!$C$100+Pressupostos!$C$101) -> 60000 | G13: =Volumes!G26*(Pressupostos!$C$99*Pressupostos!$C$100+Pressupostos!$C$101) -> 100000
A14: Dados e índice | B14: € | C14: =Pressupostos!$C$273 -> 0 | D14: =Pressupostos!$D$273 -> 0 | E14: =Pressupostos!$E$273 -> 0 | F14: =Pressupostos!$F$273 -> 10000 | G14: =Pressupostos!$G$273 -> 30000
A15: Receita total | B15: € | C15: =C9+C10+C12+C13+C14 -> 267690 | D15: =D9+D10+D12+D13+D14 -> 1780435 | E15: =E9+E10+E12+E13+E14 -> 4066155 | F15: =F9+F10+F12+F13+F14 -> 7052305 | G15: =G9+G10+G12+G13+G14 -> 10796070
A17: GMV e capital de lotes (€)
A18: GMV total (azeite + café + água) | B18: € | C18: =C9+C10+C11 -> 307380 | D18: =D9+D10+D11 -> 1929195 | E18: =E9+E10+E11 -> 4300755 | F18: =F9+F10+F11 -> 7352745 | G18: =G9+G10+G11 -> 11142350
A19: Valor de compra dos lotes (granel + embalamento; café verde) | B19: € | C19: =Volumes!C10*1000*(Custos!C6+Custos!C9)+Volumes!C11*1000*(Custos!C30+Custos!C33)+Volumes!C12*1000*(Custos!C54+Custos!C57)+Volumes!C23*1000*Pressupostos!$C$90 -> 243800 | D19: =Volumes!D10*1000*(Custos!D6+Custos!D9)+Volumes!D11*1000*(Custos!D30+Custos!D33)+Volumes!D12*1000*(Custos!D54+Custos!D57)+Volumes!D23*1000*Pressupostos!$C$90 -> 1623700 | E19: =Volumes!E10*1000*(Custos!E6+Custos!E9)+Volumes!E11*1000*(Custos!E30+Custos!E33)+Volumes!E12*1000*(Custos!E54+Custos!E57)+Volumes!E23*1000*Pressupostos!$C$90 -> 3665800 | F19: =Volumes!F10*1000*(Custos!F6+Custos!F9)+Volumes!F11*1000*(Custos!F30+Custos!F33)+Volumes!F12*1000*(Custos!F54+Custos!F57)+Volumes!F23*1000*Pressupostos!$C$90 -> 6319200 | G19: =Volumes!G10*1000*(Custos!G6+Custos!G9)+Volumes!G11*1000*(Custos!G30+Custos!G33)+Volumes!G12*1000*(Custos!G54+Custos!G57)+Volumes!G23*1000*Pressupostos!$C$90 -> 9651000
A20: dos quais financiados por obrigações (capital financiado) | B20: € | C20: =C19*Pressupostos!$C$280 -> 0 | D20: =D19*Pressupostos!$D$280 -> 1461330 | E20: =E19*Pressupostos!$E$280 -> 3299220 | F20: =F19*Pressupostos!$F$280 -> 5687280 | G20: =G19*Pressupostos!$G$280 -> 8685900
A22: Margem de contribuição por fluxo (€)
A23: Azeite: HoReCa/gourmet | B23: € | C23: =Volumes!C10*1000*Custos!C25 -> 2727.5145 | D23: =Volumes!D10*1000*Custos!D25 -> 5610.3505 | E23: =Volumes!E10*1000*Custos!E25 -> 46169.051 | F23: =Volumes!F10*1000*Custos!F25 -> 96209.043 | G23: =Volumes!G10*1000*Custos!G25 -> 147736.73
A24: Azeite: distribuidores/exportação | B24: € | C24: =Volumes!C11*1000*Custos!C49 -> 5010.6274 | D24: =Volumes!D11*1000*Custos!D49 -> 18665.41 | E24: =Volumes!E11*1000*Custos!E49 -> 46051.842 | F24: =Volumes!F11*1000*Custos!F49 -> 79304.957 | G24: =Volumes!G11*1000*Custos!G49 -> 119996.51
A25: Azeite: granel certificado | B25: € | C25: =Volumes!C12*1000*Custos!C73 -> 0 | D25: =Volumes!D12*1000*Custos!D73 -> 0 | E25: =Volumes!E12*1000*Custos!E73 -> 0 | F25: =Volumes!F12*1000*Custos!F73 -> 0 | G25: =Volumes!G12*1000*Custos!G73 -> 0
A26: Azeite | B26: € | C26: =C23+C24+C25 -> 7738.1419 | D26: =D23+D24+D25 -> 24275.761 | E26: =E23+E24+E25 -> 92220.893 | F26: =F23+F24+F25 -> 175514 | G26: =G23+G24+G25 -> 267733.24
A27: Margem média do azeite | B27: €/kg | C27: =IF(Volumes!C13>0,C26/(Volumes!C13*1000),0) -> 0.12896903 | D27: =IF(Volumes!D13>0,D26/(Volumes!D13*1000),0) -> 0.060689402 | E27: =IF(Volumes!E13>0,E26/(Volumes!E13*1000),0) -> 0.10849517 | F27: =IF(Volumes!F13>0,F26/(Volumes!F13*1000),0) -> 0.12104414 | G27: =IF(Volumes!G13>0,G26/(Volumes!G13*1000),0) -> 0.12169693
A28: Margem do azeite em % das vendas de azeite | B28: % | C28: =IF(C9>0,C26/C9,0) -> 0.028994836 | D28: =IF(D9>0,D26/D9,0) -> 0.013736889 | E28: =IF(E9>0,E26/E9,0) -> 0.024298998 | F28: =IF(F9>0,F26/F9,0) -> 0.026986605 | G28: =IF(G9>0,G26/G9,0) -> 0.027122252
A29: Café: cupão por kg | B29: €/kg | C29: =Pressupostos!$C$286*Pressupostos!$C$90*(Pressupostos!$C$93+Pressupostos!$C$94-Pressupostos!$C$95)/365*Pressupostos!$C$280/Pressupostos!$G$31 -> 0 | D29: =Pressupostos!$D$286*Pressupostos!$C$90*(Pressupostos!$C$93+Pressupostos!$C$94-Pressupostos!$C$95)/365*Pressupostos!$D$280/Pressupostos!$G$31 -> 0.077671233 | E29: =Pressupostos!$E$286*Pressupostos!$C$90*(Pressupostos!$C$93+Pressupostos!$C$94-Pressupostos!$C$95)/365*Pressupostos!$E$280/Pressupostos!$G$31 -> 0.072816781 | F29: =Pressupostos!$F$286*Pressupostos!$C$90*(Pressupostos!$C$93+Pressupostos!$C$94-Pressupostos!$C$95)/365*Pressupostos!$F$280/Pressupostos!$G$31 -> 0.067962329 | G29: =Pressupostos!$G$286*Pressupostos!$C$90*(Pressupostos!$C$93+Pressupostos!$C$94-Pressupostos!$C$95)/365*Pressupostos!$G$280/Pressupostos!$G$31 -> 0.067962329
A30: Café verde | B30: € | C30: =Volumes!C23*1000*(Pressupostos!$C$91-Pressupostos!$C$90-Pressupostos!$C$92-C29-Pressupostos!$C$96*Pressupostos!$C$91-Pressupostos!$C$97-Pressupostos!$G$29*Pressupostos!$C$90) -> 0 | D30: =Volumes!D23*1000*(Pressupostos!$C$91-Pressupostos!$C$90-Pressupostos!$C$92-D29-Pressupostos!$C$96*Pressupostos!$C$91-Pressupostos!$C$97-Pressupostos!$G$29*Pressupostos!$C$90) -> 0 | E30: =Volumes!E23*1000*(Pressupostos!$C$91-Pressupostos!$C$90-Pressupostos!$C$92-E29-Pressupostos!$C$96*Pressupostos!$C$91-Pressupostos!$C$97-Pressupostos!$G$29*Pressupostos!$C$90) -> 16502.497 | F30: =Volumes!F23*1000*(Pressupostos!$C$91-Pressupostos!$C$90-Pressupostos!$C$92-F29-Pressupostos!$C$96*Pressupostos!$C$91-Pressupostos!$C$97-Pressupostos!$G$29*Pressupostos!$C$90) -> 33296.26 | G30: =Volumes!G23*1000*(Pressupostos!$C$91-Pressupostos!$C$90-Pressupostos!$C$92-G29-Pressupostos!$C$96*Pressupostos!$C$91-Pressupostos!$C$97-Pressupostos!$G$29*Pressupostos!$C$90) -> 55493.767
A31: Água (comissão) | B31: € | C31: =C12 -> 810 | D31: =D12 -> 3240 | E31: =E12 -> 5400 | F31: =F12 -> 7560 | G31: =G12 -> 9720
A32: Verificação para terceiros (líquida) | B32: € | C32: =C13-Custos!C89 -> 0 | D32: =D13-Custos!D89 -> 1771.4286 | E32: =E13-Custos!E89 -> 5314.2857 | F32: =F13-Custos!F89 -> 10628.571 | G32: =G13-Custos!G89 -> 17714.286
A33: Dados e índice | B33: € | C33: =C14 -> 0 | D33: =D14 -> 0 | E33: =E14 -> 0 | F33: =F14 -> 10000 | G33: =G14 -> 30000
A34: Margem de contribuição total | B34: € | C34: =C26+C30+C31+C32+C33 -> 8548.1419 | D34: =D26+D30+D31+D32+D33 -> 29287.189 | E34: =E26+E30+E31+E32+E33 -> 119437.67 | F34: =F26+F30+F31+F32+F33 -> 236998.83 | G34: =G26+G30+G31+G32+G33 -> 380661.3

Sheet Pessoal
A1: Pessoal
A2: Equipa por função; salário bruto anual com 14 meses, TSU de 23,75% + 2% e subsídio de refeição (cenário ativo).
A3: ="Cenário ativo: "&Pressupostos!$C$4&" · euros correntes, sem IVA" -> Cenário ativo: Base · euros correntes, sem IVA
A4: Rubrica | B4: Unidade | C4: 2027 | D4: 2028 | E4: 2029 | F4: 2030 | G4: 2031 | H4: Notas
A5: FTE por função
A6: CEO / comercial (fundador) | B6: FTE | C6: =Pressupostos!$C$318 -> 1 | D6: =Pressupostos!$D$318 -> 1 | E6: =Pressupostos!$E$318 -> 1 | F6: =Pressupostos!$F$318 -> 1 | G6: =Pressupostos!$G$318 -> 1
A7: CTO (fundador) | B7: FTE | C7: =Pressupostos!$C$324 -> 1 | D7: =Pressupostos!$D$324 -> 1 | E7: =Pressupostos!$E$324 -> 1 | F7: =Pressupostos!$F$324 -> 1 | G7: =Pressupostos!$G$324 -> 1
A8: Engenheiro(a) de software | B8: FTE | C8: =Pressupostos!$C$330 -> 1 | D8: =Pressupostos!$D$330 -> 1 | E8: =Pressupostos!$E$330 -> 2 | F8: =Pressupostos!$F$330 -> 2 | G8: =Pressupostos!$G$330 -> 2
A9: Responsável de Risco e Tesouraria | B9: FTE | C9: =Pressupostos!$C$336 -> 1 | D9: =Pressupostos!$D$336 -> 1 | E9: =Pressupostos!$E$336 -> 1 | F9: =Pressupostos!$F$336 -> 1 | G9: =Pressupostos!$G$336 -> 1
A10: Compliance / AML | B10: FTE | C10: =Pressupostos!$C$342 -> 0.5 | D10: =Pressupostos!$D$342 -> 1 | E10: =Pressupostos!$E$342 -> 1 | F10: =Pressupostos!$F$342 -> 1 | G10: =Pressupostos!$G$342 -> 1
A11: Operações e supply | B11: FTE | C11: =Pressupostos!$C$348 -> 1 | D11: =Pressupostos!$D$348 -> 1 | E11: =Pressupostos!$E$348 -> 1 | F11: =Pressupostos!$F$348 -> 2 | G11: =Pressupostos!$G$348 -> 2
A12: Técnico(a) de qualidade do azeite | B12: FTE | C12: =Pressupostos!$C$354 -> 0.5 | D12: =Pressupostos!$D$354 -> 1 | E12: =Pressupostos!$E$354 -> 1 | F12: =Pressupostos!$F$354 -> 1 | G12: =Pressupostos!$G$354 -> 1
A13: Gestor(a) de conta B2B (~400 contas) | B13: FTE | C13: =Pressupostos!$C$360 -> 1 | D13: =Pressupostos!$D$360 -> 1 | E13: =Pressupostos!$E$360 -> 2 | F13: =Pressupostos!$F$360 -> 3 | G13: =Pressupostos!$G$360 -> 5
A14: Controller financeiro | B14: FTE | C14: =Pressupostos!$C$366 -> 0 | D14: =Pressupostos!$D$366 -> 0 | E14: =Pressupostos!$E$366 -> 0 | F14: =Pressupostos!$F$366 -> 1 | G14: =Pressupostos!$G$366 -> 1
A15: Analista de dados/produto | B15: FTE | C15: =Pressupostos!$C$372 -> 0 | D15: =Pressupostos!$D$372 -> 0 | E15: =Pressupostos!$E$372 -> 0 | F15: =Pressupostos!$F$372 -> 0 | G15: =Pressupostos!$G$372 -> 1
A16: Assistente de operações | B16: FTE | C16: =Pressupostos!$C$378 -> 0 | D16: =Pressupostos!$D$378 -> 0 | E16: =Pressupostos!$E$378 -> 1 | F16: =Pressupostos!$F$378 -> 1 | G16: =Pressupostos!$G$378 -> 1
A17: Trader de granel e exportação | B17: FTE | C17: =Pressupostos!$C$384 -> 0 | D17: =Pressupostos!$D$384 -> 0 | E17: =Pressupostos!$E$384 -> 0 | F17: =Pressupostos!$F$384 -> 0 | G17: =Pressupostos!$G$384 -> 0
A18: Total de FTE | B18: FTE | C18: =C6+C7+C8+C9+C10+C11+C12+C13+C14+C15+C16+C17 -> 7 | D18: =D6+D7+D8+D9+D10+D11+D12+D13+D14+D15+D16+D17 -> 8 | E18: =E6+E7+E8+E9+E10+E11+E12+E13+E14+E15+E16+E17 -> 11 | F18: =F6+F7+F8+F9+F10+F11+F12+F13+F14+F15+F16+F17 -> 14 | G18: =G6+G7+G8+G9+G10+G11+G12+G13+G14+G15+G16+G17 -> 17
A20: Custo salarial bruto (€, 14 meses, com variável e atualização)
A21: CEO / comercial (fundador) | B21: € | C21: =C6*Pressupostos!$C$129*(1+Pressupostos!$C$125)^0*(1+Pressupostos!$C$130)*Pressupostos!$C$126 -> 43998 | D21: =D6*Pressupostos!$C$129*(1+Pressupostos!$C$125)^1*(1+Pressupostos!$C$130) -> 61800 | E21: =E6*Pressupostos!$C$129*(1+Pressupostos!$C$125)^2*(1+Pressupostos!$C$130) -> 63654 | F21: =F6*Pressupostos!$C$129*(1+Pressupostos!$C$125)^3*(1+Pressupostos!$C$130) -> 65563.62 | G21: =G6*Pressupostos!$C$129*(1+Pressupostos!$C$125)^4*(1+Pressupostos!$C$130) -> 67530.529
A22: CTO (fundador) | B22: € | C22: =C7*Pressupostos!$C$131*(1+Pressupostos!$C$125)^0*(1+Pressupostos!$C$132)*Pressupostos!$C$126 -> 47664.5 | D22: =D7*Pressupostos!$C$131*(1+Pressupostos!$C$125)^1*(1+Pressupostos!$C$132) -> 66950 | E22: =E7*Pressupostos!$C$131*(1+Pressupostos!$C$125)^2*(1+Pressupostos!$C$132) -> 68958.5 | F22: =F7*Pressupostos!$C$131*(1+Pressupostos!$C$125)^3*(1+Pressupostos!$C$132) -> 71027.255 | G22: =G7*Pressupostos!$C$131*(1+Pressupostos!$C$125)^4*(1+Pressupostos!$C$132) -> 73158.073
A23: Engenheiro(a) de software | B23: € | C23: =C8*Pressupostos!$C$133*(1+Pressupostos!$C$125)^0*(1+Pressupostos!$C$134) -> 45000 | D23: =D8*Pressupostos!$C$133*(1+Pressupostos!$C$125)^1*(1+Pressupostos!$C$134) -> 46350 | E23: =E8*Pressupostos!$C$133*(1+Pressupostos!$C$125)^2*(1+Pressupostos!$C$134) -> 95481 | F23: =F8*Pressupostos!$C$133*(1+Pressupostos!$C$125)^3*(1+Pressupostos!$C$134) -> 98345.43 | G23: =G8*Pressupostos!$C$133*(1+Pressupostos!$C$125)^4*(1+Pressupostos!$C$134) -> 101295.79
A24: Responsável de Risco e Tesouraria | B24: € | C24: =C9*Pressupostos!$C$135*(1+Pressupostos!$C$125)^0*(1+Pressupostos!$C$136) -> 60000 | D24: =D9*Pressupostos!$C$135*(1+Pressupostos!$C$125)^1*(1+Pressupostos!$C$136) -> 61800 | E24: =E9*Pressupostos!$C$135*(1+Pressupostos!$C$125)^2*(1+Pressupostos!$C$136) -> 63654 | F24: =F9*Pressupostos!$C$135*(1+Pressupostos!$C$125)^3*(1+Pressupostos!$C$136) -> 65563.62 | G24: =G9*Pressupostos!$C$135*(1+Pressupostos!$C$125)^4*(1+Pressupostos!$C$136) -> 67530.529
A25: Compliance / AML | B25: € | C25: =C10*Pressupostos!$C$137*(1+Pressupostos!$C$125)^0*(1+Pressupostos!$C$138) -> 22500 | D25: =D10*Pressupostos!$C$137*(1+Pressupostos!$C$125)^1*(1+Pressupostos!$C$138) -> 46350 | E25: =E10*Pressupostos!$C$137*(1+Pressupostos!$C$125)^2*(1+Pressupostos!$C$138) -> 47740.5 | F25: =F10*Pressupostos!$C$137*(1+Pressupostos!$C$125)^3*(1+Pressupostos!$C$138) -> 49172.715 | G25: =G10*Pressupostos!$C$137*(1+Pressupostos!$C$125)^4*(1+Pressupostos!$C$138) -> 50647.896
A26: Operações e supply | B26: € | C26: =C11*Pressupostos!$C$139*(1+Pressupostos!$C$125)^0*(1+Pressupostos!$C$140) -> 38000 | D26: =D11*Pressupostos!$C$139*(1+Pressupostos!$C$125)^1*(1+Pressupostos!$C$140) -> 39140 | E26: =E11*Pressupostos!$C$139*(1+Pressupostos!$C$125)^2*(1+Pressupostos!$C$140) -> 40314.2 | F26: =F11*Pressupostos!$C$139*(1+Pressupostos!$C$125)^3*(1+Pressupostos!$C$140) -> 83047.252 | G26: =G11*Pressupostos!$C$139*(1+Pressupostos!$C$125)^4*(1+Pressupostos!$C$140) -> 85538.67
A27: Técnico(a) de qualidade do azeite | B27: € | C27: =C12*Pressupostos!$C$141*(1+Pressupostos!$C$125)^0*(1+Pressupostos!$C$142) -> 16000 | D27: =D12*Pressupostos!$C$141*(1+Pressupostos!$C$125)^1*(1+Pressupostos!$C$142) -> 32960 | E27: =E12*Pressupostos!$C$141*(1+Pressupostos!$C$125)^2*(1+Pressupostos!$C$142) -> 33948.8 | F27: =F12*Pressupostos!$C$141*(1+Pressupostos!$C$125)^3*(1+Pressupostos!$C$142) -> 34967.264 | G27: =G12*Pressupostos!$C$141*(1+Pressupostos!$C$125)^4*(1+Pressupostos!$C$142) -> 36016.282
A28: Gestor(a) de conta B2B (~400 contas) | B28: € | C28: =C13*Pressupostos!$C$143*(1+Pressupostos!$C$125)^0*(1+Pressupostos!$C$144) -> 34500 | D28: =D13*Pressupostos!$C$143*(1+Pressupostos!$C$125)^1*(1+Pressupostos!$C$144) -> 35535 | E28: =E13*Pressupostos!$C$143*(1+Pressupostos!$C$125)^2*(1+Pressupostos!$C$144) -> 73202.1 | F28: =F13*Pressupostos!$C$143*(1+Pressupostos!$C$125)^3*(1+Pressupostos!$C$144) -> 113097.24 | G28: =G13*Pressupostos!$C$143*(1+Pressupostos!$C$125)^4*(1+Pressupostos!$C$144) -> 194150.27
A29: Controller financeiro | B29: € | C29: =C14*Pressupostos!$C$145*(1+Pressupostos!$C$125)^0*(1+Pressupostos!$C$146) -> 0 | D29: =D14*Pressupostos!$C$145*(1+Pressupostos!$C$125)^1*(1+Pressupostos!$C$146) -> 0 | E29: =E14*Pressupostos!$C$145*(1+Pressupostos!$C$125)^2*(1+Pressupostos!$C$146) -> 0 | F29: =F14*Pressupostos!$C$145*(1+Pressupostos!$C$125)^3*(1+Pressupostos!$C$146) -> 49172.715 | G29: =G14*Pressupostos!$C$145*(1+Pressupostos!$C$125)^4*(1+Pressupostos!$C$146) -> 50647.896
A30: Analista de dados/produto | B30: € | C30: =C15*Pressupostos!$C$147*(1+Pressupostos!$C$125)^0*(1+Pressupostos!$C$148) -> 0 | D30: =D15*Pressupostos!$C$147*(1+Pressupostos!$C$125)^1*(1+Pressupostos!$C$148) -> 0 | E30: =E15*Pressupostos!$C$147*(1+Pressupostos!$C$125)^2*(1+Pressupostos!$C$148) -> 0 | F30: =F15*Pressupostos!$C$147*(1+Pressupostos!$C$125)^3*(1+Pressupostos!$C$148) -> 0 | G30: =G15*Pressupostos!$C$147*(1+Pressupostos!$C$125)^4*(1+Pressupostos!$C$148) -> 45020.352
A31: Assistente de operações | B31: € | C31: =C16*Pressupostos!$C$149*(1+Pressupostos!$C$125)^0*(1+Pressupostos!$C$150) -> 0 | D31: =D16*Pressupostos!$C$149*(1+Pressupostos!$C$125)^1*(1+Pressupostos!$C$150) -> 0 | E31: =E16*Pressupostos!$C$149*(1+Pressupostos!$C$125)^2*(1+Pressupostos!$C$150) -> 25461.6 | F31: =F16*Pressupostos!$C$149*(1+Pressupostos!$C$125)^3*(1+Pressupostos!$C$150) -> 26225.448 | G31: =G16*Pressupostos!$C$149*(1+Pressupostos!$C$125)^4*(1+Pressupostos!$C$150) -> 27012.211
A32: Trader de granel e exportação | B32: € | C32: =C17*Pressupostos!$C$151*(1+Pressupostos!$C$125)^0*(1+Pressupostos!$C$152) -> 0 | D32: =D17*Pressupostos!$C$151*(1+Pressupostos!$C$125)^1*(1+Pressupostos!$C$152) -> 0 | E32: =E17*Pressupostos!$C$151*(1+Pressupostos!$C$125)^2*(1+Pressupostos!$C$152) -> 0 | F32: =F17*Pressupostos!$C$151*(1+Pressupostos!$C$125)^3*(1+Pressupostos!$C$152) -> 0 | G32: =G17*Pressupostos!$C$151*(1+Pressupostos!$C$125)^4*(1+Pressupostos!$C$152) -> 0
A33: Salários brutos | B33: € | C33: =C21+C22+C23+C24+C25+C26+C27+C28+C29+C30+C31+C32 -> 307662.5 | D33: =D21+D22+D23+D24+D25+D26+D27+D28+D29+D30+D31+D32 -> 390885 | E33: =E21+E22+E23+E24+E25+E26+E27+E28+E29+E30+E31+E32 -> 512414.7 | F33: =F21+F22+F23+F24+F25+F26+F27+F28+F29+F30+F31+F32 -> 656182.56 | G33: =G21+G22+G23+G24+G25+G26+G27+G28+G29+G30+G31+G32 -> 798548.5
A34: TSU e outros encargos | B34: € | C34: =C33*(Pressupostos!$C$122+Pressupostos!$C$123) -> 79223.094 | D34: =D33*(Pressupostos!$C$122+Pressupostos!$C$123) -> 100652.89 | E34: =E33*(Pressupostos!$C$122+Pressupostos!$C$123) -> 131946.79 | F34: =F33*(Pressupostos!$C$122+Pressupostos!$C$123) -> 168967.01 | G34: =G33*(Pressupostos!$C$122+Pressupostos!$C$123) -> 205626.24
A35: Subsídio de refeição | B35: € | C35: =C18*Pressupostos!$C$124*(1+Pressupostos!$C$125)^0 -> 14000 | D35: =D18*Pressupostos!$C$124*(1+Pressupostos!$C$125)^1 -> 16480 | E35: =E18*Pressupostos!$C$124*(1+Pressupostos!$C$125)^2 -> 23339.8 | F35: =F18*Pressupostos!$C$124*(1+Pressupostos!$C$125)^3 -> 30596.356 | G35: =G18*Pressupostos!$C$124*(1+Pressupostos!$C$125)^4 -> 38267.3
A36: Custo total com pessoal | B36: € | C36: =C33+C34+C35 -> 400885.59 | D36: =D33+D34+D35 -> 508017.89 | E36: =E33+E34+E35 -> 667701.29 | F36: =F33+F34+F35 -> 855745.93 | G36: =G33+G34+G35 -> 1042442
A37: Custo médio por FTE | B37: € | C37: =IF(C18>0,C36/C18,0) -> 57269.371 | D37: =IF(D18>0,D36/D18,0) -> 63502.236 | E37: =IF(E18>0,E36/E18,0) -> 60700.117 | F37: =IF(F18>0,F36/F18,0) -> 61124.709 | G37: =IF(G18>0,G36/G18,0) -> 61320.12
A39: Tabela salarial (inputs em Pressupostos; valores de 2027)
A40: Função | B40: Fundador? | C40: Salário anual (14 meses) | D40: Salário mensal (÷ 14) | E40: Variável | F40: Custo anual c/ encargos (1 FTE)
A41: CEO / comercial (fundador) | B41: sim (60% até ao gate) | C41: =Pressupostos!$C$129 -> 60000 | D41: =C41/14 -> 4285.7143 | E41: =Pressupostos!$C$130 -> 0 | F41: =C41*(1+E41)*(1+Pressupostos!$C$122+Pressupostos!$C$123)+Pressupostos!$C$124 -> 77450
A42: CTO (fundador) | B42: sim (60% até ao gate) | C42: =Pressupostos!$C$131 -> 65000 | D42: =C42/14 -> 4642.8571 | E42: =Pressupostos!$C$132 -> 0 | F42: =C42*(1+E42)*(1+Pressupostos!$C$122+Pressupostos!$C$123)+Pressupostos!$C$124 -> 83737.5
A43: Engenheiro(a) de software | B43: não | C43: =Pressupostos!$C$133 -> 45000 | D43: =C43/14 -> 3214.2857 | E43: =Pressupostos!$C$134 -> 0 | F43: =C43*(1+E43)*(1+Pressupostos!$C$122+Pressupostos!$C$123)+Pressupostos!$C$124 -> 58587.5
A44: Responsável de Risco e Tesouraria | B44: não | C44: =Pressupostos!$C$135 -> 60000 | D44: =C44/14 -> 4285.7143 | E44: =Pressupostos!$C$136 -> 0 | F44: =C44*(1+E44)*(1+Pressupostos!$C$122+Pressupostos!$C$123)+Pressupostos!$C$124 -> 77450
A45: Compliance / AML | B45: não | C45: =Pressupostos!$C$137 -> 45000 | D45: =C45/14 -> 3214.2857 | E45: =Pressupostos!$C$138 -> 0 | F45: =C45*(1+E45)*(1+Pressupostos!$C$122+Pressupostos!$C$123)+Pressupostos!$C$124 -> 58587.5
A46: Operações e supply | B46: não | C46: =Pressupostos!$C$139 -> 38000 | D46: =C46/14 -> 2714.2857 | E46: =Pressupostos!$C$140 -> 0 | F46: =C46*(1+E46)*(1+Pressupostos!$C$122+Pressupostos!$C$123)+Pressupostos!$C$124 -> 49785
A47: Técnico(a) de qualidade do azeite | B47: não | C47: =Pressupostos!$C$141 -> 32000 | D47: =C47/14 -> 2285.7143 | E47: =Pressupostos!$C$142 -> 0 | F47: =C47*(1+E47)*(1+Pressupostos!$C$122+Pressupostos!$C$123)+Pressupostos!$C$124 -> 42240
A48: Gestor(a) de conta B2B (~400 contas) | B48: não | C48: =Pressupostos!$C$143 -> 30000 | D48: =C48/14 -> 2142.8571 | E48: =Pressupostos!$C$144 -> 0.15 | F48: =C48*(1+E48)*(1+Pressupostos!$C$122+Pressupostos!$C$123)+Pressupostos!$C$124 -> 45383.75
A49: Controller financeiro | B49: não | C49: =Pressupostos!$C$145 -> 45000 | D49: =C49/14 -> 3214.2857 | E49: =Pressupostos!$C$146 -> 0 | F49: =C49*(1+E49)*(1+Pressupostos!$C$122+Pressupostos!$C$123)+Pressupostos!$C$124 -> 58587.5
A50: Analista de dados/produto | B50: não | C50: =Pressupostos!$C$147 -> 40000 | D50: =C50/14 -> 2857.1429 | E50: =Pressupostos!$C$148 -> 0 | F50: =C50*(1+E50)*(1+Pressupostos!$C$122+Pressupostos!$C$123)+Pressupostos!$C$124 -> 52300
A51: Assistente de operações | B51: não | C51: =Pressupostos!$C$149 -> 24000 | D51: =C51/14 -> 1714.2857 | E51: =Pressupostos!$C$150 -> 0 | F51: =C51*(1+E51)*(1+Pressupostos!$C$122+Pressupostos!$C$123)+Pressupostos!$C$124 -> 32180
A52: Trader de granel e exportação | B52: não | C52: =Pressupostos!$C$151 -> 45000 | D52: =C52/14 -> 3214.2857 | E52: =Pressupostos!$C$152 -> 0.15 | F52: =C52*(1+E52)*(1+Pressupostos!$C$122+Pressupostos!$C$123)+Pressupostos!$C$124 -> 67075.625

Sheet Custos
A1: Custos
A2: Economia por kg de cada canal, custos diretos, opex não salarial, capex e amortizações (cenário ativo).
A3: ="Cenário ativo: "&Pressupostos!$C$4&" · euros correntes, sem IVA" -> Cenário ativo: Base · euros correntes, sem IVA
A4: Rubrica | B4: Unidade | C4: 2027 | D4: 2028 | E4: 2029 | F4: 2030 | G4: 2031 | H4: Notas
A5: Economia por kg: HoReCa/gourmet
A6: Preço ao produtor (índice + prémio de origem) | B6: €/kg | C6: =Pressupostos!$G$10+Pressupostos!$G$11 -> 3.6 | D6: =Pressupostos!$G$10+Pressupostos!$G$11 -> 3.6 | E6: =Pressupostos!$G$10+Pressupostos!$G$11 -> 3.6 | F6: =Pressupostos!$G$10+Pressupostos!$G$11 -> 3.6 | G6: =Pressupostos!$G$10+Pressupostos!$G$11 -> 3.6
A7: Preço de referência do comprador | B7: €/kg | C7: =Pressupostos!$G$15 -> 5.65 | D7: =Pressupostos!$G$15 -> 5.65 | E7: =Pressupostos!$G$15 -> 5.65 | F7: =Pressupostos!$G$15 -> 5.65 | G7: =Pressupostos!$G$15 -> 5.65
A8: Preço de venda Sprout (referência − desconto) | B8: €/kg | C8: =C7*(1-Pressupostos!$G$16) -> 5.085 | D8: =D7*(1-Pressupostos!$G$16) -> 5.085 | E8: =E7*(1-Pressupostos!$G$16) -> 5.085 | F8: =F7*(1-Pressupostos!$G$16) -> 5.085 | G8: =G7*(1-Pressupostos!$G$16) -> 5.085
A9: Embalamento | B9: €/kg | C9: =Pressupostos!$C$37 -> 0.55 | D9: =Pressupostos!$C$37 -> 0.55 | E9: =Pressupostos!$C$37 -> 0.55 | F9: =Pressupostos!$C$37 -> 0.55 | G9: =Pressupostos!$C$37 -> 0.55
A10: Logística | B10: €/kg | C10: =Pressupostos!$C$236 -> 0.3 | D10: =Pressupostos!$D$236 -> 0.3 | E10: =Pressupostos!$E$236 -> 0.28 | F10: =Pressupostos!$F$236 -> 0.27 | G10: =Pressupostos!$G$236 -> 0.27
A11: Armazém logístico (3PL) e picking | B11: €/kg | C11: =Pressupostos!$C$38 -> 0.06 | D11: =Pressupostos!$C$38 -> 0.06 | E11: =Pressupostos!$C$38 -> 0.06 | F11: =Pressupostos!$C$38 -> 0.06 | G11: =Pressupostos!$C$38 -> 0.06
A12: Stock médio | B12: dias | C12: =Pressupostos!$C$242 -> 180 | D12: =Pressupostos!$D$242 -> 180 | E12: =Pressupostos!$E$242 -> 45 | F12: =Pressupostos!$F$242 -> 45 | G12: =Pressupostos!$G$242 -> 45
A13: Prazo médio de recebimento | B13: dias | C13: =Pressupostos!$G$17 -> 35 | D13: =Pressupostos!$G$17 -> 35 | E13: =Pressupostos!$G$17 -> 35 | F13: =Pressupostos!$G$17 -> 35 | G13: =Pressupostos!$G$17 -> 35
A14: Armazenagem | B14: €/kg | C14: =Pressupostos!$C$64*C12/30/1000 -> 0.024 | D14: =Pressupostos!$C$64*D12/30/1000 -> 0.024 | E14: =Pressupostos!$C$64*E12/30/1000 -> 0.006 | F14: =Pressupostos!$C$64*F12/30/1000 -> 0.006 | G14: =Pressupostos!$C$64*G12/30/1000 -> 0.006
A15: Seguro do stock | B15: €/kg | C15: =C6*Pressupostos!$C$65*C12/365 -> 0.0035506849 | D15: =D6*Pressupostos!$C$65*D12/365 -> 0.0035506849 | E15: =E6*Pressupostos!$C$65*E12/365 -> 0.00088767123 | F15: =F6*Pressupostos!$C$65*F12/365 -> 0.00088767123 | G15: =G6*Pressupostos!$C$65*G12/365 -> 0.00088767123
A16: Análises (testes de qualidade) | B16: €/kg | C16: =Pressupostos!$C$40*Pressupostos!$C$66/(Pressupostos!$C$39*1000) -> 0.03 | D16: =Pressupostos!$C$40*Pressupostos!$C$66/(Pressupostos!$C$39*1000) -> 0.03 | E16: =Pressupostos!$C$40*Pressupostos!$C$66/(Pressupostos!$C$39*1000) -> 0.03 | F16: =Pressupostos!$C$40*Pressupostos!$C$66/(Pressupostos!$C$39*1000) -> 0.03 | G16: =Pressupostos!$C$40*Pressupostos!$C$66/(Pressupostos!$C$39*1000) -> 0.03
A17: Perdas físicas | B17: €/kg | C17: =Pressupostos!$C$67*C6 -> 0.018 | D17: =Pressupostos!$C$67*D6 -> 0.018 | E17: =Pressupostos!$C$67*E6 -> 0.018 | F17: =Pressupostos!$C$67*F6 -> 0.018 | G17: =Pressupostos!$C$67*G6 -> 0.018
A18: Desclassificação esperada | B18: €/kg | C18: =Pressupostos!$C$68*Pressupostos!$C$69*C12/90 -> 0.018 | D18: =Pressupostos!$C$68*Pressupostos!$C$69*D12/90 -> 0.018 | E18: =Pressupostos!$C$68*Pressupostos!$C$69*E12/90 -> 0.0045 | F18: =Pressupostos!$C$68*Pressupostos!$C$69*F12/90 -> 0.0045 | G18: =Pressupostos!$C$68*Pressupostos!$C$69*G12/90 -> 0.0045
A19: Custódia (collateral manager) | B19: €/kg | C19: =Pressupostos!$C$41/(Pressupostos!$C$39*1000) -> 0.1 | D19: =Pressupostos!$C$41/(Pressupostos!$C$39*1000) -> 0.1 | E19: =Pressupostos!$C$41/(Pressupostos!$C$39*1000) -> 0.1 | F19: =Pressupostos!$C$41/(Pressupostos!$C$39*1000) -> 0.1 | G19: =Pressupostos!$C$41/(Pressupostos!$C$39*1000) -> 0.1
A20: Pagamentos bancários | B20: €/kg | C20: =Pressupostos!$C$42 -> 0.01 | D20: =Pressupostos!$C$42 -> 0.01 | E20: =Pressupostos!$C$42 -> 0.01 | F20: =Pressupostos!$C$42 -> 0.01 | G20: =Pressupostos!$C$42 -> 0.01
A21: Provisão de crédito | B21: €/kg | C21: =Pressupostos!$G$18*C8 -> 0.03051 | D21: =Pressupostos!$G$18*D8 -> 0.03051 | E21: =Pressupostos!$G$18*E8 -> 0.03051 | F21: =Pressupostos!$G$18*F8 -> 0.03051 | G21: =Pressupostos!$G$18*G8 -> 0.03051
A22: Cobertura de preço explícita (sem futuros de azeite) | B22: €/kg | C22: =Pressupostos!$C$71*C8 -> 0 | D22: =Pressupostos!$C$71*D8 -> 0 | E22: =Pressupostos!$C$71*E8 -> 0 | F22: =Pressupostos!$C$71*F8 -> 0 | G22: =Pressupostos!$C$71*G8 -> 0
A23: Cupão das obrigações (financiamento do stock) | B23: €/kg | C23: =Pressupostos!$C$286*(C6+C9)*(C12+C13-Pressupostos!$C$70)/365*Pressupostos!$C$280/Pressupostos!$G$31 -> 0 | D23: =Pressupostos!$D$286*(D6+D9)*(D12+D13-Pressupostos!$C$70)/365*Pressupostos!$D$280/Pressupostos!$G$31 -> 0.18930822 | E23: =Pressupostos!$E$286*(E6+E9)*(E12+E13-Pressupostos!$C$70)/365*Pressupostos!$E$280/Pressupostos!$G$31 -> 0.04796661 | F23: =Pressupostos!$F$286*(F6+F9)*(F12+F13-Pressupostos!$C$70)/365*Pressupostos!$F$280/Pressupostos!$G$31 -> 0.044768836 | G23: =Pressupostos!$G$286*(G6+G9)*(G12+G13-Pressupostos!$C$70)/365*Pressupostos!$G$280/Pressupostos!$G$31 -> 0.044768836
A24: Custo direto total | B24: €/kg | C24: =C6+C9+C10+C11+C14+C15+C16+C17+C18+C19+C20+C21+C22+C23 -> 4.7440607 | D24: =D6+D9+D10+D11+D14+D15+D16+D17+D18+D19+D20+D21+D22+D23 -> 4.9333689 | E24: =E6+E9+E10+E11+E14+E15+E16+E17+E18+E19+E20+E21+E22+E23 -> 4.7378643 | F24: =F6+F9+F10+F11+F14+F15+F16+F17+F18+F19+F20+F21+F22+F23 -> 4.7246665 | G24: =G6+G9+G10+G11+G14+G15+G16+G17+G18+G19+G20+G21+G22+G23 -> 4.7246665
A25: Margem de contribuição | B25: €/kg | C25: =C8-C24 -> 0.34093932 | D25: =D8-D24 -> 0.1516311 | E25: =E8-E24 -> 0.34713572 | F25: =F8-F24 -> 0.36033349 | G25: =G8-G24 -> 0.36033349
A26: Margem de contribuição em % do preço | B26: % | C26: =IF(C8>0,C25/C8,0) -> 0.067048046 | D26: =IF(D8>0,D25/D8,0) -> 0.029819291 | E26: =IF(E8>0,E25/E8,0) -> 0.068266611 | F26: =IF(F8>0,F25/F8,0) -> 0.070862044 | G26: =IF(G8>0,G25/G8,0) -> 0.070862044
A27: Capital de giro por kg vendido | B27: €/kg | C27: =(C6+C9)*(C12-Pressupostos!$C$70)/365+C8*C13/365 -> 2.1930822 | D27: =(D6+D9)*(D12-Pressupostos!$C$70)/365+D8*D13/365 -> 2.1930822 | E27: =(E6+E9)*(E12-Pressupostos!$C$70)/365+E8*E13/365 -> 0.65815068 | F27: =(F6+F9)*(F12-Pressupostos!$C$70)/365+F8*F13/365 -> 0.65815068 | G27: =(G6+G9)*(G12-Pressupostos!$C$70)/365+G8*G13/365 -> 0.65815068
A29: Economia por kg: distribuidores/exportação
A30: Preço ao produtor (índice + prémio de origem) | B30: €/kg | C30: =Pressupostos!$G$10+Pressupostos!$G$12 -> 3.6 | D30: =Pressupostos!$G$10+Pressupostos!$G$12 -> 3.6 | E30: =Pressupostos!$G$10+Pressupostos!$G$12 -> 3.6 | F30: =Pressupostos!$G$10+Pressupostos!$G$12 -> 3.6 | G30: =Pressupostos!$G$10+Pressupostos!$G$12 -> 3.6
A31: Preço de referência do comprador | B31: €/kg | C31: =Pressupostos!$G$20+Pressupostos!$G$21 -> 4.35 | D31: =Pressupostos!$G$20+Pressupostos!$G$21 -> 4.35 | E31: =Pressupostos!$G$20+Pressupostos!$G$21 -> 4.35 | F31: =Pressupostos!$G$20+Pressupostos!$G$21 -> 4.35 | G31: =Pressupostos!$G$20+Pressupostos!$G$21 -> 4.35
A32: Preço de venda Sprout (referência − desconto) | B32: €/kg | C32: =C31*(1-Pressupostos!$G$22) -> 4.35 | D32: =D31*(1-Pressupostos!$G$22) -> 4.35 | E32: =E31*(1-Pressupostos!$G$22) -> 4.35 | F32: =F31*(1-Pressupostos!$G$22) -> 4.35 | G32: =G31*(1-Pressupostos!$G$22) -> 4.35
A33: Embalamento | B33: €/kg | C33: =Pressupostos!$C$44 -> 0.45 | D33: =Pressupostos!$C$44 -> 0.45 | E33: =Pressupostos!$C$44 -> 0.45 | F33: =Pressupostos!$C$44 -> 0.45 | G33: =Pressupostos!$C$44 -> 0.45
A34: Logística | B34: €/kg | C34: =Pressupostos!$C$248 -> 0.1 | D34: =Pressupostos!$D$248 -> 0.1 | E34: =Pressupostos!$E$248 -> 0.09 | F34: =Pressupostos!$F$248 -> 0.09 | G34: =Pressupostos!$G$248 -> 0.09
A35: Armazém logístico (3PL) e picking | B35: €/kg | C35: =Pressupostos!$C$45 -> 0 | D35: =Pressupostos!$C$45 -> 0 | E35: =Pressupostos!$C$45 -> 0 | F35: =Pressupostos!$C$45 -> 0 | G35: =Pressupostos!$C$45 -> 0
A36: Stock médio | B36: dias | C36: =Pressupostos!$G$23 -> 30 | D36: =Pressupostos!$G$23 -> 30 | E36: =Pressupostos!$G$23 -> 30 | F36: =Pressupostos!$G$23 -> 30 | G36: =Pressupostos!$G$23 -> 30
A37: Prazo médio de recebimento | B37: dias | C37: =Pressupostos!$G$24 -> 45 | D37: =Pressupostos!$G$24 -> 45 | E37: =Pressupostos!$G$24 -> 45 | F37: =Pressupostos!$G$24 -> 45 | G37: =Pressupostos!$G$24 -> 45
A38: Armazenagem | B38: €/kg | C38: =Pressupostos!$C$64*C36/30/1000 -> 0.004 | D38: =Pressupostos!$C$64*D36/30/1000 -> 0.004 | E38: =Pressupostos!$C$64*E36/30/1000 -> 0.004 | F38: =Pressupostos!$C$64*F36/30/1000 -> 0.004 | G38: =Pressupostos!$C$64*G36/30/1000 -> 0.004
A39: Seguro do stock | B39: €/kg | C39: =C30*Pressupostos!$C$65*C36/365 -> 0.00059178082 | D39: =D30*Pressupostos!$C$65*D36/365 -> 0.00059178082 | E39: =E30*Pressupostos!$C$65*E36/365 -> 0.00059178082 | F39: =F30*Pressupostos!$C$65*F36/365 -> 0.00059178082 | G39: =G30*Pressupostos!$C$65*G36/365 -> 0.00059178082
A40: Análises (testes de qualidade) | B40: €/kg | C40: =Pressupostos!$C$47*Pressupostos!$C$66/(Pressupostos!$C$46*1000) -> 0.02 | D40: =Pressupostos!$C$47*Pressupostos!$C$66/(Pressupostos!$C$46*1000) -> 0.02 | E40: =Pressupostos!$C$47*Pressupostos!$C$66/(Pressupostos!$C$46*1000) -> 0.02 | F40: =Pressupostos!$C$47*Pressupostos!$C$66/(Pressupostos!$C$46*1000) -> 0.02 | G40: =Pressupostos!$C$47*Pressupostos!$C$66/(Pressupostos!$C$46*1000) -> 0.02
A41: Perdas físicas | B41: €/kg | C41: =Pressupostos!$C$67*C30 -> 0.018 | D41: =Pressupostos!$C$67*D30 -> 0.018 | E41: =Pressupostos!$C$67*E30 -> 0.018 | F41: =Pressupostos!$C$67*F30 -> 0.018 | G41: =Pressupostos!$C$67*G30 -> 0.018
A42: Desclassificação esperada | B42: €/kg | C42: =Pressupostos!$C$68*Pressupostos!$C$69*C36/90 -> 0.003 | D42: =Pressupostos!$C$68*Pressupostos!$C$69*D36/90 -> 0.003 | E42: =Pressupostos!$C$68*Pressupostos!$C$69*E36/90 -> 0.003 | F42: =Pressupostos!$C$68*Pressupostos!$C$69*F36/90 -> 0.003 | G42: =Pressupostos!$C$68*Pressupostos!$C$69*G36/90 -> 0.003
A43: Custódia (collateral manager) | B43: €/kg | C43: =Pressupostos!$C$48/(Pressupostos!$C$46*1000) -> 0.04 | D43: =Pressupostos!$C$48/(Pressupostos!$C$46*1000) -> 0.04 | E43: =Pressupostos!$C$48/(Pressupostos!$C$46*1000) -> 0.04 | F43: =Pressupostos!$C$48/(Pressupostos!$C$46*1000) -> 0.04 | G43: =Pressupostos!$C$48/(Pressupostos!$C$46*1000) -> 0.04
A44: Pagamentos bancários | B44: €/kg | C44: =Pressupostos!$C$49 -> 0.005 | D44: =Pressupostos!$C$49 -> 0.005 | E44: =Pressupostos!$C$49 -> 0.005 | F44: =Pressupostos!$C$49 -> 0.005 | G44: =Pressupostos!$C$49 -> 0.005
A45: Provisão de crédito | B45: €/kg | C45: =Pressupostos!$G$25*C32 -> 0.01305 | D45: =Pressupostos!$G$25*D32 -> 0.01305 | E45: =Pressupostos!$G$25*E32 -> 0.01305 | F45: =Pressupostos!$G$25*F32 -> 0.01305 | G45: =Pressupostos!$G$25*G32 -> 0.01305
A46: Cobertura de preço explícita (sem futuros de azeite) | B46: €/kg | C46: =Pressupostos!$C$71*C32 -> 0 | D46: =Pressupostos!$C$71*D32 -> 0 | E46: =Pressupostos!$C$71*E32 -> 0 | F46: =Pressupostos!$C$71*F32 -> 0 | G46: =Pressupostos!$C$71*G32 -> 0
A47: Cupão das obrigações (financiamento do stock) | B47: €/kg | C47: =Pressupostos!$C$286*(C30+C33)*(C36+C37-Pressupostos!$C$70)/365*Pressupostos!$C$280/Pressupostos!$G$31 -> 0 | D47: =Pressupostos!$D$286*(D30+D33)*(D36+D37-Pressupostos!$C$70)/365*Pressupostos!$D$280/Pressupostos!$G$31 -> 0.044938356 | E47: =Pressupostos!$E$286*(E30+E33)*(E36+E37-Pressupostos!$C$70)/365*Pressupostos!$E$280/Pressupostos!$G$31 -> 0.042129709 | F47: =Pressupostos!$F$286*(F30+F33)*(F36+F37-Pressupostos!$C$70)/365*Pressupostos!$F$280/Pressupostos!$G$31 -> 0.039321062 | G47: =Pressupostos!$G$286*(G30+G33)*(G36+G37-Pressupostos!$C$70)/365*Pressupostos!$G$280/Pressupostos!$G$31 -> 0.039321062
A48: Custo direto total | B48: €/kg | C48: =C30+C33+C34+C35+C38+C39+C40+C41+C42+C43+C44+C45+C46+C47 -> 4.2536418 | D48: =D30+D33+D34+D35+D38+D39+D40+D41+D42+D43+D44+D45+D46+D47 -> 4.2985801 | E48: =E30+E33+E34+E35+E38+E39+E40+E41+E42+E43+E44+E45+E46+E47 -> 4.2857715 | F48: =F30+F33+F34+F35+F38+F39+F40+F41+F42+F43+F44+F45+F46+F47 -> 4.2829628 | G48: =G30+G33+G34+G35+G38+G39+G40+G41+G42+G43+G44+G45+G46+G47 -> 4.2829628
A49: Margem de contribuição | B49: €/kg | C49: =C32-C48 -> 0.096358219 | D49: =D32-D48 -> 0.051419863 | E49: =E32-E48 -> 0.06422851 | F49: =F32-F48 -> 0.067037158 | G49: =G32-G48 -> 0.067037158
A50: Margem de contribuição em % do preço | B50: % | C50: =IF(C32>0,C49/C32,0) -> 0.022151315 | D50: =IF(D32>0,D49/D32,0) -> 0.011820658 | E50: =IF(E32>0,E49/E32,0) -> 0.014765175 | F50: =IF(F32>0,F49/F32,0) -> 0.015410841 | G50: =IF(G32>0,G49/G32,0) -> 0.015410841
A51: Capital de giro por kg vendido | B51: €/kg | C51: =(C30+C33)*(C36-Pressupostos!$C$70)/365+C32*C37/365 -> 0.53630137 | D51: =(D30+D33)*(D36-Pressupostos!$C$70)/365+D32*D37/365 -> 0.53630137 | E51: =(E30+E33)*(E36-Pressupostos!$C$70)/365+E32*E37/365 -> 0.53630137 | F51: =(F30+F33)*(F36-Pressupostos!$C$70)/365+F32*F37/365 -> 0.53630137 | G51: =(G30+G33)*(G36-Pressupostos!$C$70)/365+G32*G37/365 -> 0.53630137
A53: Economia por kg: granel certificado
A54: Preço ao produtor (índice + prémio de origem) | B54: €/kg | C54: =Pressupostos!$G$10+Pressupostos!$G$13 -> 3.5 | D54: =Pressupostos!$G$10+Pressupostos!$G$13 -> 3.5 | E54: =Pressupostos!$G$10+Pressupostos!$G$13 -> 3.5 | F54: =Pressupostos!$G$10+Pressupostos!$G$13 -> 3.5 | G54: =Pressupostos!$G$10+Pressupostos!$G$13 -> 3.5
A55: Preço de referência do comprador | B55: €/kg | C55: =Pressupostos!$G$10+Pressupostos!$C$51 -> 3.65 | D55: =Pressupostos!$G$10+Pressupostos!$C$51 -> 3.65 | E55: =Pressupostos!$G$10+Pressupostos!$C$51 -> 3.65 | F55: =Pressupostos!$G$10+Pressupostos!$C$51 -> 3.65 | G55: =Pressupostos!$G$10+Pressupostos!$C$51 -> 3.65
A56: Preço de venda Sprout (referência − desconto) | B56: €/kg | C56: =C55*(1-Pressupostos!$C$52) -> 3.65 | D56: =D55*(1-Pressupostos!$C$52) -> 3.65 | E56: =E55*(1-Pressupostos!$C$52) -> 3.65 | F56: =F55*(1-Pressupostos!$C$52) -> 3.65 | G56: =G55*(1-Pressupostos!$C$52) -> 3.65
A57: Embalamento | B57: €/kg | C57: =Pressupostos!$C$53 -> 0 | D57: =Pressupostos!$C$53 -> 0 | E57: =Pressupostos!$C$53 -> 0 | F57: =Pressupostos!$C$53 -> 0 | G57: =Pressupostos!$C$53 -> 0
A58: Logística | B58: €/kg | C58: =Pressupostos!$C$54 -> 0.04 | D58: =Pressupostos!$C$54 -> 0.04 | E58: =Pressupostos!$C$54 -> 0.04 | F58: =Pressupostos!$C$54 -> 0.04 | G58: =Pressupostos!$C$54 -> 0.04
A59: Armazém logístico (3PL) e picking | B59: €/kg | C59: =Pressupostos!$C$55 -> 0 | D59: =Pressupostos!$C$55 -> 0 | E59: =Pressupostos!$C$55 -> 0 | F59: =Pressupostos!$C$55 -> 0 | G59: =Pressupostos!$C$55 -> 0
A60: Stock médio | B60: dias | C60: =Pressupostos!$C$56 -> 15 | D60: =Pressupostos!$C$56 -> 15 | E60: =Pressupostos!$C$56 -> 15 | F60: =Pressupostos!$C$56 -> 15 | G60: =Pressupostos!$C$56 -> 15
A61: Prazo médio de recebimento | B61: dias | C61: =Pressupostos!$C$57 -> 45 | D61: =Pressupostos!$C$57 -> 45 | E61: =Pressupostos!$C$57 -> 45 | F61: =Pressupostos!$C$57 -> 45 | G61: =Pressupostos!$C$57 -> 45
A62: Armazenagem | B62: €/kg | C62: =Pressupostos!$C$64*C60/30/1000 -> 0.002 | D62: =Pressupostos!$C$64*D60/30/1000 -> 0.002 | E62: =Pressupostos!$C$64*E60/30/1000 -> 0.002 | F62: =Pressupostos!$C$64*F60/30/1000 -> 0.002 | G62: =Pressupostos!$C$64*G60/30/1000 -> 0.002
A63: Seguro do stock | B63: €/kg | C63: =C54*Pressupostos!$C$65*C60/365 -> 0.00028767123 | D63: =D54*Pressupostos!$C$65*D60/365 -> 0.00028767123 | E63: =E54*Pressupostos!$C$65*E60/365 -> 0.00028767123 | F63: =F54*Pressupostos!$C$65*F60/365 -> 0.00028767123 | G63: =G54*Pressupostos!$C$65*G60/365 -> 0.00028767123
A64: Análises (testes de qualidade) | B64: €/kg | C64: =Pressupostos!$C$59*Pressupostos!$C$66/(Pressupostos!$C$58*1000) -> 0.006 | D64: =Pressupostos!$C$59*Pressupostos!$C$66/(Pressupostos!$C$58*1000) -> 0.006 | E64: =Pressupostos!$C$59*Pressupostos!$C$66/(Pressupostos!$C$58*1000) -> 0.006 | F64: =Pressupostos!$C$59*Pressupostos!$C$66/(Pressupostos!$C$58*1000) -> 0.006 | G64: =Pressupostos!$C$59*Pressupostos!$C$66/(Pressupostos!$C$58*1000) -> 0.006
A65: Perdas físicas | B65: €/kg | C65: =Pressupostos!$C$67*C54 -> 0.0175 | D65: =Pressupostos!$C$67*D54 -> 0.0175 | E65: =Pressupostos!$C$67*E54 -> 0.0175 | F65: =Pressupostos!$C$67*F54 -> 0.0175 | G65: =Pressupostos!$C$67*G54 -> 0.0175
A66: Desclassificação esperada | B66: €/kg | C66: =Pressupostos!$C$68*Pressupostos!$C$69*C60/90 -> 0.0015 | D66: =Pressupostos!$C$68*Pressupostos!$C$69*D60/90 -> 0.0015 | E66: =Pressupostos!$C$68*Pressupostos!$C$69*E60/90 -> 0.0015 | F66: =Pressupostos!$C$68*Pressupostos!$C$69*F60/90 -> 0.0015 | G66: =Pressupostos!$C$68*Pressupostos!$C$69*G60/90 -> 0.0015
A67: Custódia (collateral manager) | B67: €/kg | C67: =Pressupostos!$C$60/(Pressupostos!$C$58*1000) -> 0.012 | D67: =Pressupostos!$C$60/(Pressupostos!$C$58*1000) -> 0.012 | E67: =Pressupostos!$C$60/(Pressupostos!$C$58*1000) -> 0.012 | F67: =Pressupostos!$C$60/(Pressupostos!$C$58*1000) -> 0.012 | G67: =Pressupostos!$C$60/(Pressupostos!$C$58*1000) -> 0.012
A68: Pagamentos bancários | B68: €/kg | C68: =Pressupostos!$C$61 -> 0.001 | D68: =Pressupostos!$C$61 -> 0.001 | E68: =Pressupostos!$C$61 -> 0.001 | F68: =Pressupostos!$C$61 -> 0.001 | G68: =Pressupostos!$C$61 -> 0.001
A69: Provisão de crédito | B69: €/kg | C69: =Pressupostos!$C$62*C56 -> 0.01095 | D69: =Pressupostos!$C$62*D56 -> 0.01095 | E69: =Pressupostos!$C$62*E56 -> 0.01095 | F69: =Pressupostos!$C$62*F56 -> 0.01095 | G69: =Pressupostos!$C$62*G56 -> 0.01095
A70: Cobertura de preço explícita (sem futuros de azeite) | B70: €/kg | C70: =Pressupostos!$C$71*C56 -> 0 | D70: =Pressupostos!$C$71*D56 -> 0 | E70: =Pressupostos!$C$71*E56 -> 0 | F70: =Pressupostos!$C$71*F56 -> 0 | G70: =Pressupostos!$C$71*G56 -> 0
A71: Cupão das obrigações (financiamento do stock) | B71: €/kg | C71: =Pressupostos!$C$286*(C54+C57)*(C60+C61-Pressupostos!$C$70)/365*Pressupostos!$C$280/Pressupostos!$G$31 -> 0 | D71: =Pressupostos!$D$286*(D54+D57)*(D60+D61-Pressupostos!$C$70)/365*Pressupostos!$D$280/Pressupostos!$G$31 -> 0.025890411 | E71: =Pressupostos!$E$286*(E54+E57)*(E60+E61-Pressupostos!$C$70)/365*Pressupostos!$E$280/Pressupostos!$G$31 -> 0.02427226 | F71: =Pressupostos!$F$286*(F54+F57)*(F60+F61-Pressupostos!$C$70)/365*Pressupostos!$F$280/Pressupostos!$G$31 -> 0.02265411 | G71: =Pressupostos!$G$286*(G54+G57)*(G60+G61-Pressupostos!$C$70)/365*Pressupostos!$G$280/Pressupostos!$G$31 -> 0.02265411
A72: Custo direto total | B72: €/kg | C72: =C54+C57+C58+C59+C62+C63+C64+C65+C66+C67+C68+C69+C70+C71 -> 3.5912377 | D72: =D54+D57+D58+D59+D62+D63+D64+D65+D66+D67+D68+D69+D70+D71 -> 3.6171281 | E72: =E54+E57+E58+E59+E62+E63+E64+E65+E66+E67+E68+E69+E70+E71 -> 3.6155099 | F72: =F54+F57+F58+F59+F62+F63+F64+F65+F66+F67+F68+F69+F70+F71 -> 3.6138918 | G72: =G54+G57+G58+G59+G62+G63+G64+G65+G66+G67+G68+G69+G70+G71 -> 3.6138918
A73: Margem de contribuição | B73: €/kg | C73: =C56-C72 -> 0.058762329 | D73: =D56-D72 -> 0.032871918 | E73: =E56-E72 -> 0.034490068 | F73: =F56-F72 -> 0.036108219 | G73: =G56-G72 -> 0.036108219
A74: Margem de contribuição em % do preço | B74: % | C74: =IF(C56>0,C73/C56,0) -> 0.016099268 | D74: =IF(D56>0,D73/D56,0) -> 0.0090060049 | E74: =IF(E56>0,E73/E56,0) -> 0.0094493338 | F74: =IF(F56>0,F73/F56,0) -> 0.0098926628 | G74: =IF(G56>0,G73/G56,0) -> 0.0098926628
A75: Capital de giro por kg vendido | B75: €/kg | C75: =(C54+C57)*(C60-Pressupostos!$C$70)/365+C56*C61/365 -> 0.30616438 | D75: =(D54+D57)*(D60-Pressupostos!$C$70)/365+D56*D61/365 -> 0.30616438 | E75: =(E54+E57)*(E60-Pressupostos!$C$70)/365+E56*E61/365 -> 0.30616438 | F75: =(F54+F57)*(F60-Pressupostos!$C$70)/365+F56*F61/365 -> 0.30616438 | G75: =(G54+G57)*(G60-Pressupostos!$C$70)/365+G56*G61/365 -> 0.30616438
A77: Custo das mercadorias e custos diretos (€)
A78: Custo das mercadorias: azeite (granel + embalamento) | B78: € | C78: =Volumes!C10*1000*(C6+C9)+Volumes!C11*1000*(C30+C33)+Volumes!C12*1000*(C54+C57) -> 243800 | D78: =Volumes!D10*1000*(D6+D9)+Volumes!D11*1000*(D30+D33)+Volumes!D12*1000*(D54+D57) -> 1623700 | E78: =Volumes!E10*1000*(E6+E9)+Volumes!E11*1000*(E30+E33)+Volumes!E12*1000*(E54+E57) -> 3455800 | F78: =Volumes!F10*1000*(F6+F9)+Volumes!F11*1000*(F30+F33)+Volumes!F12*1000*(F54+F57) -> 5899200 | G78: =Volumes!G10*1000*(G6+G9)+Volumes!G11*1000*(G30+G33)+Volumes!G12*1000*(G54+G57) -> 8951000
A79: Custo das mercadorias: café verde | B79: € | C79: =Volumes!C23*1000*Pressupostos!$C$90 -> 0 | D79: =Volumes!D23*1000*Pressupostos!$C$90 -> 0 | E79: =Volumes!E23*1000*Pressupostos!$C$90 -> 210000 | F79: =Volumes!F23*1000*Pressupostos!$C$90 -> 420000 | G79: =Volumes!G23*1000*Pressupostos!$C$90 -> 700000
A80: Custo das mercadorias vendidas | B80: € | C80: =C78+C79 -> 243800 | D80: =D78+D79 -> 1623700 | E80: =E78+E79 -> 3665800 | F80: =F78+F79 -> 6319200 | G80: =G78+G79 -> 9651000
A81: Logística | B81: € | C81: =Volumes!C10*1000*(C10)+Volumes!C11*1000*(C34)+Volumes!C12*1000*(C58)+Volumes!C23*1000*Pressupostos!$C$92 -> 7600 | D81: =Volumes!D10*1000*(D10)+Volumes!D11*1000*(D34)+Volumes!D12*1000*(D58)+Volumes!D23*1000*Pressupostos!$C$92 -> 47400 | E81: =Volumes!E10*1000*(E10)+Volumes!E11*1000*(E34)+Volumes!E12*1000*(E58)+Volumes!E23*1000*Pressupostos!$C$92 -> 106270 | F81: =Volumes!F10*1000*(F10)+Volumes!F11*1000*(F34)+Volumes!F12*1000*(F58)+Volumes!F23*1000*Pressupostos!$C$92 -> 187560 | G81: =Volumes!G10*1000*(G10)+Volumes!G11*1000*(G34)+Volumes!G12*1000*(G58)+Volumes!G23*1000*Pressupostos!$C$92 -> 286800
A82: Armazém logístico (3PL) e picking | B82: € | C82: =Volumes!C10*1000*(C11)+Volumes!C11*1000*(C35)+Volumes!C12*1000*(C59) -> 480 | D82: =Volumes!D10*1000*(D11)+Volumes!D11*1000*(D35)+Volumes!D12*1000*(D59) -> 2220 | E82: =Volumes!E10*1000*(E11)+Volumes!E11*1000*(E35)+Volumes!E12*1000*(E59) -> 7980 | F82: =Volumes!F10*1000*(F11)+Volumes!F11*1000*(F35)+Volumes!F12*1000*(F59) -> 16020 | G82: =Volumes!G10*1000*(G11)+Volumes!G11*1000*(G35)+Volumes!G12*1000*(G59) -> 24600
A83: Armazenagem e seguro do stock | B83: € | C83: =Volumes!C10*1000*(C14+C15)+Volumes!C11*1000*(C38+C39)+Volumes!C12*1000*(C62+C63) -> 459.17808 | D83: =Volumes!D10*1000*(D14+D15)+Volumes!D11*1000*(D38+D39)+Volumes!D12*1000*(D62+D63) -> 2686.1918 | E83: =Volumes!E10*1000*(E14+E15)+Volumes!E11*1000*(E38+E39)+Volumes!E12*1000*(E62+E63) -> 4208.3671 | F83: =Volumes!F10*1000*(F14+F15)+Volumes!F11*1000*(F38+F39)+Volumes!F12*1000*(F62+F63) -> 7271.0849 | G83: =Volumes!G10*1000*(G14+G15)+Volumes!G11*1000*(G38+G39)+Volumes!G12*1000*(G62+G63) -> 11043.233
A84: Análises, perdas e desclassificação | B84: € | C84: =Volumes!C10*1000*(C16+C17+C18)+Volumes!C11*1000*(C40+C41+C42)+Volumes!C12*1000*(C64+C65+C66) -> 2660 | D84: =Volumes!D10*1000*(D16+D17+D18)+Volumes!D11*1000*(D40+D41+D42)+Volumes!D12*1000*(D64+D65+D66) -> 17325 | E84: =Volumes!E10*1000*(E16+E17+E18)+Volumes!E11*1000*(E40+E41+E42)+Volumes!E12*1000*(E64+E65+E66) -> 36379.5 | F84: =Volumes!F10*1000*(F16+F17+F18)+Volumes!F11*1000*(F40+F41+F42)+Volumes!F12*1000*(F64+F65+F66) -> 62520.5 | G84: =Volumes!G10*1000*(G16+G17+G18)+Volumes!G11*1000*(G40+G41+G42)+Volumes!G12*1000*(G64+G65+G66) -> 94915
A85: Custódia (collateral manager) | B85: € | C85: =Volumes!C10*1000*(C19)+Volumes!C11*1000*(C43)+Volumes!C12*1000*(C67) -> 2880 | D85: =Volumes!D10*1000*(D19)+Volumes!D11*1000*(D43)+Volumes!D12*1000*(D67) -> 18220 | E85: =Volumes!E10*1000*(E19)+Volumes!E11*1000*(E43)+Volumes!E12*1000*(E67) -> 41980 | F85: =Volumes!F10*1000*(F19)+Volumes!F11*1000*(F43)+Volumes!F12*1000*(F67) -> 74020 | G85: =Volumes!G10*1000*(G19)+Volumes!G11*1000*(G43)+Volumes!G12*1000*(G67) -> 112600
A86: Pagamentos bancários e operações | B86: € | C86: =Volumes!C10*1000*(C20)+Volumes!C11*1000*(C44)+Volumes!C12*1000*(C68)+Volumes!C23*1000*Pressupostos!$C$97 -> 340 | D86: =Volumes!D10*1000*(D20)+Volumes!D11*1000*(D44)+Volumes!D12*1000*(D68)+Volumes!D23*1000*Pressupostos!$C$97 -> 2185 | E86: =Volumes!E10*1000*(E20)+Volumes!E11*1000*(E44)+Volumes!E12*1000*(E68)+Volumes!E23*1000*Pressupostos!$C$97 -> 5815 | F86: =Volumes!F10*1000*(F20)+Volumes!F11*1000*(F44)+Volumes!F12*1000*(F68)+Volumes!F23*1000*Pressupostos!$C$97 -> 10385 | G86: =Volumes!G10*1000*(G20)+Volumes!G11*1000*(G44)+Volumes!G12*1000*(G68)+Volumes!G23*1000*Pressupostos!$C$97 -> 16050
A87: Provisão de crédito | B87: € | C87: =Volumes!C10*1000*(C21)+Volumes!C11*1000*(C45)+Volumes!C12*1000*(C69)+Volumes!C23*1000*Pressupostos!$C$96*Pressupostos!$C$91 -> 922.68 | D87: =Volumes!D10*1000*(D21)+Volumes!D11*1000*(D45)+Volumes!D12*1000*(D69)+Volumes!D23*1000*Pressupostos!$C$96*Pressupostos!$C$91 -> 5866.02 | E87: =Volumes!E10*1000*(E21)+Volumes!E11*1000*(E45)+Volumes!E12*1000*(E69)+Volumes!E23*1000*Pressupostos!$C$96*Pressupostos!$C$91 -> 14827.68 | F87: =Volumes!F10*1000*(F21)+Volumes!F11*1000*(F45)+Volumes!F12*1000*(F69)+Volumes!F23*1000*Pressupostos!$C$96*Pressupostos!$C$91 -> 26410.32 | G87: =Volumes!G10*1000*(G21)+Volumes!G11*1000*(G45)+Volumes!G12*1000*(G69)+Volumes!G23*1000*Pressupostos!$C$96*Pressupostos!$C$91 -> 40578.6
A88: Cobertura explícita (café: forward EUR/USD; azeite: sem futuros) | B88: € | C88: =Volumes!C10*1000*(C22)+Volumes!C11*1000*(C46)+Volumes!C12*1000*(C70)+Volumes!C23*1000*Pressupostos!$G$29*Pressupostos!$C$90 -> 0 | D88: =Volumes!D10*1000*(D22)+Volumes!D11*1000*(D46)+Volumes!D12*1000*(D70)+Volumes!D23*1000*Pressupostos!$G$29*Pressupostos!$C$90 -> 0 | E88: =Volumes!E10*1000*(E22)+Volumes!E11*1000*(E46)+Volumes!E12*1000*(E70)+Volumes!E23*1000*Pressupostos!$G$29*Pressupostos!$C$90 -> 0 | F88: =Volumes!F10*1000*(F22)+Volumes!F11*1000*(F46)+Volumes!F12*1000*(F70)+Volumes!F23*1000*Pressupostos!$G$29*Pressupostos!$C$90 -> 0 | G88: =Volumes!G10*1000*(G22)+Volumes!G11*1000*(G46)+Volumes!G12*1000*(G70)+Volumes!G23*1000*Pressupostos!$G$29*Pressupostos!$C$90 -> 0
A89: Verificação para terceiros (collateral manager e análises) | B89: € | C89: =Volumes!C27*1000*Pressupostos!$C$102*Pressupostos!$G$30 -> 0 | D89: =Volumes!D27*1000*Pressupostos!$C$102*Pressupostos!$G$30 -> 8228.5714 | E89: =Volumes!E27*1000*Pressupostos!$C$102*Pressupostos!$G$30 -> 24685.714 | F89: =Volumes!F27*1000*Pressupostos!$C$102*Pressupostos!$G$30 -> 49371.429 | G89: =Volumes!G27*1000*Pressupostos!$C$102*Pressupostos!$G$30 -> 82285.714
A90: Custos variáveis diretos | B90: € | C90: =C81+C82+C83+C84+C85+C86+C87+C88+C89 -> 15341.858 | D90: =D81+D82+D83+D84+D85+D86+D87+D88+D89 -> 104130.78 | E90: =E81+E82+E83+E84+E85+E86+E87+E88+E89 -> 242146.26 | F90: =F81+F82+F83+F84+F85+F86+F87+F88+F89 -> 433558.33 | G90: =G81+G82+G83+G84+G85+G86+G87+G88+G89 -> 668872.55
A91: Cupão das obrigações: azeite | B91: € | C91: =Volumes!C10*1000*(C23)+Volumes!C11*1000*(C47)+Volumes!C12*1000*(C71) -> 0 | D91: =Volumes!D10*1000*(D23)+Volumes!D11*1000*(D47)+Volumes!D12*1000*(D71) -> 23317.027 | E91: =Volumes!E10*1000*(E23)+Volumes!E11*1000*(E47)+Volumes!E12*1000*(E71) -> 36586.56 | F91: =Volumes!F10*1000*(F23)+Volumes!F11*1000*(F47)+Volumes!F12*1000*(F71) -> 58470.095 | G91: =Volumes!G10*1000*(G23)+Volumes!G11*1000*(G47)+Volumes!G12*1000*(G71) -> 88739.923
A92: Cupão das obrigações: café | B92: € | C92: =Volumes!C23*1000*Receitas!C29 -> 0 | D92: =Volumes!D23*1000*Receitas!D29 -> 0 | E92: =Volumes!E23*1000*Receitas!E29 -> 2184.5034 | F92: =Volumes!F23*1000*Receitas!F29 -> 4077.7397 | G92: =Volumes!G23*1000*Receitas!G29 -> 6796.2329
A93: Cupão das obrigações (custo de financiar o stock) | B93: € | C93: =C91+C92 -> 0 | D93: =D91+D92 -> 23317.027 | E93: =E91+E92 -> 38771.064 | F93: =F91+F92 -> 62547.835 | G93: =G91+G92 -> 95536.156
A94: Verificação: receita − CMV − variáveis − cupão − margem de contribuição | B94: € | C94: =ROUND(Receitas!C15-C80-C90-C93-Receitas!C34,6) -> 0 | D94: =ROUND(Receitas!D15-D80-D90-D93-Receitas!D34,6) -> 0 | E94: =ROUND(Receitas!E15-E80-E90-E93-Receitas!E34,6) -> 0 | F94: =ROUND(Receitas!F15-F80-F90-F93-Receitas!F34,6) -> 0 | G94: =ROUND(Receitas!G15-G80-G90-G93-Receitas!G34,6) -> 0
A96: Opex não salarial (€ nominais: + contingência e inflação)
A97: Jurídico e compliance externo | B97: € | C97: =Pressupostos!$C$391*(1+Pressupostos!$C$154)*(1+Pressupostos!$C$155)^0 -> 94500 | D97: =Pressupostos!$D$391*(1+Pressupostos!$C$154)*(1+Pressupostos!$C$155)^1 -> 53550 | E97: =Pressupostos!$E$391*(1+Pressupostos!$C$154)*(1+Pressupostos!$C$155)^2 -> 49158.9 | F97: =Pressupostos!$F$391*(1+Pressupostos!$C$154)*(1+Pressupostos!$C$155)^3 -> 50142.078 | G97: =Pressupostos!$G$391*(1+Pressupostos!$C$154)*(1+Pressupostos!$C$155)^4 -> 51144.92
A98: Auditoria (ROC) | B98: € | C98: =Pressupostos!$C$397*(1+Pressupostos!$C$154)*(1+Pressupostos!$C$155)^0 -> 10500 | D98: =Pressupostos!$D$397*(1+Pressupostos!$C$154)*(1+Pressupostos!$C$155)^1 -> 10710 | E98: =Pressupostos!$E$397*(1+Pressupostos!$C$154)*(1+Pressupostos!$C$155)^2 -> 10924.2 | F98: =Pressupostos!$F$397*(1+Pressupostos!$C$154)*(1+Pressupostos!$C$155)^3 -> 11142.684 | G98: =Pressupostos!$G$397*(1+Pressupostos!$C$154)*(1+Pressupostos!$C$155)^4 -> 11365.538
A99: Contabilidade externa | B99: € | C99: =Pressupostos!$C$403*(1+Pressupostos!$C$154)*(1+Pressupostos!$C$155)^0 -> 12600 | D99: =Pressupostos!$D$403*(1+Pressupostos!$C$154)*(1+Pressupostos!$C$155)^1 -> 12852 | E99: =Pressupostos!$E$403*(1+Pressupostos!$C$154)*(1+Pressupostos!$C$155)^2 -> 13109.04 | F99: =Pressupostos!$F$403*(1+Pressupostos!$C$154)*(1+Pressupostos!$C$155)^3 -> 0 | G99: =Pressupostos!$G$403*(1+Pressupostos!$C$154)*(1+Pressupostos!$C$155)^4 -> 0
A100: Tecnologia: cloud, SaaS, KYC, faturação certificada | B100: € | C100: =Pressupostos!$C$409*(1+Pressupostos!$C$154)*(1+Pressupostos!$C$155)^0 -> 31500 | D100: =Pressupostos!$D$409*(1+Pressupostos!$C$154)*(1+Pressupostos!$C$155)^1 -> 42840 | E100: =Pressupostos!$E$409*(1+Pressupostos!$C$154)*(1+Pressupostos!$C$155)^2 -> 60083.1 | F100: =Pressupostos!$F$409*(1+Pressupostos!$C$154)*(1+Pressupostos!$C$155)^3 -> 77998.788 | G100: =Pressupostos!$G$409*(1+Pressupostos!$C$154)*(1+Pressupostos!$C$155)^4 -> 96607.07
A101: Segurança: pentest e ISO 27001 | B101: € | C101: =Pressupostos!$C$415*(1+Pressupostos!$C$154)*(1+Pressupostos!$C$155)^0 -> 15750 | D101: =Pressupostos!$D$415*(1+Pressupostos!$C$154)*(1+Pressupostos!$C$155)^1 -> 16065 | E101: =Pressupostos!$E$415*(1+Pressupostos!$C$154)*(1+Pressupostos!$C$155)^2 -> 38234.7 | F101: =Pressupostos!$F$415*(1+Pressupostos!$C$154)*(1+Pressupostos!$C$155)^3 -> 22285.368 | G101: =Pressupostos!$G$415*(1+Pressupostos!$C$154)*(1+Pressupostos!$C$155)^4 -> 22731.075
A102: Seguros da empresa (RC, D&O, ciber) | B102: € | C102: =Pressupostos!$C$421*(1+Pressupostos!$C$154)*(1+Pressupostos!$C$155)^0 -> 10500 | D102: =Pressupostos!$D$421*(1+Pressupostos!$C$154)*(1+Pressupostos!$C$155)^1 -> 12852 | E102: =Pressupostos!$E$421*(1+Pressupostos!$C$154)*(1+Pressupostos!$C$155)^2 -> 16386.3 | F102: =Pressupostos!$F$421*(1+Pressupostos!$C$154)*(1+Pressupostos!$C$155)^3 -> 20056.831 | G102: =Pressupostos!$G$421*(1+Pressupostos!$C$154)*(1+Pressupostos!$C$155)^4 -> 22731.075
A103: Marketing e comercial B2B | B103: € | C103: =Pressupostos!$C$427*(1+Pressupostos!$C$154)*(1+Pressupostos!$C$155)^0 -> 42000 | D103: =Pressupostos!$D$427*(1+Pressupostos!$C$154)*(1+Pressupostos!$C$155)^1 -> 53550 | E103: =Pressupostos!$E$427*(1+Pressupostos!$C$154)*(1+Pressupostos!$C$155)^2 -> 76469.4 | F103: =Pressupostos!$F$427*(1+Pressupostos!$C$154)*(1+Pressupostos!$C$155)^3 -> 100284.16 | G103: =Pressupostos!$G$427*(1+Pressupostos!$C$154)*(1+Pressupostos!$C$155)^4 -> 125020.91
A104: Escritório | B104: € | C104: =Pressupostos!$C$433*(1+Pressupostos!$C$154)*(1+Pressupostos!$C$155)^0 -> 12600 | D104: =Pressupostos!$D$433*(1+Pressupostos!$C$154)*(1+Pressupostos!$C$155)^1 -> 16065 | E104: =Pressupostos!$E$433*(1+Pressupostos!$C$154)*(1+Pressupostos!$C$155)^2 -> 26218.08 | F104: =Pressupostos!$F$433*(1+Pressupostos!$C$154)*(1+Pressupostos!$C$155)^3 -> 33428.052 | G104: =Pressupostos!$G$433*(1+Pressupostos!$C$154)*(1+Pressupostos!$C$155)^4 -> 40915.936
...

Sheet DR
A1: Demonstração de resultados
A2: Receita, margem bruta, margem de contribuição, EBITDA, amortizações, EBIT, IRC com derramas e resultado líquido (cenário ativo).
A3: ="Cenário ativo: "&Pressupostos!$C$4&" · euros correntes, sem IVA" -> Cenário ativo: Base · euros correntes, sem IVA
A4: Rubrica | B4: Unidade | C4: 2027 | D4: 2028 | E4: 2029 | F4: 2030 | G4: 2031 | H4: Notas
A5: Demonstração de resultados (€)
A6: Receita | B6: € | C6: =Receitas!C15 -> 267690 | D6: =Receitas!D15 -> 1780435 | E6: =Receitas!E15 -> 4066155 | F6: =Receitas!F15 -> 7052305 | G6: =Receitas!G15 -> 10796070
A7: Custo das mercadorias vendidas | B7: € | C7: =-Custos!C80 -> -243800 | D7: =-Custos!D80 -> -1623700 | E7: =-Custos!E80 -> -3665800 | F7: =-Custos!F80 -> -6319200 | G7: =-Custos!G80 -> -9651000
A8: Margem bruta | B8: € | C8: =C6+C7 -> 23890 | D8: =D6+D7 -> 156735 | E8: =E6+E7 -> 400355 | F8: =F6+F7 -> 733105 | G8: =G6+G7 -> 1145070
A9: Margem bruta em % da receita | B9: % | C9: =IF(C6>0,C8/C6,0) -> 0.089245022 | D9: =IF(D6>0,D8/D6,0) -> 0.088031857 | E9: =IF(E6>0,E8/E6,0) -> 0.098460339 | F9: =IF(F6>0,F8/F6,0) -> 0.10395254 | G9: =IF(G6>0,G8/G6,0) -> 0.1060636
A10: Custos variáveis diretos (logística, custódia, qualidade, crédito, pagamentos) | B10: € | C10: =-Custos!C90 -> -15341.858 | D10: =-Custos!D90 -> -104130.78 | E10: =-Custos!E90 -> -242146.26 | F10: =-Custos!F90 -> -433558.33 | G10: =-Custos!G90 -> -668872.55
A11: Cupão das obrigações (custo de financiar o stock) | B11: € | C11: =-Custos!C93 -> 0 | D11: =-Custos!D93 -> -23317.027 | E11: =-Custos!E93 -> -38771.064 | F11: =-Custos!F93 -> -62547.835 | G11: =-Custos!G93 -> -95536.156
A12: Margem de contribuição | B12: € | C12: =C8+C10+C11 -> 8548.1419 | D12: =D8+D10+D11 -> 29287.189 | E12: =E8+E10+E11 -> 119437.67 | F12: =F8+F10+F11 -> 236998.83 | G12: =G8+G10+G11 -> 380661.3
A13: Pessoal | B13: € | C13: =-Pessoal!C36 -> -400885.59 | D13: =-Pessoal!D36 -> -508017.89 | E13: =-Pessoal!E36 -> -667701.29 | F13: =-Pessoal!F36 -> -855745.93 | G13: =-Pessoal!G36 -> -1042442
A14: Opex não salarial (incl. SPV e seguro de crédito) | B14: € | C14: =-Custos!C110 -> -319100 | D14: =-Custos!D110 -> -322682.78 | E14: =-Custos!E110 -> -421646.38 | F14: =-Custos!F110 -> -475409.16 | G14: =-Custos!G110 -> -558195.15
A15: EBITDA | B15: € | C15: =C12+C13+C14 -> -711437.45 | D15: =D12+D13+D14 -> -801413.48 | E15: =E12+E13+E14 -> -969909.99 | F15: =F12+F13+F14 -> -1094156.3 | G15: =G12+G13+G14 -> -1219975.9 | H15: Convenção do modelo (igual ao 01 e a calculo_referencia.py): inclui o cupão, que financia stock lote a lote
A16: EBITDA em % da receita | B16: % | C16: =IF(C6>0,C15/C6,0) -> -2.6576916 | D16: =IF(D6>0,D15/D6,0) -> -0.45012229 | E16: =IF(E6>0,E15/E6,0) -> -0.23853247 | F16: =IF(F6>0,F15/F6,0) -> -0.15514874 | G16: =IF(G6>0,G15/G6,0) -> -0.11300185
A17: Memo: EBITDA sem o cupão (juros abaixo do EBIT, convenção SNC) | B17: € | C17: =C15+Custos!C93 -> -711437.45 | D17: =D15+Custos!D93 -> -778096.45 | E17: =E15+Custos!E93 -> -931138.93 | F17: =F15+Custos!F93 -> -1031608.4 | G17: =G15+Custos!G93 -> -1124439.7
A18: Amortizações | B18: € | C18: =-Custos!C120 -> -27100 | D18: =-Custos!D120 -> -40000 | E18: =-Custos!E120 -> -53900 | F18: =-Custos!F120 -> -44466.667 | G18: =-Custos!G120 -> -41533.333
A19: EBIT | B19: € | C19: =C15+C18 -> -738537.45 | D19: =D15+D18 -> -841413.48 | E19: =E15+E18 -> -1023810 | F19: =F15+F18 -> -1138622.9 | G19: =G15+G18 -> -1261509.2
A21: IRC e derramas [L]
A22: Lucro tributável antes de prejuízos (= EBIT; sem correções fiscais) | B22: € | C22: =C19 -> -738537.45 | D22: =D19 -> -841413.48 | E22: =E19 -> -1023810 | F22: =F19 -> -1138622.9 | G22: =G19 -> -1261509.2
A23: Prejuízos fiscais reportáveis no início do ano | B23: € | C23: =0 -> 0 | D23: =C26 -> 738537.45 | E23: =D26 -> 1579950.9 | F23: =E26 -> 2603760.9 | G23: =F26 -> 3742383.8
A24: Prejuízo fiscal gerado no ano | B24: € | C24: =MAX(0,-C22) -> 738537.45 | D24: =MAX(0,-D22) -> 841413.48 | E24: =MAX(0,-E22) -> 1023810 | F24: =MAX(0,-F22) -> 1138622.9 | G24: =MAX(0,-G22) -> 1261509.2
A25: Dedução de prejuízos (até 65% do lucro tributável) | B25: € | C25: =MIN(C23,Pressupostos!$C$179*MAX(0,C22)) -> 0 | D25: =MIN(D23,Pressupostos!$C$179*MAX(0,D22)) -> 0 | E25: =MIN(E23,Pressupostos!$C$179*MAX(0,E22)) -> 0 | F25: =MIN(F23,Pressupostos!$C$179*MAX(0,F22)) -> 0 | G25: =MIN(G23,Pressupostos!$C$179*MAX(0,G22)) -> 0
A26: Prejuízos fiscais reportáveis no fim do ano | B26: € | C26: =C23+C24-C25 -> 738537.45 | D26: =D23+D24-D25 -> 1579950.9 | E26: =E23+E24-E25 -> 2603760.9 | F26: =F23+F24-F25 -> 3742383.8 | G26: =G23+G24-G25 -> 5003893.1
A27: Matéria coletável | B27: € | C27: =MAX(0,C22)-C25 -> 0 | D27: =MAX(0,D22)-D25 -> 0 | E27: =MAX(0,E22)-E25 -> 0 | F27: =MAX(0,F22)-F25 -> 0 | G27: =MAX(0,G22)-G25 -> 0
A28: IRC (15% até 50.000 €; taxa geral acima) | B28: € | C28: =Pressupostos!$C$170*MIN(C27,Pressupostos!$C$171)+Pressupostos!$C$450*MAX(0,C27-Pressupostos!$C$171) -> 0 | D28: =Pressupostos!$C$170*MIN(D27,Pressupostos!$C$171)+Pressupostos!$D$450*MAX(0,D27-Pressupostos!$C$171) -> 0 | E28: =Pressupostos!$C$170*MIN(E27,Pressupostos!$C$171)+Pressupostos!$E$450*MAX(0,E27-Pressupostos!$C$171) -> 0 | F28: =Pressupostos!$C$170*MIN(F27,Pressupostos!$C$171)+Pressupostos!$F$450*MAX(0,F27-Pressupostos!$C$171) -> 0 | G28: =Pressupostos!$C$170*MIN(G27,Pressupostos!$C$171)+Pressupostos!$G$450*MAX(0,G27-Pressupostos!$C$171) -> 0
A29: Derrama municipal | B29: € | C29: =Pressupostos!$C$172*MAX(0,C22) -> 0 | D29: =Pressupostos!$C$172*MAX(0,D22) -> 0 | E29: =Pressupostos!$C$172*MAX(0,E22) -> 0 | F29: =Pressupostos!$C$172*MAX(0,F22) -> 0 | G29: =Pressupostos!$C$172*MAX(0,G22) -> 0
A30: Derrama estadual | B30: € | C30: =Pressupostos!$C$174*MAX(0,MIN(C22,Pressupostos!$C$175)-Pressupostos!$C$173)+Pressupostos!$C$176*MAX(0,MIN(C22,Pressupostos!$C$177)-Pressupostos!$C$175)+Pressupostos!$C$178*MAX(0,C22-Pressupostos!$C$177) -> 0 | D30: =Pressupostos!$C$174*MAX(0,MIN(D22,Pressupostos!$C$175)-Pressupostos!$C$173)+Pressupostos!$C$176*MAX(0,MIN(D22,Pressupostos!$C$177)-Pressupostos!$C$175)+Pressupostos!$C$178*MAX(0,D22-Pressupostos!$C$177) -> 0 | E30: =Pressupostos!$C$174*MAX(0,MIN(E22,Pressupostos!$C$175)-Pressupostos!$C$173)+Pressupostos!$C$176*MAX(0,MIN(E22,Pressupostos!$C$177)-Pressupostos!$C$175)+Pressupostos!$C$178*MAX(0,E22-Pressupostos!$C$177) -> 0 | F30: =Pressupostos!$C$174*MAX(0,MIN(F22,Pressupostos!$C$175)-Pressupostos!$C$173)+Pressupostos!$C$176*MAX(0,MIN(F22,Pressupostos!$C$177)-Pressupostos!$C$175)+Pressupostos!$C$178*MAX(0,F22-Pressupostos!$C$177) -> 0 | G30: =Pressupostos!$C$174*MAX(0,MIN(G22,Pressupostos!$C$175)-Pressupostos!$C$173)+Pressupostos!$C$176*MAX(0,MIN(G22,Pressupostos!$C$177)-Pressupostos!$C$175)+Pressupostos!$C$178*MAX(0,G22-Pressupostos!$C$177) -> 0
A31: Imposto sobre o rendimento | B31: € | C31: =C28+C29+C30 -> 0 | D31: =D28+D29+D30 -> 0 | E31: =E28+E29+E30 -> 0 | F31: =F28+F29+F30 -> 0 | G31: =G28+G29+G30 -> 0
A33: Resultado
A34: Imposto sobre o rendimento | B34: € | C34: =-C31 -> 0 | D34: =-D31 -> 0 | E34: =-E31 -> 0 | F34: =-F31 -> 0 | G34: =-G31 -> 0
A35: Resultado líquido | B35: € | C35: =C19+C34 -> -738537.45 | D35: =D19+D34 -> -841413.48 | E35: =E19+E34 -> -1023810 | F35: =F19+F34 -> -1138622.9 | G35: =G19+G34 -> -1261509.2

Sheet Cash flow
A1: Cash flow
A2: Capital de giro por prazos médios, obrigações e float das séries, cash flow para o acionista, caixa e rondas (cenário ativo).
A3: ="Cenário ativo: "&Pressupostos!$C$4&" · euros correntes, sem IVA" -> Cenário ativo: Base · euros correntes, sem IVA
A4: Rubrica | B4: Unidade | C4: 2027 | D4: 2028 | E4: 2029 | F4: 2030 | G4: 2031 | H4: Notas
A5: Capital de giro (€, nível médio do ano, sem IVA)
A6: Stock de azeite (ao custo) | B6: € | C6: =Volumes!C10*1000*((Custos!C6+Custos!C9)*Custos!C12/365)+Volumes!C11*1000*((Custos!C30+Custos!C33)*Custos!C36/365)+Volumes!C12*1000*((Custos!C54+Custos!C57)*Custos!C60/365) -> 33682.192 | D6: =Volumes!D10*1000*((Custos!D6+Custos!D9)*Custos!D12/365)+Volumes!D11*1000*((Custos!D30+Custos!D33)*Custos!D36/365)+Volumes!D12*1000*((Custos!D54+Custos!D57)*Custos!D60/365) -> 196557.53 | E6: =Volumes!E10*1000*((Custos!E6+Custos!E9)*Custos!E12/365)+Volumes!E11*1000*((Custos!E30+Custos!E33)*Custos!E36/365)+Volumes!E12*1000*((Custos!E54+Custos!E57)*Custos!E60/365) -> 306721.23 | F6: =Volumes!F10*1000*((Custos!F6+Custos!F9)*Custos!F12/365)+Volumes!F11*1000*((Custos!F30+Custos!F33)*Custos!F36/365)+Volumes!F12*1000*((Custos!F54+Custos!F57)*Custos!F60/365) -> 530402.05 | G6: =Volumes!G10*1000*((Custos!G6+Custos!G9)*Custos!G12/365)+Volumes!G11*1000*((Custos!G30+Custos!G33)*Custos!G36/365)+Volumes!G12*1000*((Custos!G54+Custos!G57)*Custos!G60/365) -> 805623.29
A7: Stock total (azeite + café) | B7: € | C7: =C6+Volumes!C23*1000*Pressupostos!$C$90*Pressupostos!$C$93/365 -> 33682.192 | D7: =D6+Volumes!D23*1000*Pressupostos!$C$90*Pressupostos!$C$93/365 -> 196557.53 | E7: =E6+Volumes!E23*1000*Pressupostos!$C$90*Pressupostos!$C$93/365 -> 332611.64 | F7: =F6+Volumes!F23*1000*Pressupostos!$C$90*Pressupostos!$C$93/365 -> 582182.88 | G7: =G6+Volumes!G23*1000*Pressupostos!$C$90*Pressupostos!$C$93/365 -> 891924.66
A8: Recebíveis (prazos médios de recebimento) | B8: € | C8: =Volumes!C10*1000*(Custos!C8*Custos!C13/365)+Volumes!C11*1000*(Custos!C32*Custos!C37/365)+Volumes!C12*1000*(Custos!C56*Custos!C61/365)+Receitas!C10*Pressupostos!$C$94/365+Receitas!C12*Pressupostos!$C$80/365 -> 31855.068 | D8: =Volumes!D10*1000*(Custos!D8*Custos!D13/365)+Volumes!D11*1000*(Custos!D32*Custos!D37/365)+Volumes!D12*1000*(Custos!D56*Custos!D61/365)+Receitas!D10*Pressupostos!$C$94/365+Receitas!D12*Pressupostos!$C$80/365 -> 212985 | E8: =Volumes!E10*1000*(Custos!E8*Custos!E13/365)+Volumes!E11*1000*(Custos!E32*Custos!E37/365)+Volumes!E12*1000*(Custos!E56*Custos!E61/365)+Receitas!E10*Pressupostos!$C$94/365+Receitas!E12*Pressupostos!$C$80/365 -> 469179.25 | F8: =Volumes!F10*1000*(Custos!F8*Custos!F13/365)+Volumes!F11*1000*(Custos!F32*Custos!F37/365)+Volumes!F12*1000*(Custos!F56*Custos!F61/365)+Receitas!F10*Pressupostos!$C$94/365+Receitas!F12*Pressupostos!$C$80/365 -> 803968.15 | G8: =Volumes!G10*1000*(Custos!G8*Custos!G13/365)+Volumes!G11*1000*(Custos!G32*Custos!G37/365)+Volumes!G12*1000*(Custos!G56*Custos!G61/365)+Receitas!G10*Pressupostos!$C$94/365+Receitas!G12*Pressupostos!$C$80/365 -> 1225216
A9: Fornecedores (produtor pago a 30 dias) | B9: € | C9: =Volumes!C10*1000*((Custos!C6+Custos!C9)*Pressupostos!$C$70/365)+Volumes!C11*1000*((Custos!C30+Custos!C33)*Pressupostos!$C$70/365)+Volumes!C12*1000*((Custos!C54+Custos!C57)*Pressupostos!$C$70/365)+Volumes!C23*1000*Pressupostos!$C$90*Pressupostos!$C$95/365 -> 20038.356 | D9: =Volumes!D10*1000*((Custos!D6+Custos!D9)*Pressupostos!$C$70/365)+Volumes!D11*1000*((Custos!D30+Custos!D33)*Pressupostos!$C$70/365)+Volumes!D12*1000*((Custos!D54+Custos!D57)*Pressupostos!$C$70/365)+Volumes!D23*1000*Pressupostos!$C$90*Pressupostos!$C$95/365 -> 133454.79 | E9: =Volumes!E10*1000*((Custos!E6+Custos!E9)*Pressupostos!$C$70/365)+Volumes!E11*1000*((Custos!E30+Custos!E33)*Pressupostos!$C$70/365)+Volumes!E12*1000*((Custos!E54+Custos!E57)*Pressupostos!$C$70/365)+Volumes!E23*1000*Pressupostos!$C$90*Pressupostos!$C$95/365 -> 301298.63 | F9: =Volumes!F10*1000*((Custos!F6+Custos!F9)*Pressupostos!$C$70/365)+Volumes!F11*1000*((Custos!F30+Custos!F33)*Pressupostos!$C$70/365)+Volumes!F12*1000*((Custos!F54+Custos!F57)*Pressupostos!$C$70/365)+Volumes!F23*1000*Pressupostos!$C$90*Pressupostos!$C$95/365 -> 519386.3 | G9: =Volumes!G10*1000*((Custos!G6+Custos!G9)*Pressupostos!$C$70/365)+Volumes!G11*1000*((Custos!G30+Custos!G33)*Pressupostos!$C$70/365)+Volumes!G12*1000*((Custos!G54+Custos!G57)*Pressupostos!$C$70/365)+Volumes!G23*1000*Pressupostos!$C$90*Pressupostos!$C$95/365 -> 793232.88
A10: Capital de giro líquido | B10: € | C10: =C7+C8-C9 -> 45498.904 | D10: =D7+D8-D9 -> 276087.74 | E10: =E7+E8-E9 -> 500492.26 | F10: =F7+F8-F9 -> 866764.73 | G10: =G7+G8-G9 -> 1323907.8
A12: Financiamento do capital de giro (€)
A13: Obrigações em circulação (capital levantado nas séries) | B13: € | C13: =Pressupostos!$C$280*C10/Pressupostos!$G$31 -> 0 | D13: =Pressupostos!$D$280*D10/Pressupostos!$G$31 -> 310598.71 | E13: =Pressupostos!$E$280*E10/Pressupostos!$G$31 -> 563053.79 | F13: =Pressupostos!$F$280*F10/Pressupostos!$G$31 -> 975110.32 | G13: =Pressupostos!$G$280*G10/Pressupostos!$G$31 -> 1489396.3
A14: das quais aplicadas em stock e recebíveis | B14: € | C14: =Pressupostos!$C$280*C10 -> 0 | D14: =Pressupostos!$D$280*D10 -> 248478.97 | E14: =Pressupostos!$E$280*E10 -> 450443.03 | F14: =Pressupostos!$F$280*F10 -> 780088.25 | G14: =Pressupostos!$G$280*G10 -> 1191517
A15: Caixa parada nas séries (float de financiamento) | B15: € | C15: =C13-C14 -> 0 | D15: =D13-D14 -> 62119.741 | E15: =E13-E14 -> 112610.76 | F15: =F13-F14 -> 195022.06 | G15: =G13-G14 -> 297879.26
A16: Capital de giro financiado por capital próprio | B16: € | C16: =C10-C14 -> 45498.904 | D16: =D10-D14 -> 27608.774 | E16: =E10-E14 -> 50049.226 | F16: =F10-F14 -> 86676.473 | G16: =G10-G14 -> 132390.78
A17: Capital social da SPV ainda em caixa (não aplicado em stock) | B17: € | C17: =MAX(0,Pressupostos!$C$106-C16) -> 4501.0959 | D17: =MAX(0,Pressupostos!$C$106-D16) -> 22391.226 | E17: =MAX(0,Pressupostos!$C$106-E16) -> 0 | F17: =MAX(0,Pressupostos!$C$106-F16) -> 0 | G17: =MAX(0,Pressupostos!$C$106-G16) -> 0
A18: Reserva de primeira perda (caixa restrita, 5% das obrigações) | B18: € | C18: =Pressupostos!$C$107*C13 -> 0 | D18: =Pressupostos!$C$107*D13 -> 15529.935 | E18: =Pressupostos!$C$107*E13 -> 28152.69 | F18: =Pressupostos!$C$107*F13 -> 48755.516 | G18: =Pressupostos!$C$107*G13 -> 74469.814
A19: Investidores estimados (obrigações ÷ ticket médio) | B19: n.º | C19: =C13/Pressupostos!$C$110 -> 0 | D19: =D13/Pressupostos!$C$110 -> 6.2119741 | E19: =E13/Pressupostos!$C$110 -> 11.261076 | F19: =F13/Pressupostos!$C$110 -> 19.502206 | G19: =G13/Pressupostos!$C$110 -> 29.787926
A21: Cash flow (€)
A22: EBITDA | B22: € | C22: =DR!C15 -> -711437.45 | D22: =DR!D15 -> -801413.48 | E22: =DR!E15 -> -969909.99 | F22: =DR!F15 -> -1094156.3 | G22: =DR!G15 -> -1219975.9
A23: Imposto pago (no próprio ano; simplificação) | B23: € | C23: =-DR!C31 -> 0 | D23: =-DR!D31 -> 0 | E23: =-DR!E31 -> 0 | F23: =-DR!F31 -> 0 | G23: =-DR!G31 -> 0
A24: Variação do capital de giro | B24: € | C24: =-C10 -> -45498.904 | D24: =-(D10-C10) -> -230588.84 | E24: =-(E10-D10) -> -224404.52 | F24: =-(F10-E10) -> -366272.47 | G24: =-(G10-F10) -> -457143.08
A25: Capex | B25: € | C25: =-Custos!C116 -> -92000 | D25: =-Custos!D116 -> -44000 | E25: =-Custos!E116 -> -48000 | F25: =-Custos!F116 -> -38000 | G25: =-Custos!G116 -> -38000
A26: Cash flow operacional e de investimento | B26: € | C26: =C22+C23+C24+C25 -> -848936.36 | D26: =D22+D23+D24+D25 -> -1076002.3 | E26: =E22+E23+E24+E25 -> -1242314.5 | F26: =F22+F23+F24+F25 -> -1498428.7 | G26: =G22+G23+G24+G25 -> -1715119
A27: Emissão líquida de obrigações | B27: € | C27: =C13 -> 0 | D27: =D13-C13 -> 310598.71 | E27: =E13-D13 -> 252455.09 | F27: =F13-E13 -> 412056.52 | G27: =G13-F13 -> 514285.97
A28: Variação da caixa parada nas séries | B28: € | C28: =-C15 -> 0 | D28: =-(D15-C15) -> -62119.741 | E28: =-(E15-D15) -> -50491.017 | F28: =-(F15-E15) -> -82411.305 | G28: =-(G15-F15) -> -102857.19
A29: Variação da reserva de primeira perda | B29: € | C29: =-C18 -> 0 | D29: =-(D18-C18) -> -15529.935 | E29: =-(E18-D18) -> -12622.754 | F29: =-(F18-E18) -> -20602.826 | G29: =-(G18-F18) -> -25714.298
A30: Capital social da SPV aplicado em stock | B30: € | C30: =-(C17-Pressupostos!$C$106) -> 45498.904 | D30: =-(D17-C17) -> -17890.13 | E30: =-(E17-D17) -> 22391.226 | F30: =-(F17-E17) -> 0 | G30: =-(G17-F17) -> 0
A31: Cash flow para o acionista | B31: € | C31: =C26+C27+C28+C29+C30 -> -803437.45 | D31: =D26+D27+D28+D29+D30 -> -860943.41 | E31: =E26+E27+E28+E29+E30 -> -1030582 | F31: =F26+F27+F28+F29+F30 -> -1189386.3 | G31: =G26+G27+G28+G29+G30 -> -1329404.5
A32: Cash flow para o acionista acumulado | B32: € | C32: =C31 -> -803437.45 | D32: =C32+D31 -> -1664380.9 | E32: =D32+E31 -> -2694962.8 | F32: =E32+F31 -> -3884349.2 | G32: =F32+G31 -> -5213753.7
A33: Verificação: EBITDA − capex − imposto − Δ max(capital próprio no giro; capital SPV) − Δ reserva − cash flow | B33: € | C33: =ROUND(DR!C15-Custos!C116-DR!C31-(MAX(C16,Pressupostos!$C$106)-Pressupostos!$C$106)-(C18)-C31,6) -> 0 | D33: =ROUND(DR!D15-Custos!D116-DR!D31-(MAX(D16,Pressupostos!$C$106)-MAX(C16,Pressupostos!$C$106))-(D18-C18)-D31,6) -> 0 | E33: =ROUND(DR!E15-Custos!E116-DR!E31-(MAX(E16,Pressupostos!$C$106)-MAX(D16,Pressupostos!$C$106))-(E18-D18)-E31,6) -> 0 | F33: =ROUND(DR!F15-Custos!F116-DR!F31-(MAX(F16,Pressupostos!$C$106)-MAX(E16,Pressupostos!$C$106))-(F18-E18)-F31,6) -> 0 | G33: =ROUND(DR!G15-Custos!G116-DR!G31-(MAX(G16,Pressupostos!$C$106)-MAX(F16,Pressupostos!$C$106))-(G18-F18)-G31,6) -> 0
A35: Caixa e rondas de capital (€)
A36: Caixa livre no início do ano | B36: € | C36: =0 -> 0 | D36: =C41 -> 151562.55 | E36: =D41 -> 150000 | F36: =E41 -> 150000 | G36: =F41 -> 150000
A37: Pré-arranque (4.º trim. 2026) e capital social da SPV | B37: € | C37: =-(Pressupostos!$C$157+Pressupostos!$C$158+Pressupostos!$C$159+Pressupostos!$C$160+Pressupostos!$C$161+Pressupostos!$C$106) -> -145000 | D37: =0 -> 0 | E37: =0 -> 0 | F37: =0 -> 0 | G37: =0 -> 0
A38: Ronda pré-seed | B38: € | C38: =Pressupostos!$G$32 -> 1100000 | D38: =0 -> 0 | E38: =0 -> 0 | F38: =0 -> 0 | G38: =0 -> 0
A39: Caixa antes de rondas adicionais | B39: € | C39: =C36+C37+C38+C31 -> 151562.55 | D39: =D36+D37+D38+D31 -> -709380.87 | E39: =E36+E37+E38+E31 -> -880581.97 | F39: =F36+F37+F38+F31 -> -1039386.3 | G39: =G36+G37+G38+G31 -> -1179404.5
A40: Ronda adicional necessária para manter a caixa mínima | B40: € | C40: =MAX(0,Pressupostos!$C$168-C39) -> 0 | D40: =MAX(0,Pressupostos!$C$168-D39) -> 859380.87 | E40: =MAX(0,Pressupostos!$C$168-E39) -> 1030582 | F40: =MAX(0,Pressupostos!$C$168-F39) -> 1189386.3 | G40: =MAX(0,Pressupostos!$C$168-G39) -> 1329404.5
A41: Caixa livre no fim do ano | B41: € | C41: =C39+C40 -> 151562.55 | D41: =D39+D40 -> 150000 | E41: =E39+E40 -> 150000 | F41: =F39+F40 -> 150000 | G41: =G39+G40 -> 150000
A42: Caixa restrita (séries, reserva, capital da SPV) | B42: € | C42: =C15+C18+C17 -> 4501.0959 | D42: =D15+D18+D17 -> 100040.9 | E42: =E15+E18+E17 -> 140763.45 | F42: =F15+F18+F17 -> 243777.58 | G42: =G15+G18+G17 -> 372349.07
A43: Caixa total | B43: € | C43: =C41+C42 -> 156063.64 | D43: =D41+D42 -> 250040.9 | E43: =E41+E42 -> 290763.45 | F43: =F41+F42 -> 393777.58 | G43: =G41+G42 -> 522349.07
A44: Capital próprio levantado (acumulado) | B44: € | C44: =C38+C40 -> 1100000 | D44: =C44+D38+D40 -> 1959380.9 | E44: =D44+E38+E40 -> 2989962.8 | F44: =E44+F38+F40 -> 4179349.2 | G44: =F44+G38+G40 -> 5508753.7

Sheet Capital & financiamento
A1: Capital & financiamento
A2: Necessidade de capital, aplicação de fundos, runway, break-even, investidores e o que tem de ser verdade (cenário ativo).
A3: ="Cenário ativo: "&Pressupostos!$C$4&" · euros correntes, sem IVA" -> Cenário ativo: Base · euros correntes, sem IVA
A4: Rubrica | B4: Unidade | C4: 2027 | D4: 2028 | E4: 2029 | F4: 2030 | G4: 2031 | H4: Notas
A5: Necessidade de capital próprio
A6: Pré-arranque (4.º trim. 2026) | B6: € | C6: =Pressupostos!$C$157+Pressupostos!$C$158+Pressupostos!$C$159+Pressupostos!$C$160+Pressupostos!$C$161 -> 95000
A7: Capital social da SPV | B7: € | C7: =Pressupostos!$C$106 -> 50000
A8: Caixa mínima operacional | B8: € | C8: =Pressupostos!$C$168 -> 150000
A9: Vale do cash flow acumulado para o acionista | B9: € | C9: =MAX(0,-MIN('Cash flow'!$C$32:$G$32)) -> 5213753.7
A10: Necessidade de capital próprio (pico no horizonte) | B10: € | C10: =C6+C7+C8+C9 -> 5508753.7
A11: Ano do mínimo do cash flow acumulado | B11: ano | C11: =INDEX(Volumes!$C$6:$G$6,1,MATCH(MIN('Cash flow'!$C$32:$G$32),'Cash flow'!$C$32:$G$32,0)) -> 2031
A12: O acumulado ainda desce em 2031? | C12: =IF('Cash flow'!G31<0,"sim","não") -> sim
A13: Capital próprio levantado no plano (pré-seed + rondas adicionais) | B13: € | C13: ='Cash flow'!G44 -> 5508753.7
A15: Aplicação de fundos até ao ano do mínimo (€)
A16: Pré-arranque e capital social da SPV | B16: € | C16: =C6+C7 -> 145000
A17: Perdas operacionais (EBITDA negativo acumulado) | B17: € | C17: =-SUMPRODUCT((Volumes!$C$6:$G$6<=C11)*DR!$C$15:$G$15) -> 4796893.1
A18: Capex | B18: € | C18: =SUMPRODUCT((Volumes!$C$6:$G$6<=C11)*Custos!$C$116:$G$116) -> 260000
A19: Impostos | B19: € | C19: =SUMPRODUCT((Volumes!$C$6:$G$6<=C11)*DR!$C$31:$G$31) -> 0
A20: Capital de giro, reserva e caixa das séries a cargo do capital próprio | B20: € | C20: =C9-C17-C18-C19 -> 156860.6
A21: Caixa mínima operacional | B21: € | C21: =C8 -> 150000
A22: Total = necessidade de capital próprio | B22: € | C22: =C16+C17+C18+C19+C20+C21 -> 5508753.7
A24: Pré-seed, runway e gate
A25: Ronda pré-seed | B25: € | C25: =Pressupostos!$G$32 -> 1100000
A26: Gasto até ao gate de 31-08-2027 (pré-arranque, SPV, opex jan.–ago., capex, stock do piloto) | B26: € | C26: =C6+Pressupostos!$C$106+Pressupostos!$C$128/12*((Pessoal!C33-Pessoal!C21-Pessoal!C22+(Pessoal!C21+Pessoal!C22)/Pressupostos!$C$126*Pressupostos!$C$127)*(1+Pressupostos!$C$122+Pressupostos!$C$123)+Pessoal!C18*Pressupostos!$C$124+Custos!C110)+Custos!C116+MAX(0,Pressupostos!$C$181*1000*(Custos!C6+Custos!C9)+Pressupostos!$C$182*1000*(Custos!C30+Custos!C33)-Pressupostos!$C$106) -> 734421.67 | H26: 01 §5.5: ~0,74 M€ no base
A27: Gasto até 31-12-2027 (pré-arranque, SPV e cash flow de 2027) | B27: € | C27: =C6+Pressupostos!$C$106-'Cash flow'!C31 -> 948437.45
A28: Caixa sem rondas adicionais (pré-seed − pré-arranque − SPV + cash flow acumulado) | B28: € | C28: =Pressupostos!$G$32-C6-Pressupostos!$C$106+'Cash flow'!C32 -> 151562.55 | D28: =Pressupostos!$G$32-C6-Pressupostos!$C$106+'Cash flow'!D32 -> -709380.87 | E28: =Pressupostos!$G$32-C6-Pressupostos!$C$106+'Cash flow'!E32 -> -1739962.8 | F28: =Pressupostos!$G$32-C6-Pressupostos!$C$106+'Cash flow'!F32 -> -2929349.2 | G28: =Pressupostos!$G$32-C6-Pressupostos!$C$106+'Cash flow'!G32 -> -4258753.7
A29: Mês em que a caixa sem rondas adicionais chega a zero (1 = jan. 2027) | B29: mês | C29: =IF(AND(Pressupostos!$G$32-C6-Pressupostos!$C$106>0,C28<=0),12*(Pressupostos!$G$32-C6-Pressupostos!$C$106)/(Pressupostos!$G$32-C6-Pressupostos!$C$106-C28),"") | D29: =IF(AND(C28>0,D28<=0),12+12*C28/(C28-D28),"") -> 14.112509 | E29: =IF(AND(D28>0,E28<=0),24+12*D28/(D28-E28),"") | F29: =IF(AND(E28>0,F28<=0),36+12*E28/(E28-F28),"") | G29: =IF(AND(F28>0,G28<=0),48+12*F28/(F28-G28),"")
A30: Runway da pré-seed (meses desde jan. 2027; sem rondas adicionais) | B30: meses | C30: =IF(COUNT($C$29:$G$29)=0,"> 60",MIN($C$29:$G$29)) -> 14.112509
A32: Break-even
A33: Cruzamento do EBITDA mensal (run-rate) com zero (mês; 1 = jan. 2027) | B33: mês | C33: =IF(DR!C15>=0,1,"") | D33: =IF(AND(DR!C15<0,DR!D15>=0),6.5+12*(-DR!C15)/(DR!D15-DR!C15),"") | E33: =IF(AND(DR!D15<0,DR!E15>=0),18.5+12*(-DR!D15)/(DR!E15-DR!D15),"") | F33: =IF(AND(DR!E15<0,DR!F15>=0),30.5+12*(-DR!E15)/(DR!F15-DR!E15),"") | G33: =IF(AND(DR!F15<0,DR!G15>=0),42.5+12*(-DR!F15)/(DR!G15-DR!F15),"")
A34: Mês de break-even do EBITDA (run-rate; 1 = jan. 2027) | B34: mês | C34: =IF(COUNT($C$33:$G$33)=0,"não atinge até 2031",ROUNDUP(MIN($C$33:$G$33),0)) -> não atinge até 2031
A35: Break-even do EBITDA (mês) | B35: data | C35: =IF(ISNUMBER(C34),DATE(2027,C34,1),"não atinge até 2031") -> não atinge até 2031
A36: Anos com EBITDA ≥ 0 | B36: ano | C36: =IF(DR!C15>=0,Volumes!C6,"") | D36: =IF(DR!D15>=0,Volumes!D6,"") | E36: =IF(DR!E15>=0,Volumes!E6,"") | F36: =IF(DR!F15>=0,Volumes!F6,"") | G36: =IF(DR!G15>=0,Volumes!G6,"")
A37: 1.º ano com EBITDA ≥ 0 | B37: ano | C37: =IF(COUNT($C$36:$G$36)=0,"não atinge até 2031",MIN($C$36:$G$36)) -> não atinge até 2031
A38: Anos com resultado líquido ≥ 0 | B38: ano | C38: =IF(DR!C35>=0,Volumes!C6,"") | D38: =IF(DR!D35>=0,Volumes!D6,"") | E38: =IF(DR!E35>=0,Volumes!E6,"") | F38: =IF(DR!F35>=0,Volumes!F6,"") | G38: =IF(DR!G35>=0,Volumes!G6,"")
A39: 1.º ano com resultado líquido ≥ 0 | B39: ano | C39: =IF(COUNT($C$38:$G$38)=0,"não atinge até 2031",MIN($C$38:$G$38)) -> não atinge até 2031
A40: Anos com cash flow para o acionista ≥ 0 | B40: ano | C40: =IF('Cash flow'!C31>=0,Volumes!C6,"") | D40: =IF('Cash flow'!D31>=0,Volumes!D6,"") | E40: =IF('Cash flow'!E31>=0,Volumes!E6,"") | F40: =IF('Cash flow'!F31>=0,Volumes!F6,"") | G40: =IF('Cash flow'!G31>=0,Volumes!G6,"")
A41: 1.º ano com cash flow para o acionista ≥ 0 | B41: ano | C41: =IF(COUNT($C$40:$G$40)=0,"não atinge até 2031",MIN($C$40:$G$40)) -> não atinge até 2031
A43: Investidores (obrigações da Sprout Capital, SA)
A44: Obrigações em circulação | B44: € | C44: ='Cash flow'!C13 -> 0 | D44: ='Cash flow'!D13 -> 310598.71 | E44: ='Cash flow'!E13 -> 563053.79 | F44: ='Cash flow'!F13 -> 975110.32 | G44: ='Cash flow'!G13 -> 1489396.3
A45: Cupão bruto anual | B45: % | C45: =Pressupostos!$C$286 -> 0.08 | D45: =Pressupostos!$D$286 -> 0.08 | E45: =Pressupostos!$E$286 -> 0.075 | F45: =Pressupostos!$F$286 -> 0.07 | G45: =Pressupostos!$G$286 -> 0.07
A46: Cupão líquido para um particular residente (retenção de 28%) | B46: % | C46: =Pressupostos!$C$286*(1-Pressupostos!$C$109) -> 0.0576 | D46: =Pressupostos!$D$286*(1-Pressupostos!$C$109) -> 0.0576 | E46: =Pressupostos!$E$286*(1-Pressupostos!$C$109) -> 0.054 | F46: =Pressupostos!$F$286*(1-Pressupostos!$C$109) -> 0.0504 | G46: =Pressupostos!$G$286*(1-Pressupostos!$C$109) -> 0.0504
A47: Cupão pago no ano | B47: € | C47: =Custos!C93 -> 0 | D47: =Custos!D93 -> 23317.027 | E47: =Custos!E93 -> 38771.064 | F47: =Custos!F93 -> 62547.835 | G47: =Custos!G93 -> 95536.156
A48: Almofada de primeira perda (capital próprio no giro + reserva) em % das obrigações | B48: % | C48: =IF('Cash flow'!C13>0,('Cash flow'!C16+'Cash flow'!C18)/'Cash flow'!C13,0) -> 0 | D48: =IF('Cash flow'!D13>0,('Cash flow'!D16+'Cash flow'!D18)/'Cash flow'!D13,0) -> 0.13888889 | E48: =IF('Cash flow'!E13>0,('Cash flow'!E16+'Cash flow'!E18)/'Cash flow'!E13,0) -> 0.13888889 | F48: =IF('Cash flow'!F13>0,('Cash flow'!F16+'Cash flow'!F18)/'Cash flow'!F13,0) -> 0.13888889 | G48: =IF('Cash flow'!G13>0,('Cash flow'!G16+'Cash flow'!G18)/'Cash flow'!G13,0) -> 0.13888889
A49: Investidores estimados | B49: n.º | C49: ='Cash flow'!C19 -> 0 | D49: ='Cash flow'!D19 -> 6.2119741 | E49: ='Cash flow'!E19 -> 11.261076 | F49: ='Cash flow'!F19 -> 19.502206 | G49: ='Cash flow'!G19 -> 29.787926
A51: O que tem de ser verdade para EBITDA = 0 (uma alavanca de cada vez)
A52: Défice de EBITDA a cobrir | B52: € | C52: =MAX(0,-DR!C15) -> 711437.45 | D52: =MAX(0,-DR!D15) -> 801413.48 | E52: =MAX(0,-DR!E15) -> 969909.99 | F52: =MAX(0,-DR!F15) -> 1094156.3 | G52: =MAX(0,-DR!G15) -> 1219975.9
A53: Seguro de crédito acima do prémio mínimo? (1 = sim) | C53: =IF(AND(Volumes!C6>=Pressupostos!$C$118,Pressupostos!$C$116*(Receitas!C6+Receitas!C7)+Pressupostos!$C$117*Receitas!C8>Pressupostos!$C$298),1,0) -> 0 | D53: =IF(AND(Volumes!D6>=Pressupostos!$C$118,Pressupostos!$C$116*(Receitas!D6+Receitas!D7)+Pressupostos!$C$117*Receitas!D8>Pressupostos!$D$298),1,0) -> 1 | E53: =IF(AND(Volumes!E6>=Pressupostos!$C$118,Pressupostos!$C$116*(Receitas!E6+Receitas!E7)+Pressupostos!$C$117*Receitas!E8>Pressupostos!$E$298),1,0) -> 1 | F53: =IF(AND(Volumes!F6>=Pressupostos!$C$118,Pressupostos!$C$116*(Receitas!F6+Receitas!F7)+Pressupostos!$C$117*Receitas!F8>Pressupostos!$F$298),1,0) -> 1 | G53: =IF(AND(Volumes!G6>=Pressupostos!$C$118,Pressupostos!$C$116*(Receitas!G6+Receitas!G7)+Pressupostos!$C$117*Receitas!G8>Pressupostos!$G$298),1,0) -> 1
A54: Prémio adicional pago pelos distribuidores/exportadores | B54: €/kg | C54: =IF(Volumes!C11>0,C52/(Volumes!C11*1000*(1-Pressupostos!$G$22)*(1-Pressupostos!$G$25-C53*Pressupostos!$C$116)),"n/a") -> 13.722657 | D54: =IF(Volumes!D11>0,D52/(Volumes!D11*1000*(1-Pressupostos!$G$22)*(1-Pressupostos!$G$25-D53*Pressupostos!$C$116)),"n/a") -> 2.2233138 | E54: =IF(Volumes!E11>0,E52/(Volumes!E11*1000*(1-Pressupostos!$G$22)*(1-Pressupostos!$G$25-E53*Pressupostos!$C$116)),"n/a") -> 1.3622695 | F54: =IF(Volumes!F11>0,F52/(Volumes!F11*1000*(1-Pressupostos!$G$22)*(1-Pressupostos!$G$25-F53*Pressupostos!$C$116)),"n/a") -> 0.93141957 | G54: =IF(Volumes!G11>0,G52/(Volumes!G11*1000*(1-Pressupostos!$G$22)*(1-Pressupostos!$G$25-G53*Pressupostos!$C$116)),"n/a") -> 0.68635527
A55: Referência HoReCa documentada necessária | B55: €/kg | C55: =IF(Volumes!C10>0,Pressupostos!$G$15+C52/(Volumes!C10*1000*(1-Pressupostos!$G$16)*(1-Pressupostos!$G$18-C53*Pressupostos!$C$116)),"n/a") -> 105.0572 | D55: =IF(Volumes!D10>0,Pressupostos!$G$15+D52/(Volumes!D10*1000*(1-Pressupostos!$G$16)*(1-Pressupostos!$G$18-D53*Pressupostos!$C$116)),"n/a") -> 29.959566 | E55: =IF(Volumes!E10>0,Pressupostos!$G$15+E52/(Volumes!E10*1000*(1-Pressupostos!$G$16)*(1-Pressupostos!$G$18-E53*Pressupostos!$C$116)),"n/a") -> 13.834687 | F55: =IF(Volumes!F10>0,Pressupostos!$G$15+F52/(Volumes!F10*1000*(1-Pressupostos!$G$16)*(1-Pressupostos!$G$18-F53*Pressupostos!$C$116)),"n/a") -> 10.249286 | G55: =IF(Volumes!G10>0,Pressupostos!$G$15+G52/(Volumes!G10*1000*(1-Pressupostos!$G$16)*(1-Pressupostos!$G$18-G53*Pressupostos!$C$116)),"n/a") -> 8.9895634
A56: Margem do granel depois do seguro de crédito | B56: €/kg | C56: =Custos!C73-C53*Pressupostos!$C$117*Custos!C56 -> 0.058762329 | D56: =Custos!D73-D53*Pressupostos!$C$117*Custos!D56 -> 0.025571918 | E56: =Custos!E73-E53*Pressupostos!$C$117*Custos!E56 -> 0.027190068 | F56: =Custos!F73-F53*Pressupostos!$C$117*Custos!F56 -> 0.028808219 | G56: =Custos!G73-G53*Pressupostos!$C$117*Custos!G56 -> 0.028808219
A57: Volume de granel certificado necessário | B57: t | C57: =IF(C56>0,Volumes!C12+C52/(C56*1000),"n/a") -> 12107.033 | D57: =IF(D56>0,Volumes!D12+D52/(D56*1000),"n/a") -> 31339.592 | E57: =IF(E56>0,Volumes!E12+E52/(E56*1000),"n/a") -> 35671.48 | F57: =IF(F56>0,Volumes!F12+F52/(F56*1000),"n/a") -> 37980.698 | G57: =IF(G56>0,Volumes!G12+G52/(G56*1000),"n/a") -> 42348.189
A58: Corte necessário nos custos fixos (pessoal + opex sem seguro de crédito) | B58: % | C58: =C52/(Pessoal!C36+Custos!C107+Custos!C108) -> 0.98812734 | D58: =D52/(Pessoal!D36+Custos!D107+Custos!D108) -> 0.97302386 | E58: =E52/(Pessoal!E36+Custos!E107+Custos!E108) -> 0.90294182 | F58: =F52/(Pessoal!F36+Custos!F107+Custos!F108) -> 0.83834391 | G58: =G52/(Pessoal!G36+Custos!G107+Custos!G108) -> 0.78145886
A59: Margem líquida da verificação para terceiros por € de carteira | B59: % | C59: =Pressupostos!$C$99*Pressupostos!$C$100+Pressupostos!$C$101-Pressupostos!$G$30*Pressupostos!$C$102*Pressupostos!$C$100/(Pressupostos!$C$103*Pressupostos!$C$104) -> 0.0035428571 | D59: =Pressupostos!$C$99*Pressupostos!$C$100+Pressupostos!$C$101-Pressupostos!$G$30*Pressupostos!$C$102*Pressupostos!$C$100/(Pressupostos!$C$103*Pressupostos!$C$104) -> 0.0035428571 | E59: =Pressupostos!$C$99*Pressupostos!$C$100+Pressupostos!$C$101-Pressupostos!$G$30*Pressupostos!$C$102*Pressupostos!$C$100/(Pressupostos!$C$103*Pressupostos!$C$104) -> 0.0035428571 | F59: =Pressupostos!$C$99*Pressupostos!$C$100+Pressupostos!$C$101-Pressupostos!$G$30*Pressupostos!$C$102*Pressupostos!$C$100/(Pressupostos!$C$103*Pressupostos!$C$104) -> 0.0035428571 | G59: =Pressupostos!$C$99*Pressupostos!$C$100+Pressupostos!$C$101-Pressupostos!$G$30*Pressupostos!$C$102*Pressupostos!$C$100/(Pressupostos!$C$103*Pressupostos!$C$104) -> 0.0035428571
A60: Carteira de terceiros necessária | B60: € | C60: =IF(C59>0,Volumes!C26+C52/C59,"n/a") -> 2.0080896e+08 | D60: =IF(D59>0,Volumes!D26+D52/D59,"n/a") -> 2.2670542e+08 | E60: =IF(E59>0,Volumes!E26+E52/E59,"n/a") -> 2.7526492e+08 | F60: =IF(F59>0,Volumes!F26+F52/F59,"n/a") -> 3.1183443e+08 | G60: =IF(G59>0,Volumes!G26+G52/G59,"n/a") -> 3.4934804e+08

Sheet Cenários
A1: Cenários
A2: Os três cenários do documento-fonte (com as correções verificadas, sem ajustes) e o cenário Recomendado (reestruturado), lado a lado. Ligações ao Motor: não dependem do seletor.
A4: 1. Indicadores por ano
A5: Indicador | B5: Cenário | C5: 2027 | D5: 2028 | E5: 2029 | F5: 2030 | G5: 2031 | H5: Unidade
A6: Azeite transacionado | B6: Pessimista | C6: =Motor!C14 -> 40 | D6: =Motor!D14 -> 150 | E6: =Motor!E14 -> 300 | F6: =Motor!F14 -> 450 | G6: =Motor!G14 -> 600 | H6: t
B7: Base | C7: =Motor!C324 -> 60 | D7: =Motor!D324 -> 400 | E7: =Motor!E324 -> 850 | F7: =Motor!F324 -> 1450 | G7: =Motor!G324 -> 2200 | H7: t
B8: Otimista | C8: =Motor!C634 -> 80 | D8: =Motor!D634 -> 650 | E8: =Motor!E634 -> 1300 | F8: =Motor!F634 -> 2200 | G8: =Motor!G634 -> 3300 | H8: t
B9: Recomendado | C9: =Motor!C944 -> 60.2 | D9: =Motor!D944 -> 893.75 | E9: =Motor!E944 -> 2299 | F9: =Motor!F944 -> 3826.5 | G9: =Motor!G944 -> 5495 | H9: t
A10: GMV total | B10: Pessimista | C10: =Motor!C107 -> 188160 | D10: =Motor!D107 -> 643860 | E10: =Motor!E107 -> 1372160 | F10: =Motor!F107 -> 2101120 | G10: =Motor!G107 -> 2823480 | H10: €
B11: Base | C11: =Motor!C417 -> 307380 | D11: =Motor!D417 -> 1929195 | E11: =Motor!E417 -> 4300755 | F11: =Motor!F417 -> 7352745 | G11: =Motor!G417 -> 11142350 | H11: €
B12: Otimista | C12: =Motor!C727 -> 417600 | D12: =Motor!D727 -> 3353800 | E12: =Motor!E727 -> 6832000 | F12: =Motor!F727 -> 11648000 | G12: =Motor!G727 -> 17469500 | H12: €
B13: Recomendado | C13: =Motor!C1037 -> 285400 | D13: =Motor!D1037 -> 3642850 | E13: =Motor!E1037 -> 9205650 | F13: =Motor!F1037 -> 15491350 | G13: =Motor!G1037 -> 22483000 | H13: €
A14: Receita total | B14: Pessimista | C14: =Motor!C105 -> 172122 | D14: =Motor!D105 -> 643860 | E14: =Motor!E105 -> 1372160 | F14: =Motor!F105 -> 2111120 | G14: =Motor!G105 -> 2843480 | H14: €
B15: Base | C15: =Motor!C415 -> 267690 | D15: =Motor!D415 -> 1780435 | E15: =Motor!E415 -> 4066155 | F15: =Motor!F415 -> 7052305 | G15: =Motor!G415 -> 10796070 | H15: €
B16: Otimista | C16: =Motor!C725 -> 370458 | D16: =Motor!D725 -> 3164280 | E16: =Motor!E725 -> 6509150 | F16: =Motor!F725 -> 11221820 | G16: =Motor!G725 -> 16943800 | H16: €
B17: Recomendado | C17: =Motor!C1035 -> 275874.4 | D17: =Motor!D1035 -> 3617129 | E17: =Motor!E1035 -> 9140394 | F17: =Motor!F1035 -> 15394652 | G17: =Motor!G1035 -> 22374860 | H17: €
A18: — vendas de azeite HoReCa/gourmet | B18: Pessimista | C18: =Motor!C96 -> 29160 | D18: =Motor!D96 -> 102060 | E18: =Motor!E96 -> 247860 | F18: =Motor!F96 -> 398520 | G18: =Motor!G96 -> 500580 | H18: €
B19: Base | C19: =Motor!C406 -> 40680 | D19: =Motor!D406 -> 188145 | E19: =Motor!E406 -> 676305 | F19: =Motor!F406 -> 1357695 | G19: =Motor!G406 -> 2084850 | H19: €
B20: Otimista | C20: =Motor!C716 -> 54000 | D20: =Motor!D716 -> 334800 | E20: =Motor!E716 -> 1107000 | F20: =Motor!F716 -> 2214000 | G20: =Motor!G716 -> 3321000 | H20: €
B21: Recomendado | C21: =Motor!C1026 -> 44280 | D21: =Motor!D1026 -> 166050 | E21: =Motor!E1026 -> 442800 | F21: =Motor!F1026 -> 774900 | G21: =Motor!G1026 -> 1107000 | H21: €
A22: — vendas de azeite a distribuidores/exportação | B22: Pessimista | C22: =Motor!C97 -> 142800 | D22: =Motor!D97 -> 541800 | E22: =Motor!E97 -> 1045800 | F22: =Motor!F97 -> 1545600 | G22: =Motor!G97 -> 2087400 | H22: €
B23: Base | C23: =Motor!C407 -> 226200 | D23: =Motor!D407 -> 1579050 | E23: =Motor!E407 -> 3118950 | F23: =Motor!F407 -> 5146050 | G23: =Motor!G407 -> 7786500 | H23: €
B24: Otimista | C24: =Motor!C717 -> 315000 | D24: =Motor!D717 -> 2646000 | E24: =Motor!E717 -> 4927500 | F24: =Motor!F717 -> 8055000 | G24: =Motor!G717 -> 12082500 | H24: €
B25: Recomendado | C25: =Motor!C1027 -> 231400 | D25: =Motor!D1027 -> 1615350 | E25: =Motor!E1027 -> 3190650 | F25: =Motor!F1027 -> 5264350 | G25: =Motor!G1027 -> 7965500 | H25: €
A26: — vendas de granel certificado | B26: Pessimista | C26: =Motor!C98 -> 0 | D26: =Motor!D98 -> 0 | E26: =Motor!E98 -> 0 | F26: =Motor!F98 -> 0 | G26: =Motor!G98 -> 0 | H26: €
B27: Base | C27: =Motor!C408 -> 0 | D27: =Motor!D408 -> 0 | E27: =Motor!E408 -> 0 | F27: =Motor!F408 -> 0 | G27: =Motor!G408 -> 0 | H27: €
B28: Otimista | C28: =Motor!C718 -> 0 | D28: =Motor!D718 -> 0 | E28: =Motor!E718 -> 0 | F28: =Motor!F718 -> 0 | G28: =Motor!G718 -> 0 | H28: €
B29: Recomendado | C29: =Motor!C1028 -> 0 | D29: =Motor!D1028 -> 1825000 | E29: =Motor!E1028 -> 5475000 | F29: =Motor!F1028 -> 9125000 | G29: =Motor!G1028 -> 12775000 | H29: €
A30: — vendas de café verde | B30: Pessimista | C30: =Motor!C100 -> 0 | D30: =Motor!D100 -> 0 | E30: =Motor!E100 -> 78500 | F30: =Motor!F100 -> 157000 | G30: =Motor!G100 -> 235500 | H30: €
B31: Base | C31: =Motor!C410 -> 0 | D31: =Motor!D410 -> 0 | E31: =Motor!E410 -> 235500 | F31: =Motor!F410 -> 471000 | G31: =Motor!G410 -> 785000 | H31: €
B32: Otimista | C32: =Motor!C720 -> 0 | D32: =Motor!D720 -> 157000 | E32: =Motor!E720 -> 392500 | F32: =Motor!F720 -> 785000 | G32: =Motor!G720 -> 1256000 | H32: €
B33: Recomendado | C33: =Motor!C1030 -> 0 | D33: =Motor!D1030 -> 0 | E33: =Motor!E1030 -> 0 | F33: =Motor!F1030 -> 157000 | G33: =Motor!G1030 -> 392500 | H33: €
A34: — comissões de água | B34: Pessimista | C34: =Motor!C102 -> 162 | D34: =Motor!D102 -> 0 | E34: =Motor!E102 -> 0 | F34: =Motor!F102 -> 0 | G34: =Motor!G102 -> 0 | H34: €
B35: Base | C35: =Motor!C412 -> 810 | D35: =Motor!D412 -> 3240 | E35: =Motor!E412 -> 5400 | F35: =Motor!F412 -> 7560 | G35: =Motor!G412 -> 9720 | H35: €
B36: Otimista | C36: =Motor!C722 -> 1458 | D36: =Motor!D722 -> 6480 | E36: =Motor!E722 -> 12150 | F36: =Motor!F722 -> 17820 | G36: =Motor!G722 -> 24300 | H36: €
B37: Recomendado | C37: =Motor!C1032 -> 194.4 | D37: =Motor!D1032 -> 729 | E37: =Motor!E1032 -> 1944 | F37: =Motor!F1032 -> 3402 | G37: =Motor!G1032 -> 4860 | H37: €
A38: — verificação para terceiros | B38: Pessimista | C38: =Motor!C103 -> 0 | D38: =Motor!D103 -> 0 | E38: =Motor!E103 -> 0 | F38: =Motor!F103 -> 10000 | G38: =Motor!G103 -> 20000 | H38: €
B39: Base | C39: =Motor!C413 -> 0 | D39: =Motor!D413 -> 10000 | E39: =Motor!E413 -> 30000 | F39: =Motor!F413 -> 60000 | G39: =Motor!G413 -> 100000 | H39: €
B40: Otimista | C40: =Motor!C723 -> 0 | D40: =Motor!D723 -> 20000 | E40: =Motor!E723 -> 60000 | F40: =Motor!F723 -> 120000 | G40: =Motor!G723 -> 200000 | H40: €
B41: Recomendado | C41: =Motor!C1033 -> 0 | D41: =Motor!D1033 -> 10000 | E41: =Motor!E1033 -> 30000 | F41: =Motor!F1033 -> 60000 | G41: =Motor!G1033 -> 100000 | H41: €
A42: — dados e índice | B42: Pessimista | C42: =Motor!C104 -> 0 | D42: =Motor!D104 -> 0 | E42: =Motor!E104 -> 0 | F42: =Motor!F104 -> 0 | G42: =Motor!G104 -> 0 | H42: €
B43: Base | C43: =Motor!C414 -> 0 | D43: =Motor!D414 -> 0 | E43: =Motor!E414 -> 0 | F43: =Motor!F414 -> 10000 | G43: =Motor!G414 -> 30000 | H43: €
B44: Otimista | C44: =Motor!C724 -> 0 | D44: =Motor!D724 -> 0 | E44: =Motor!E724 -> 10000 | F44: =Motor!F724 -> 30000 | G44: =Motor!G724 -> 60000 | H44: €
B45: Recomendado | C45: =Motor!C1034 -> 0 | D45: =Motor!D1034 -> 0 | E45: =Motor!E1034 -> 0 | F45: =Motor!F1034 -> 10000 | G45: =Motor!G1034 -> 30000 | H45: €
A46: Margem bruta | B46: Pessimista | C46: =Motor!C200 -> 7522 | D46: =Motor!D200 -> 26760 | E46: =Motor!E200 -> 67060 | F46: =Motor!F200 -> 117920 | G46: =Motor!G200 -> 163180 | H46: €
B47: Base | C47: =Motor!C510 -> 23890 | D47: =Motor!D510 -> 156735 | E47: =Motor!E510 -> 400355 | F47: =Motor!F510 -> 733105 | G47: =Motor!G510 -> 1145070 | H47: €
B48: Otimista | C48: =Motor!C820 -> 49458 | D48: =Motor!D820 -> 418080 | E48: =Motor!E820 -> 938650 | F48: =Motor!F820 -> 1680820 | G48: =Motor!G820 -> 2562300 | H48: €
B49: Recomendado | C49: =Motor!C1130 -> 30834.4 | D49: =Motor!D1130 -> 267829 | E49: =Motor!E1130 -> 642144 | F49: =Motor!F1130 -> 1110802 | G49: =Motor!G1130 -> 1664360 | H49: €
A50: Margem de contribuição | B50: Pessimista | C50: =Motor!C122 -> -3800.3467 | D50: =Motor!D122 -> -29750.552 | E50: =Motor!E122 -> -53805.848 | F50: =Motor!F122 -> -65150.688 | G50: =Motor!G122 -> -79079.842 | H50: €
B51: Base | C51: =Motor!C432 -> 8548.1419 | D51: =Motor!D432 -> 29287.189 | E51: =Motor!E432 -> 119437.67 | F51: =Motor!F432 -> 236998.83 | G51: =Motor!G432 -> 380661.3 | H51: €
B52: Otimista | C52: =Motor!C742 -> 29375.612 | D52: =Motor!D742 -> 225646.64 | E52: =Motor!E742 -> 530196.17 | F52: =Motor!F742 -> 957600.56 | G52: =Motor!G742 -> 1458148.7 | H52: €
B53: Recomendado | C53: =Motor!C1052 -> 15340.177 | D53: =Motor!D1052 -> 91070.391 | E53: =Motor!E1052 -> 244474.43 | F53: =Motor!F1052 -> 450613.38 | G53: =Motor!G1052 -> 698395.68 | H53: €
A54: Margem média do azeite | B54: Pessimista | C54: =Motor!C115 -> -0.099058667 | D54: =Motor!D115 -> -0.19833701 | E54: =Motor!E115 -> -0.19697232 | F54: =Motor!F115 -> -0.17220848 | G54: =Motor!G115 -> -0.16413375 | H54: €/kg
B55: Base | C55: =Motor!C425 -> 0.12896903 | D55: =Motor!D425 -> 0.060689402 | E55: =Motor!E425 -> 0.10849517 | F55: =Motor!F425 -> 0.12104414 | G55: =Motor!G425 -> 0.12169693 | H55: €/kg
B56: Otimista | C56: =Motor!C735 -> 0.34897015 | D56: =Motor!D735 -> 0.31467147 | E56: =Motor!E735 -> 0.36113141 | F56: =Motor!F735 -> 0.37826045 | G56: =Motor!G735 -> 0.37826045 | H56: €/kg
B57: Recomendado | C57: =Motor!C1045 -> 0.25159099 | D57: =Motor!D1045 -> 0.089892466 | E57: =Motor!E1045 -> 0.092444727 | F57: =Motor!F1045 -> 0.09578796 | G57: =Motor!G1045 -> 0.097695869 | H57: €/kg
A58: Pessoal | B58: Pessimista | C58: =Motor!C171 -> 400885.59 | D58: =Motor!D171 -> 456091.72 | E58: =Motor!E171 -> 469774.48 | F58: =Motor!F171 -> 515877.78 | G58: =Motor!G171 -> 531354.12 | H58: €
B59: Base | C59: =Motor!C481 -> 400885.59 | D59: =Motor!D481 -> 508017.89 | E59: =Motor!E481 -> 667701.29 | F59: =Motor!F481 -> 855745.93 | G59: =Motor!G481 -> 1042442 | H59: €
B60: Otimista | C60: =Motor!C791 -> 400885.59 | D60: =Motor!D791 -> 699532.22 | E60: =Motor!E791 -> 948461.84 | F60: =Motor!F791 -> 1229685.3 | G60: =Motor!G791 -> 1625549.9 | H60: €
B61: Recomendado | C61: =Motor!C1101 -> 303573.09 | D61: =Motor!D1101 -> 477845.33 | E61: =Motor!E1101 -> 563341.22 | F61: =Motor!F1101 -> 697007.53 | G61: =Motor!G1101 -> 768997.56 | H61: €
A62: Opex não salarial | B62: Pessimista | C62: =Motor!C187 -> 304400 | D62: =Motor!D187 -> 252142.44 | E62: =Motor!E187 -> 273364.76 | F62: =Motor!F187 -> 301201.5 | G62: =Motor!G187 -> 320847.53 | H62: €
B63: Base | C63: =Motor!C497 -> 319100 | D63: =Motor!D497 -> 322682.78 | E63: =Motor!E497 -> 421646.38 | F63: =Motor!F497 -> 475409.16 | G63: =Motor!G497 -> 558195.15 | H63: €
B64: Otimista | C64: =Motor!C807 -> 334850 | D64: =Motor!D807 -> 409649.2 | E64: =Motor!E807 -> 485854.68 | F64: =Motor!F807 -> 602439.95 | G64: =Motor!G807 -> 738758.51 | H64: €
B65: Recomendado | C65: =Motor!C1117 -> 298100 | D65: =Motor!D1117 -> 293188.6 | E65: =Motor!E1117 -> 374050.9 | F65: =Motor!F1117 -> 407116.78 | G65: =Motor!G1117 -> 458938.5 | H65: €
A66: EBITDA | B66: Pessimista | C66: =Motor!C207 -> -709085.94 | D66: =Motor!D207 -> -737984.72 | E66: =Motor!E207 -> -796945.08 | F66: =Motor!F207 -> -882229.97 | G66: =Motor!G207 -> -931281.49 | H66: €
B67: Base | C67: =Motor!C517 -> -711437.45 | D67: =Motor!D517 -> -801413.48 | E67: =Motor!E517 -> -969909.99 | F67: =Motor!F517 -> -1094156.3 | G67: =Motor!G517 -> -1219975.9 | H67: €
B68: Otimista | C68: =Motor!C827 -> -706359.98 | D68: =Motor!D827 -> -883534.78 | E68: =Motor!E827 -> -904120.35 | F68: =Motor!F827 -> -874524.69 | G68: =Motor!G827 -> -906159.63 | H68: €
B69: Recomendado | C69: =Motor!C1137 -> -586332.92 | D69: =Motor!D1137 -> -679963.53 | E69: =Motor!E1137 -> -692917.69 | F69: =Motor!F1137 -> -653510.93 | G69: =Motor!G1137 -> -529540.38 | H69: €
A70: Resultado líquido | B70: Pessimista | C70: =Motor!C225 -> -736185.94 | D70: =Motor!D225 -> -770084.72 | E70: =Motor!E225 -> -835245.08 | F70: =Motor!F225 -> -906979.97 | G70: =Motor!G225 -> -953731.49 | H70: €
B71: Base | C71: =Motor!C535 -> -738537.45 | D71: =Motor!D535 -> -841413.48 | E71: =Motor!E535 -> -1023810 | F71: =Motor!F535 -> -1138622.9 | G71: =Motor!G535 -> -1261509.2 | H71: €
B72: Otimista | C72: =Motor!C845 -> -733459.98 | D72: =Motor!D845 -> -931734.78 | E72: =Motor!E845 -> -971253.68 | F72: =Motor!F845 -> -937758.02 | G72: =Motor!G845 -> -967992.97 | H72: €
B73: Recomendado | C73: =Motor!C1155 -> -612682.92 | D73: =Motor!D1155 -> -719713.53 | E73: =Motor!E1155 -> -745567.69 | F73: =Motor!F1155 -> -696477.59 | G73: =Motor!G1155 -> -569323.71 | H73: €
A74: Cash flow para o acionista | B74: Pessimista | C74: =Motor!C250 -> -801085.94 | D74: =Motor!D250 -> -761346.02 | E74: =Motor!E250 -> -827766.83 | F74: =Motor!F250 -> -915690.81 | G74: =Motor!G250 -> -971191.05 | H74: €
B75: Base | C75: =Motor!C560 -> -803437.45 | D75: =Motor!D560 -> -860943.41 | E75: =Motor!E560 -> -1030582 | F75: =Motor!F560 -> -1189386.3 | G75: =Motor!G560 -> -1329404.5 | H75: €
B76: Otimista | C76: =Motor!C870 -> -800452.42 | D76: =Motor!D870 -> -972773.1 | E76: =Motor!E870 -> -1001686.2 | F76: =Motor!F870 -> -1005522.7 | G76: =Motor!G870 -> -1056003.1 | H76: €
B77: Recomendado | C77: =Motor!C1180 -> -678616.84 | D77: =Motor!D1180 -> -748866.74 | E77: =Motor!E1180 -> -816481.02 | F77: =Motor!F1180 -> -796741.77 | G77: =Motor!G1180 -> -686001.85 | H77: €
A78: Cash flow acumulado | B78: Pessimista | C78: =Motor!C251 -> -801085.94 | D78: =Motor!D251 -> -1562432 | E78: =Motor!E251 -> -2390198.8 | F78: =Motor!F251 -> -3305889.6 | G78: =Motor!G251 -> -4277080.6 | H78: €
B79: Base | C79: =Motor!C561 -> -803437.45 | D79: =Motor!D561 -> -1664380.9 | E79: =Motor!E561 -> -2694962.8 | F79: =Motor!F561 -> -3884349.2 | G79: =Motor!G561 -> -5213753.7 | H79: €
B80: Otimista | C80: =Motor!C871 -> -800452.42 | D80: =Motor!D871 -> -1773225.5 | E80: =Motor!E871 -> -2774911.7 | F80: =Motor!F871 -> -3780434.4 | G80: =Motor!G871 -> -4836437.5 | H80: €
B81: Recomendado | C81: =Motor!C1181 -> -678616.84 | D81: =Motor!D1181 -> -1427483.6 | E81: =Motor!E1181 -> -2243964.6 | F81: =Motor!F1181 -> -3040706.4 | G81: =Motor!G1181 -> -3726708.2 | H81: €
A82: Rondas adicionais necessárias (além da pré-seed) | B82: Pessimista | C82: =Motor!C258 -> 0 | D82: =Motor!D258 -> 757431.96 | E82: =Motor!E258 -> 827766.83 | F82: =Motor!F258 -> 915690.81 | G82: =Motor!G258 -> 971191.05 | H82: €
B83: Base | C83: =Motor!C568 -> 0 | D83: =Motor!D568 -> 859380.87 | E83: =Motor!E568 -> 1030582 | F83: =Motor!F568 -> 1189386.3 | G83: =Motor!G568 -> 1329404.5 | H83: €
B84: Otimista | C84: =Motor!C878 -> 0 | D84: =Motor!D878 -> 968225.52 | E84: =Motor!E878 -> 1001686.2 | F84: =Motor!F878 -> 1005522.7 | G84: =Motor!G878 -> 1056003.1 | H84: €
B85: Recomendado | C85: =Motor!C1188 -> 0 | D85: =Motor!D1188 -> 622483.58 | E85: =Motor!E1188 -> 816481.02 | F85: =Motor!F1188 -> 796741.77 | G85: =Motor!G1188 -> 686001.85 | H85: €
A86: Caixa livre no fim do ano | B86: Pessimista | C86: =Motor!C259 -> 153914.06 | D86: =Motor!D259 -> 150000 | E86: =Motor!E259 -> 150000 | F86: =Motor!F259 -> 150000 | G86: =Motor!G259 -> 150000 | H86: €
B87: Base | C87: =Motor!C569 -> 151562.55 | D87: =Motor!D569 -> 150000 | E87: =Motor!E569 -> 150000 | F87: =Motor!F569 -> 150000 | G87: =Motor!G569 -> 150000 | H87: €
B88: Otimista | C88: =Motor!C879 -> 154547.58 | D88: =Motor!D879 -> 150000 | E88: =Motor!E879 -> 150000 | F88: =Motor!F879 -> 150000 | G88: =Motor!G879 -> 150000 | H88: €
B89: Recomendado | C89: =Motor!C1189 -> 276383.16 | D89: =Motor!D1189 -> 150000 | E89: =Motor!E1189 -> 150000 | F89: =Motor!F1189 -> 150000 | G89: =Motor!G1189 -> 150000 | H89: €
A90: Obrigações em circulação | B90: Pessimista | C90: =Motor!C233 -> 0 | D90: =Motor!D233 -> 167226.11 | E90: =Motor!E233 -> 363660.94 | F90: =Motor!F233 -> 458964.74 | G90: =Motor!G233 -> 567935.07 | H90: €
B91: Base | C91: =Motor!C543 -> 0 | D91: =Motor!D543 -> 310598.71 | E91: =Motor!E543 -> 563053.79 | F91: =Motor!F543 -> 975110.32 | G91: =Motor!G543 -> 1489396.3 | H91: €
B92: Otimista | C92: =Motor!C853 -> 0 | D92: =Motor!D853 -> 366615.18 | E92: =Motor!E853 -> 691591.62 | F92: =Motor!F853 -> 1196962.6 | G92: =Motor!G853 -> 1805109.9 | H92: €
B93: Recomendado | C93: =Motor!C1163 -> 0 | D93: =Motor!D1163 -> 523742.58 | E93: =Motor!E1163 -> 1121403.3 | F93: =Motor!F1163 -> 1886265.3 | G93: =Motor!G1163 -> 2767987.9 | H93: €
A94: Valor de lotes financiado por obrigações (capital financiado) | B94: Pessimista | C94: =Motor!C109 -> 0 | D94: =Motor!D109 -> 524535 | E94: =Motor!E109 -> 1109335 | F94: =Motor!F109 -> 1694220 | G94: =Motor!G109 -> 2278255 | H94: €
B95: Base | C95: =Motor!C419 -> 0 | D95: =Motor!D419 -> 1461330 | E95: =Motor!E419 -> 3299220 | F95: =Motor!F419 -> 5687280 | G95: =Motor!G419 -> 8685900 | H95: €
B96: Otimista | C96: =Motor!C729 -> 0 | D96: =Motor!D729 -> 2471580 | E96: =Motor!E729 -> 5013450 | F96: =Motor!F729 -> 8586900 | G96: =Motor!G729 -> 12943350 | H96: €
B97: Recomendado | C97: =Motor!C1039 -> 0 | D97: =Motor!D1039 -> 3014370 | E97: =Motor!E1039 -> 7648425 | F97: =Motor!F1039 -> 12855465 | G97: =Motor!G1039 -> 18639450 | H97: €
A98: Investidores estimados | B98: Pessimista | C98: =Motor!C239 -> 0 | D98: =Motor!D239 -> 3.3445221 | E98: =Motor!E239 -> 7.2732188 | F98: =Motor!F239 -> 9.1792947 | G98: =Motor!G239 -> 11.358701 | H98: n.º
B99: Base | C99: =Motor!C549 -> 0 | D99: =Motor!D549 -> 6.2119741 | E99: =Motor!E549 -> 11.261076 | F99: =Motor!F549 -> 19.502206 | G99: =Motor!G549 -> 29.787926 | H99: n.º
B100: Otimista | C100: =Motor!C859 -> 0 | D100: =Motor!D859 -> 7.3323036 | E100: =Motor!E859 -> 13.831832 | F100: =Motor!F859 -> 23.939252 | G100: =Motor!G859 -> 36.102198 | H100: n.º
B101: Recomendado | C101: =Motor!C1169 -> 0 | D101: =Motor!D1169 -> 10.474852 | E101: =Motor!E1169 -> 22.428066 | F101: =Motor!F1169 -> 37.725307 | G101: =Motor!G1169 -> 55.359758 | H101: n.º
...

Sheet Sensibilidade
A1: Sensibilidade
A2: Base e Recomendado: desconto HoReCa, volumes e preço do AOVE (motor completo, recalculado por caso); tese literal do documento-fonte: captura da margem do embalador × desconto.
A4: Casos (inputs em Pressupostos)
A5: Sensibilidade: desconto HoReCa — caso 1 | B5: =Pressupostos!$C$189 -> 0.1
A6: Sensibilidade: desconto HoReCa — caso 2 | B6: =Pressupostos!$C$190 -> 0.125
A7: Sensibilidade: desconto HoReCa — caso 3 | B7: =Pressupostos!$C$191 -> 0.15
A8: Sensibilidade: volumes físicos — caso baixo | B8: =Pressupostos!$C$192 -> -0.3
A9: Sensibilidade: volumes físicos — caso alto | B9: =Pressupostos!$C$193 -> 0.3
A10: Sensibilidade: preço do AOVE (índice e referências de venda) | B10: =Pressupostos!$C$195 -> -0.3
A11: Caso combinado: prémio de origem pago por distribuidores/exportadores (topo) | B11: =Pressupostos!$C$194 -> 0.2
A12: Exposição aberta máxima (piloto; política back-to-back) | B12: =Pressupostos!$C$186 -> 0.15
A14: Cenário Base
A15: Caso | B15: Valor do caso | C15: Margem HoReCa 2029 (€/kg) | D15: EBITDA 2029 (€) | E15: EBITDA 2031 (€) | F15: Δ EBITDA 2031 vs. cenário (€) | G15: Cash flow acumulado 2031 (€) | H15: Necessidade de capital (€) | I15: Break-even do EBITDA
A16: Cenário (referência) | C16: =Motor!$E$356 -> 0.34713572 | D16: =Motor!$E$517 -> -969909.99 | E16: =Motor!$G$517 -> -1219975.9 | F16: =E16-E16 -> 0 | G16: =Motor!$G$561 -> -5213753.7 | H16: =Motor!$C$578 -> 5508753.7 | I16: =Motor!$C$600 -> não atinge até 2031
A17: Desconto HoReCa | B17: =Pressupostos!$C$189 -> 0.1 | C17: =Motor!$E$1286 -> 0.34713572 | D17: =Motor!$E$1447 -> -969909.99 | E17: =Motor!$G$1447 -> -1219975.9 | F17: =E17-E16 -> 0 | G17: =Motor!$G$1491 -> -5213753.7 | H17: =Motor!$C$1508 -> 5508753.7 | I17: =Motor!$C$1530 -> não atinge até 2031
A18: Desconto HoReCa | B18: =Pressupostos!$C$190 -> 0.125 | C18: =Motor!$E$1596 -> 0.20673322 | D18: =Motor!$E$1757 -> -988508.38 | E18: =Motor!$G$1757 -> -1277309.3 | F18: =E18-E16 -> -57333.375 | G18: =Motor!$G$1801 -> -5332451.6 | H18: =Motor!$C$1818 -> 5627451.6 | I18: =Motor!$C$1840 -> não atinge até 2031
A19: Desconto HoReCa | B19: =Pressupostos!$C$191 -> 0.15 | C19: =Motor!$E$1906 -> 0.066330719 | D19: =Motor!$E$2067 -> -1007106.8 | E19: =Motor!$G$2067 -> -1334642.6 | F19: =E19-E16 -> -114666.75 | G19: =Motor!$G$2111 -> -5451149.4 | H19: =Motor!$C$2128 -> 5746149.4 | I19: =Motor!$C$2150 -> não atinge até 2031
A20: Volumes físicos (estrutura fixa) | B20: =Pressupostos!$C$192 -> -0.3 | C20: =Motor!$E$2216 -> 0.34713572 | D20: =Motor!$E$2377 -> -999592.7 | E20: =Motor!$G$2377 -> -1308014.4 | F20: =E20-E16 -> -88038.483 | G20: =Motor!$G$2421 -> -5335221.8 | H20: =Motor!$C$2438 -> 5630221.8 | I20: =Motor!$C$2460 -> não atinge até 2031
A21: Volumes físicos (estrutura fixa) | B21: =Pressupostos!$C$193 -> 0.3 | C21: =Motor!$E$2526 -> 0.34713572 | D21: =Motor!$E$2687 -> -940227.28 | E21: =Motor!$G$2687 -> -1131937.4 | F21: =E21-E16 -> 88038.483 | G21: =Motor!$G$2731 -> -5092285.5 | H21: =Motor!$C$2748 -> 5387285.5 | I21: =Motor!$C$2770 -> não atinge até 2031
A22: Preço do AOVE (índice e referências; repasse proporcional) | B22: =Pressupostos!$C$195 -> -0.3 | C22: =Motor!$E$2836 -> -0.10156625 | D22: =Motor!$E$2997 -> -1193341.5 | E22: =Motor!$G$2997 -> -1813917.6 | F22: =E22-E16 -> -593941.71 | G22: =Motor!$G$3041 -> -6479296.7 | H22: =Motor!$C$3058 -> 6774296.7 | I22: =Motor!$C$3080 -> não atinge até 2031
A23: Topo dos intervalos: prémio de origem dos distribuidores, carteira de terceiros do otimista, volumes +30% | B23: =Pressupostos!$C$194 -> 0.2 | C23: =Motor!$E$3146 -> 0.34713572 | D23: =Motor!$E$3307 -> -749797.93 | E23: =Motor!$G$3307 -> -652080.93 | F23: =E23-E16 -> 567894.97 | G23: =Motor!$G$3351 -> -4005939.3 | H23: =Motor!$C$3368 -> 4300939.3 | I23: =Motor!$C$3390 -> não atinge até 2031
A25: Cenário Recomendado (reestruturado)
A26: Caso | B26: Valor do caso | C26: Margem HoReCa 2029 (€/kg) | D26: EBITDA 2029 (€) | E26: EBITDA 2031 (€) | F26: Δ EBITDA 2031 vs. cenário (€) | G26: Cash flow acumulado 2031 (€) | H26: Necessidade de capital (€) | I26: Break-even do EBITDA
A27: Cenário (referência) | C27: =Motor!$E$976 -> 0.60940548 | D27: =Motor!$E$1137 -> -692917.69 | E27: =Motor!$G$1137 -> -529540.38 | F27: =E27-E27 -> 0 | G27: =Motor!$G$1181 -> -3726708.2 | H27: =Motor!$C$1198 -> 4021708.2 | I27: =Motor!$C$1220 -> não atinge até 2031
A28: Desconto HoReCa | B28: =Pressupostos!$C$189 -> 0.1 | C28: =Motor!$E$3456 -> 0.60940548 | D28: =Motor!$E$3617 -> -692917.69 | E28: =Motor!$G$3617 -> -529540.38 | F28: =E28-E27 -> 0 | G28: =Motor!$G$3661 -> -3726708.2 | H28: =Motor!$C$3678 -> 4021708.2 | I28: =Motor!$C$3700 -> não atinge até 2031
A29: Desconto HoReCa | B29: =Pressupostos!$C$190 -> 0.125 | C29: =Motor!$E$3766 -> 0.46030548 | D29: =Motor!$E$3927 -> -705094.69 | E29: =Motor!$G$3927 -> -559982.88 | F29: =E29-E27 -> -30442.5 | G29: =Motor!$G$3971 -> -3795965.7 | H29: =Motor!$C$3988 -> 4090965.7 | I29: =Motor!$C$4010 -> não atinge até 2031
A30: Desconto HoReCa | B30: =Pressupostos!$C$191 -> 0.15 | C30: =Motor!$E$4076 -> 0.31120548 | D30: =Motor!$E$4237 -> -717271.69 | E30: =Motor!$G$4237 -> -590425.38 | F30: =E30-E27 -> -60885 | G30: =Motor!$G$4281 -> -3865223.3 | H30: =Motor!$C$4298 -> 4160223.3 | I30: =Motor!$C$4320 -> não atinge até 2031
A31: Volumes físicos (estrutura fixa) | B31: =Pressupostos!$C$192 -> -0.3 | C31: =Motor!$E$4386 -> 0.60940548 | D31: =Motor!$E$4547 -> -749614.88 | E31: =Motor!$G$4547 -> -681507.09 | F31: =E31-E27 -> -151966.7 | G31: =Motor!$G$4591 -> -3947191.7 | H31: =Motor!$C$4608 -> 4242191.7 | I31: =Motor!$C$4630 -> não atinge até 2031
A32: Volumes físicos (estrutura fixa) | B32: =Pressupostos!$C$193 -> 0.3 | C32: =Motor!$E$4696 -> 0.60940548 | D32: =Motor!$E$4857 -> -636220.5 | E32: =Motor!$G$4857 -> -377573.68 | F32: =E32-E27 -> 151966.7 | G32: =Motor!$G$4901 -> -3506224.7 | H32: =Motor!$C$4918 -> 3801224.7 | I32: =Motor!$C$4940 -> não atinge até 2031
A33: Preço do AOVE (índice e referências; repasse proporcional) | B33: =Pressupostos!$C$195 -> -0.3 | C33: =Motor!$E$5006 -> 0.066770514 | D33: =Motor!$E$5167 -> -872905.86 | E33: =Motor!$G$5167 -> -986868.06 | F33: =E33-E27 -> -457327.68 | G33: =Motor!$G$5211 -> -4664387.9 | H33: =Motor!$C$5228 -> 4959387.9 | I33: =Motor!$C$5250 -> não atinge até 2031
A34: Topo dos intervalos: prémio de origem dos distribuidores, carteira de terceiros do otimista, volumes +30% | B34: =Pressupostos!$C$194 -> 0.2 | C34: =Motor!$E$5316 -> 0.60940548 | D34: =Motor!$E$5477 -> -513662.97 | E34: =Motor!$G$5477 -> -46502.577 | F34: =E34-E27 -> 483037.8 | G34: =Motor!$G$5521 -> -2781762.1 | H34: =Motor!$C$5538 -> 3076762.1 | I34: =Motor!$C$5560 -> não atinge até 2031
A36: Tese literal do documento-fonte, lote HoReCa do base em 2029 (€/kg que sobram para a plataforma)
A37: Saldo = captura × margem do embalador − desconto × referência − cupão − custos diretos da plataforma
A38: Margem líquida do embalador: média de 3 campanhas (€/kg) | B38: =Pressupostos!$C$197 -> 0.297
A39: Desconto \ captura da margem do embalador | B39: =Pressupostos!$C$199 -> 0.8 | C39: =Pressupostos!$C$200 -> 0.85 | D39: =Pressupostos!$C$201 -> 0.9
A40: =Pressupostos!$C$189 -> 0.1 | B40: =B$39*Pressupostos!$C$197-$A40*Motor!$E$338-Motor!$E$354-(Motor!$E$342+Motor!$E$345+Motor!$E$346+Motor!$E$347+Motor!$E$348+Motor!$E$349+Motor!$E$350+Motor!$E$351+Motor!$E$352+Motor!$E$353) -> -0.63526428 | C40: =C$39*Pressupostos!$C$197-$A40*Motor!$E$338-Motor!$E$354-(Motor!$E$342+Motor!$E$345+Motor!$E$346+Motor!$E$347+Motor!$E$348+Motor!$E$349+Motor!$E$350+Motor!$E$351+Motor!$E$352+Motor!$E$353) -> -0.62041428 | D40: =D$39*Pressupostos!$C$197-$A40*Motor!$E$338-Motor!$E$354-(Motor!$E$342+Motor!$E$345+Motor!$E$346+Motor!$E$347+Motor!$E$348+Motor!$E$349+Motor!$E$350+Motor!$E$351+Motor!$E$352+Motor!$E$353) -> -0.60556428
A41: =Pressupostos!$C$190 -> 0.125 | B41: =B$39*Pressupostos!$C$197-$A41*Motor!$E$338-Motor!$E$354-(Motor!$E$342+Motor!$E$345+Motor!$E$346+Motor!$E$347+Motor!$E$348+Motor!$E$349+Motor!$E$350+Motor!$E$351+Motor!$E$352+Motor!$E$353) -> -0.77651428 | C41: =C$39*Pressupostos!$C$197-$A41*Motor!$E$338-Motor!$E$354-(Motor!$E$342+Motor!$E$345+Motor!$E$346+Motor!$E$347+Motor!$E$348+Motor!$E$349+Motor!$E$350+Motor!$E$351+Motor!$E$352+Motor!$E$353) -> -0.76166428 | D41: =D$39*Pressupostos!$C$197-$A41*Motor!$E$338-Motor!$E$354-(Motor!$E$342+Motor!$E$345+Motor!$E$346+Motor!$E$347+Motor!$E$348+Motor!$E$349+Motor!$E$350+Motor!$E$351+Motor!$E$352+Motor!$E$353) -> -0.74681428
A42: =Pressupostos!$C$191 -> 0.15 | B42: =B$39*Pressupostos!$C$197-$A42*Motor!$E$338-Motor!$E$354-(Motor!$E$342+Motor!$E$345+Motor!$E$346+Motor!$E$347+Motor!$E$348+Motor!$E$349+Motor!$E$350+Motor!$E$351+Motor!$E$352+Motor!$E$353) -> -0.91776428 | C42: =C$39*Pressupostos!$C$197-$A42*Motor!$E$338-Motor!$E$354-(Motor!$E$342+Motor!$E$345+Motor!$E$346+Motor!$E$347+Motor!$E$348+Motor!$E$349+Motor!$E$350+Motor!$E$351+Motor!$E$352+Motor!$E$353) -> -0.90291428 | D42: =D$39*Pressupostos!$C$197-$A42*Motor!$E$338-Motor!$E$354-(Motor!$E$342+Motor!$E$345+Motor!$E$346+Motor!$E$347+Motor!$E$348+Motor!$E$349+Motor!$E$350+Motor!$E$351+Motor!$E$352+Motor!$E$353) -> -0.88806428
A44: Margem líquida do embalador: máximo, 2019/20 (€/kg) | B44: =Pressupostos!$C$198 -> 0.499
A45: Desconto \ captura da margem do embalador | B45: =Pressupostos!$C$199 -> 0.8 | C45: =Pressupostos!$C$200 -> 0.85 | D45: =Pressupostos!$C$201 -> 0.9
A46: =Pressupostos!$C$189 -> 0.1 | B46: =B$45*Pressupostos!$C$198-$A46*Motor!$E$338-Motor!$E$354-(Motor!$E$342+Motor!$E$345+Motor!$E$346+Motor!$E$347+Motor!$E$348+Motor!$E$349+Motor!$E$350+Motor!$E$351+Motor!$E$352+Motor!$E$353) -> -0.47366428 | C46: =C$45*Pressupostos!$C$198-$A46*Motor!$E$338-Motor!$E$354-(Motor!$E$342+Motor!$E$345+Motor!$E$346+Motor!$E$347+Motor!$E$348+Motor!$E$349+Motor!$E$350+Motor!$E$351+Motor!$E$352+Motor!$E$353) -> -0.44871428 | D46: =D$45*Pressupostos!$C$198-$A46*Motor!$E$338-Motor!$E$354-(Motor!$E$342+Motor!$E$345+Motor!$E$346+Motor!$E$347+Motor!$E$348+Motor!$E$349+Motor!$E$350+Motor!$E$351+Motor!$E$352+Motor!$E$353) -> -0.42376428
A47: =Pressupostos!$C$190 -> 0.125 | B47: =B$45*Pressupostos!$C$198-$A47*Motor!$E$338-Motor!$E$354-(Motor!$E$342+Motor!$E$345+Motor!$E$346+Motor!$E$347+Motor!$E$348+Motor!$E$349+Motor!$E$350+Motor!$E$351+Motor!$E$352+Motor!$E$353) -> -0.61491428 | C47: =C$45*Pressupostos!$C$198-$A47*Motor!$E$338-Motor!$E$354-(Motor!$E$342+Motor!$E$345+Motor!$E$346+Motor!$E$347+Motor!$E$348+Motor!$E$349+Motor!$E$350+Motor!$E$351+Motor!$E$352+Motor!$E$353) -> -0.58996428 | D47: =D$45*Pressupostos!$C$198-$A47*Motor!$E$338-Motor!$E$354-(Motor!$E$342+Motor!$E$345+Motor!$E$346+Motor!$E$347+Motor!$E$348+Motor!$E$349+Motor!$E$350+Motor!$E$351+Motor!$E$352+Motor!$E$353) -> -0.56501428
A48: =Pressupostos!$C$191 -> 0.15 | B48: =B$45*Pressupostos!$C$198-$A48*Motor!$E$338-Motor!$E$354-(Motor!$E$342+Motor!$E$345+Motor!$E$346+Motor!$E$347+Motor!$E$348+Motor!$E$349+Motor!$E$350+Motor!$E$351+Motor!$E$352+Motor!$E$353) -> -0.75616428 | C48: =C$45*Pressupostos!$C$198-$A48*Motor!$E$338-Motor!$E$354-(Motor!$E$342+Motor!$E$345+Motor!$E$346+Motor!$E$347+Motor!$E$348+Motor!$E$349+Motor!$E$350+Motor!$E$351+Motor!$E$352+Motor!$E$353) -> -0.73121428 | D48: =D$45*Pressupostos!$C$198-$A48*Motor!$E$338-Motor!$E$354-(Motor!$E$342+Motor!$E$345+Motor!$E$346+Motor!$E$347+Motor!$E$348+Motor!$E$349+Motor!$E$350+Motor!$E$351+Motor!$E$352+Motor!$E$353) -> -0.70626428
A50: Todas as células negativas: com 80–90% da margem do embalador não se paga um desconto de 10–15% sobre a referência, nem sequer antes do cupão e dos custos da plataforma.
A52: Choque de −30% no preço: perda pontual no stock de azeite (2031)
A53: Cenário | B53: Stock médio de azeite (€) | C53: Perda: 100% em aberto (€) | D53: Perda: 15% em aberto (€) | E53: Perda 100% ÷ margem anual do azeite
A54: Pessimista | B54: =Motor!$G$227 -> 266508.22 | C54: =Pressupostos!$C$195*B54 -> -79952.466 | D54: =Pressupostos!$C$186*C54 -> -11992.87 | E54: =IF(Motor!$G$114>0,-C54/Motor!$G$114,"n/a") -> n/a
A55: Base | B55: =Motor!$G$537 -> 805623.29 | C55: =Pressupostos!$C$195*B55 -> -241686.99 | D55: =Pressupostos!$C$186*C55 -> -36253.048 | E55: =IF(Motor!$G$424>0,-C55/Motor!$G$424,"n/a") -> 0.90271564
A56: Otimista | B56: =Motor!$G$847 -> 1046486.3 | C56: =Pressupostos!$C$195*B56 -> -313945.89 | D56: =Pressupostos!$C$186*C56 -> -47091.884 | E56: =IF(Motor!$G$734>0,-C56/Motor!$G$734,"n/a") -> 0.25150692
A57: Recomendado (reestruturado) | B57: =Motor!$G$1157 -> 1205424.7 | C57: =Pressupostos!$C$195*B57 -> -361627.4 | D57: =Pressupostos!$C$186*C57 -> -54244.11 | E57: =IF(Motor!$G$1044>0,-C57/Motor!$G$1044,"n/a") -> 0.67362381
A59: O que tem de ser verdade em 2031 (Base e Recomendado): ver Cenários, secção 3

Sheet Fontes
A1: Fontes
A2: Origem de cada pressuposto (texto de pressupostos.json → fontes) e registo de verificação. URL completas em docs/research/00-base-factual.md.
A4: Documentos
A5: docs/fonte/plano-estrategico-10-13.md | B5: Documento-fonte (reunião de 13-10): tese, piloto, responsáveis
A6: docs/research/00-base-factual.md | B6: Base factual consolidada, com fontes, etiquetas e registo de verificação (53 correções)
A7: docs/research/01-desenho-do-modelo.md | B7: Desenho do modelo recomendado: aritmética do lote, estrutura jurídica, risco, piloto, cenários
A8: docs/research/10-mercado.md | B8: Mercado, preços e cadeia de valor (azeite, água, café); TAM/SAM/SOM
A9: docs/research/20-regulatorio.md | B9: Regulatório: prospeto, MiFID, PRIIPs, ECSP, RGICSF, CSC, AIFMD
A10: docs/research/30-pagamentos-infra.md | B10: Pagamentos, PSP, KYC/AML, reconciliação, infraestrutura
A11: docs/research/40-risco-coberturas.md | B11: Risco de preço, carry, coberturas, crédito, stress tests, política de cobertura
A12: docs/research/50-concorrencia.md | B12: Concorrência e comparáveis; economia ECSP; fosso
A13: docs/business-plan/modelo/pressupostos.json | B13: Todos os pressupostos (fonte única dos inputs deste livro)
A14: docs/business-plan/modelo/calculo_referencia.py | B14: Cálculo de referência dos três cenários do documento-fonte (este livro reproduz-o)
A15: docs/business-plan/modelo/resultados.json | B15: Valores recalculados deste livro, por cenário e ano (fonte única dos números dos PDF)
A17: Registo de verificação do modelo financeiro
B18: 2026-10-13, build_model.py: o modelo em Excel (~26.500 fórmulas, 0 erros depois de recalculado no LibreOffice) reproduz calculo_referencia.py nos três cenários do documento-fonte com desvio máximo de 0,01% (EBITDA, GMV, margem, pessoal, opex, capex, capital de giro, obrigações, reserva, cash flow e necessidade de capital) e um espelho em Python do mesmo motor nos quatro cenários e nas 14 sensibilidades; o lote-tipo HoReCa de 2029 reproduz o 01 sec. 2.2 (0,347 €/kg; 6.943 €; cupão 959 €; obrigações 93.375 €; reserva 2.083 €; repartição de Π 46/4/21/28%); referência HoReCa 6,00 no base = +128k de EBITDA em 2031, como no 01 sec. 7.4. Ver resultados.json -> verificacao.
B19: Água, lote de 20 paletes (01 sec. 2.7): o financiamento de 38 EUR implica ~10%/ano; com o cupão base de 8% durante 30 dias sobre stock + depósitos SDR dá 30 EUR. Parâmetros do lote acrescentados em commodities.agua.lote_tipo; diferença de 8 EUR sem efeito no modelo (água em modelo agente).
B20: Ticket médio HoReCa de 150-300 EUR/mês (azeite + água) só é coerente no piloto (~211 EUR/mês); no base de 2031 o consumo assumido dá ~107 EUR/mês (azeite 205 kg/ano a 5,085 + água 0,9 paletes/ano), porque as paletes de água por cliente caem de ~4,8/ano no piloto para 0,9/ano. Não altera margens (água em modelo agente); corrigir a frase no deck.
B21: Gestores de conta no base de 2030: 3 para 1.300 contas (433 por gestor) contra a regra de ~400; diferença dentro do arredondamento ('~400'); não alterado.
B22: Perda potencial de deter stock 18 meses sem cobertura: carry 19,8% + VaR95 37-57% - margem do lote. Com a margem base (6,8%) dá 50-70% (01 sec. 2.6); o intervalo 45-65% só sai com margem de ~12% (referência 6,00). Usar 50-70% no caso base.
B23: Brasil: Portugal tem ~62% das importações de azeite do Brasil; não é o Brasil que compra 62% das exportações portuguesas (00 sec. 1.7).
A25: Correção de leitura (Brasil) | B25: a investigação diz que Portugal tem ~62% das importações de azeite do Brasil (2025/26), não que o Brasil compra 62% das exportações portuguesas: por volume, o 1.º destino é Espanha (37%, sobretudo granel); o Brasil é o 1.º destino do embalado com marca (00-base-factual.md sec. 1.7; 10-mercado.md sec. 1.2)
A27: Pressupostos: fonte por parâmetro (caminho no JSON)
A28: Parâmetro | B28: Fonte / método
A29: commodities.azeite.preco_indice_granel_eur_kg | B29: SIMA/GPP AOVE granel PT intervalo 3,40-3,80 EUR/kg início out. 2026 (https://www.agroportal.pt/azeite-e-azeitona-21-a-27-de-setembro-de-2026/); 3,50 EUR/kg sem. 39/2026 é cotação Oleista, não SIMA (10-mercado.md sec. 1.3; confirmar no boletim SIMA da sem. 39); Poolred 3,34 EUR/kg 29/09-05/10/2026 (https://wikifarmer.com/library/en/article/olive-oil-prices-spain-national-aforo-2026-27); Infaoliva 3,10 a 13/10/2026 (https://www.infobae.com/espana/2026/10/13/precio-del-aceite-de-oliva-en-espana-este-martes-13-de-octubre/). Índice tal como definido (média SIMA + Poolred) a out. 2026 = 3,42-3,47 (3,3-3,4 com as cotações ES de 13-10); o modelo usa 3,50, arredondado para cima (conservador para a margem). Constante: sem previsão de preço.
A30: commodities.azeite.premio_origem_pago_ao_lagar_eur_kg | B30: estimativa: prémio de origem/qualidade sobre o índice para lote individualizado com ficha analítica; diferencial AOVE-lampante de 0,24 EUR/kg em 2026 (https://navarraexports.com/en/market-intelligence/spanish-olive-oil-prices-september-2026-bulk-buyers) indica prémios de qualidade comprimidos
A31: commodities.azeite.volume_t | B31: estimativa: piloto 20 t (1 lote misto: 4 t HoReCa/gourmet + 16 t distribuidores com offtake) + rampa; base 2031 = 2.200 t (~1,3% de ~175 kt [E, ponto médio de 160 (Olivum, https://observador.pt/2026/09/23/producao-de-azeite-em-portugal-pode-crescer-10-em-2026-2027-e-aproximar-se-das-177-mil-toneladas-da-campanha-anterior/) e 179 (Governo, https://www.vejaportugal.pt/2026/07/03/producao-nacional-de-azeite-devera-atingir-179-mil-toneladas-na-campanha-2025-2026/)]); a parte HoReCa está limitada ao SOM (10-mercado.md sec. 5: 1.000-2.000 clientes no ano 3); o resto vai para distribuidores/exportadores com offtake
A32: commodities.azeite.mix_horeca_gourmet | B32: derivado de clientes_horeca_gourmet_ativos_medios x 0,205 t/ano (ponto médio de 150-300 L/ano = 137-275 kg; 10-mercado.md sec. 5); HoReCa: 74.524 empresas, 91% micro (https://tnews.pt/ahresp-setor-da-restauracao-revela-se-instavel-em-2024-devido-a-localizacao-dos-negocios/); 2.000 contas em 2031 = 2,7% das empresas
A33: commodities.azeite.canais.horeca_gourmet.preco_referencia_eur_kg | B33: estimativa (NÃO VERIFICADO no terreno): retalho PT AOVE 6,48 EUR/L c/ IVA mar-abr 2026 = 6,67 EUR/kg s/ IVA com granel a 4,43 (https://observatorioagroalimentar.gov.pt/wp-content/uploads/2026/05/Observatorio_Resumo_Periodo-042026.pdf); ajustado à descida do granel para 3,50-3,60: rácio 0,664 => 5,27-5,42; diferencial constante de 2,24 => 5,74-5,84; intervalo 5,3-6,0 (equivalente de retalho standard a out. 2026); base = 5,65 (ponto médio); 6,00 só no otimista, condicionado a cotações documentadas de AOVE de origem identificada; porta do lagar 5 L 6,08 EUR/L mar. 2026 (https://www.agroportal.pt/wp-content/uploads/2026/03/azei_News12.pdf). Validar com 20-30 cotações cash & carry/foodservice.
A34: commodities.azeite.canais.horeca_gourmet.desconto_efetivo | B34: documento-fonte (10-15%); base no limite inferior porque, com referência 5,65, 15% leva a margem de contribuição HoReCa a ~1,4% (01-desenho-do-modelo.md sec. 2.5)
A35: commodities.azeite.canais.horeca_gourmet.embalamento_eur_kg | B35: Observatorio de la Cadena Alimentaria: 0,470 (2019/20) e 0,514 EUR/kg (2020/21), intervalo 0,293-1,589 (https://www.mapa.gob.es/dam/mapa/contenido/alimentacion/temas/consumo-y-tendencias-en-alimentacion/observatorio-cadena-alimentaria-abril-2016/estudios-e-informes/estudiodelacadenadevalordelaove2019-202008062021.pdf; https://www.interempresas.net/Produccion-Aceite/474711-Actualizado-el-estudio-de-la-cadena-de-valor-del-aceite-de-oliva-virgen-extra.html); +0,05 pelo mix com vidro
A36: commodities.azeite.canais.horeca_gourmet.logistica_eur_kg | B36: estimativa 10-mercado.md sec. 1.7 (0,15-0,30 EUR/kg até à HoReCa); ANTRAM camião Lisboa-Porto 250-270 EUR em 2021 e 'emergência' de combustíveis em mai. 2026 (https://rr.pt/noticia/pais/2026/05/24/transportadoras-a-beira-do-limite-o-setor-esta-completamente-asfixiado/471894/)
A37: commodities.azeite.canais.horeca_gourmet.dias_recebimento | B37: Informa D&B mai. 2026: alojamento e restauração com atraso médio de 30 dias e 11% a pagar a horas (https://blog.informadb.pt/2026/07/empresas-portuguesas-estao-entre-as-que-mais-se-atrasam-nos-pagamentos-em-todo-o-mundo/); base 35 dias assume SDD B2B
A38: commodities.azeite.canais.horeca_gourmet.provisao_credito_pct_vendas | B38: estimativa: SDD B2B sem direito a reembolso (https://europeanpaymentscouncil.eu/sites/default/files/kb/file/2024-11/EPC222-07%202025%20SDD%20B2B%20Rulebook%20version%201.0.pdf) + limites por cliente; ~66 mil empresas em risco de atraso >90 dias (https://jornaleconomico.sapo.pt/noticias/empresas-portuguesas-em-risco-de-atrasos-graves-disparam-para-66-mil-diz-informa-db/)
A39: commodities.azeite.canais.distribuidores_export.preco_referencia_eur_kg | B39: estimativa (NÃO VERIFICADO): preço de saída do embalador pela decomposição do Observatorio de la Cadena Alimentaria: granel 3,50 + embalamento 0,47-0,51 + margem líquida do embalador 0,19-0,50 = 4,16-4,51 EUR/kg (https://www.mapa.gob.es/dam/mapa/contenido/alimentacion/temas/consumo-y-tendencias-en-alimentacion/observatorio-cadena-alimentaria-abril-2016/estudios-e-informes/estudiodelacadenadevalordelaove2019-202008062021.pdf); marca branca ES 5 L 3,99 EUR/kg s/ IVA na prateleira (https://radarsuper.com/mercadona/p/aceite-oliva-virgen-extra-hacendado-garrafa-14727). Break-even do canal em regime: 4,29 EUR/kg; cada 0,10 EUR/kg vale ~178k EUR de EBITDA em 2031 (base, 1.790 t)
... A109: cenario_recomendado | B109: ver cenario_recomendado.alteracoes (cada alteração com justificação e fonte)

Sheet Motor
A1: Motor de cálculo
A2: As mesmas linhas das folhas de detalhe, em blocos fixos por cenário e por caso de sensibilidade. Não editar: os inputs estão em Pressupostos. Cenários, Unit economics e Sensibilidade leem daqui.
A4: Rubrica | B4: Unidade | C4: 2027 | D4: 2028 | E4: 2029 | F4: 2030 | G4: 2031 | H4: id da linha
A6: Bloco: Pessimista
A7: Volumes · Calendário
A8: Ano | C8: 2027 | D8: 2028 | E8: 2029 | F8: 2030 | G8: 2031 | H8: ano
A9: Volumes · Azeite (t)
A10: Clientes HoReCa/gourmet ativos (média anual) | B10: n.º | C10: =Pressupostos!$C$207 -> 30 | D10: =Pressupostos!$D$207 -> 100 | E10: =Pressupostos!$E$207 -> 250 | F10: =Pressupostos!$F$207 -> 400 | G10: =Pressupostos!$G$207 -> 500 | H10: v_h_cli
A11: Azeite HoReCa/gourmet | B11: t | C11: =Pressupostos!$C$213 -> 6 | D11: =Pressupostos!$D$213 -> 21 | E11: =Pressupostos!$E$213 -> 51 | F11: =Pressupostos!$F$213 -> 82 | G11: =Pressupostos!$G$213 -> 103 | H11: v_h_t
A12: Azeite distribuidores/exportação (offtake) | B12: t | C12: =Pressupostos!$C$219 -> 34 | D12: =Pressupostos!$D$219 -> 129 | E12: =Pressupostos!$E$219 -> 249 | F12: =Pressupostos!$F$219 -> 368 | G12: =Pressupostos!$G$219 -> 497 | H12: v_d_t
A13: Azeite granel certificado | B13: t | C13: =Pressupostos!$C$225 -> 0 | D13: =Pressupostos!$D$225 -> 0 | E13: =Pressupostos!$E$225 -> 0 | F13: =Pressupostos!$F$225 -> 0 | G13: =Pressupostos!$G$225 -> 0 | H13: v_g_t
A14: Azeite total | B14: t | C14: =C11+C12+C13 -> 40 | D14: =D11+D12+D13 -> 150 | E14: =E11+E12+E13 -> 300 | F14: =F11+F12+F13 -> 450 | G14: =G11+G12+G13 -> 600 | H14: v_az_t
A15: Peso da HoReCa/gourmet no volume | B15: % | C15: =IF(C14>0,C11/C14,0) -> 0.15 | D15: =IF(D14>0,D11/D14,0) -> 0.14 | E15: =IF(E14>0,E11/E14,0) -> 0.17 | F15: =IF(F14>0,F11/F14,0) -> 0.18222222 | G15: =IF(G14>0,G11/G14,0) -> 0.17166667 | H15: v_h_mix
A16: Quota da produção portuguesa | B16: % | C16: =C14/(Pressupostos!$C$74*1000) -> 0.00022857143 | D16: =D14/(Pressupostos!$C$74*1000) -> 0.00085714286 | E16: =E14/(Pressupostos!$C$74*1000) -> 0.0017142857 | F16: =F14/(Pressupostos!$C$74*1000) -> 0.0025714286 | G16: =G14/(Pressupostos!$C$74*1000) -> 0.0034285714 | H16: v_quota
A17: Lotes-tipo equivalentes | B17: n.º | C17: =C11/Pressupostos!$C$39+C12/Pressupostos!$C$46+C13/Pressupostos!$C$58 -> 1.4333333 | D17: =D11/Pressupostos!$C$39+D12/Pressupostos!$C$46+D13/Pressupostos!$C$58 -> 5.35 | E17: =E11/Pressupostos!$C$39+E12/Pressupostos!$C$46+E13/Pressupostos!$C$58 -> 10.85 | F17: =F11/Pressupostos!$C$39+F12/Pressupostos!$C$46+F13/Pressupostos!$C$58 -> 16.366667 | G17: =G11/Pressupostos!$C$39+G12/Pressupostos!$C$46+G13/Pressupostos!$C$58 -> 21.716667 | H17: v_lotes
A18: Volumes · Água (modelo agente)
A19: Água | B19: paletes | C19: =Pressupostos!$C$251 -> 60 | D19: =Pressupostos!$D$251 -> 0 | E19: =Pressupostos!$E$251 -> 0 | F19: =Pressupostos!$F$251 -> 0 | G19: =Pressupostos!$G$251 -> 0 | H19: v_ag_pal
A20: Água | B20: L | C20: =C19*Pressupostos!$C$76 -> 45000 | D20: =D19*Pressupostos!$C$76 -> 0 | E20: =E19*Pressupostos!$C$76 -> 0 | F20: =F19*Pressupostos!$C$76 -> 0 | G20: =G19*Pressupostos!$C$76 -> 0 | H20: v_ag_l
A21: Volumes · Café verde
A22: Café verde (0 antes do ano de início) | B22: t | C22: =IF(C8<Pressupostos!$C$28,0,Pressupostos!$C$257) -> 0 | D22: =IF(D8<Pressupostos!$C$28,0,Pressupostos!$D$257) -> 0 | E22: =IF(E8<Pressupostos!$C$28,0,Pressupostos!$E$257) -> 10 | F22: =IF(F8<Pressupostos!$C$28,0,Pressupostos!$F$257) -> 20 | G22: =IF(G8<Pressupostos!$C$28,0,Pressupostos!$G$257) -> 30 | H22: v_cf_t
A23: Volumes · Verificação para terceiros (banco parceiro)
A24: Carteira média financiada pelo banco parceiro | B24: € | C24: =Pressupostos!$C$263 -> 0 | D24: =Pressupostos!$D$263 -> 0 | E24: =Pressupostos!$E$263 -> 0 | F24: =Pressupostos!$F$263 -> 500000 | G24: =Pressupostos!$G$263 -> 1000000 | H24: v_tp_cart
A25: Azeite verificado para terceiros | B25: t | C25: =C24/(Pressupostos!$C$103*Pressupostos!$C$104)*Pressupostos!$C$100/1000 -> 0 | D25: =D24/(Pressupostos!$C$103*Pressupostos!$C$104)*Pressupostos!$C$100/1000 -> 0 | E25: =E24/(Pressupostos!$C$103*Pressupostos!$C$104)*Pressupostos!$C$100/1000 -> 0 | F25: =F24/(Pressupostos!$C$103*Pressupostos!$C$104)*Pressupostos!$C$100/1000 -> 457.14286 | G25: =G24/(Pressupostos!$C$103*Pressupostos!$C$104)*Pressupostos!$C$100/1000 -> 914.28571 | H25: v_tp_t
A26: Custos · Economia por kg: HoReCa/gourmet
A27: Preço ao produtor (índice + prémio de origem) | B27: €/kg | C27: =Pressupostos!$C$10+Pressupostos!$C$11 -> 3.65 | D27: =Pressupostos!$C$10+Pressupostos!$C$11 -> 3.65 | E27: =Pressupostos!$C$10+Pressupostos!$C$11 -> 3.65 | F27: =Pressupostos!$C$10+Pressupostos!$C$11 -> 3.65 | G27: =Pressupostos!$C$10+Pressupostos!$C$11 -> 3.65 | H27: h_gr
A28: Preço de referência do comprador | B28: €/kg | C28: =Pressupostos!$C$15 -> 5.4 | D28: =Pressupostos!$C$15 -> 5.4 | E28: =Pressupostos!$C$15 -> 5.4 | F28: =Pressupostos!$C$15 -> 5.4 | G28: =Pressupostos!$C$15 -> 5.4 | H28: h_ref
A29: Preço de venda Sprout (referência − desconto) | B29: €/kg | C29: =C28*(1-Pressupostos!$C$16) -> 4.86 | D29: =D28*(1-Pressupostos!$C$16) -> 4.86 | E29: =E28*(1-Pressupostos!$C$16) -> 4.86 | F29: =F28*(1-Pressupostos!$C$16) -> 4.86 | G29: =G28*(1-Pressupostos!$C$16) -> 4.86 | H29: h_price
A30: Embalamento | B30: €/kg | C30: =Pressupostos!$C$37 -> 0.55 | D30: =Pressupostos!$C$37 -> 0.55 | E30: =Pressupostos!$C$37 -> 0.55 | F30: =Pressupostos!$C$37 -> 0.55 | G30: =Pressupostos!$C$37 -> 0.55 | H30: h_emb
A31: Logística | B31: €/kg | C31: =Pressupostos!$C$232 -> 0.32 | D31: =Pressupostos!$D$232 -> 0.32 | E31: =Pressupostos!$E$232 -> 0.31 | F31: =Pressupostos!$F$232 -> 0.31 | G31: =Pressupostos!$G$232 -> 0.3 | H31: h_log
A32: Armazém logístico (3PL) e picking | B32: €/kg | C32: =Pressupostos!$C$38 -> 0.06 | D32: =Pressupostos!$C$38 -> 0.06 | E32: =Pressupostos!$C$38 -> 0.06 | F32: =Pressupostos!$C$38 -> 0.06 | G32: =Pressupostos!$C$38 -> 0.06 | H32: h_3pl
A33: Stock médio | B33: dias | C33: =Pressupostos!$C$238 -> 180 | D33: =Pressupostos!$D$238 -> 180 | E33: =Pressupostos!$E$238 -> 180 | F33: =Pressupostos!$F$238 -> 90 | G33: =Pressupostos!$G$238 -> 60 | H33: h_ds
A34: Prazo médio de recebimento | B34: dias | C34: =Pressupostos!$C$17 -> 45 | D34: =Pressupostos!$C$17 -> 45 | E34: =Pressupostos!$C$17 -> 45 | F34: =Pressupostos!$C$17 -> 45 | G34: =Pressupostos!$C$17 -> 45 | H34: h_dr
A35: Armazenagem | B35: €/kg | C35: =Pressupostos!$C$64*C33/30/1000 -> 0.024 | D35: =Pressupostos!$C$64*D33/30/1000 -> 0.024 | E35: =Pressupostos!$C$64*E33/30/1000 -> 0.024 | F35: =Pressupostos!$C$64*F33/30/1000 -> 0.012 | G35: =Pressupostos!$C$64*G33/30/1000 -> 0.008 | H35: h_arm
A36: Seguro do stock | B36: €/kg | C36: =C27*Pressupostos!$C$65*C33/365 -> 0.0036 | D36: =D27*Pressupostos!$C$65*D33/365 -> 0.0036 | E36: =E27*Pressupostos!$C$65*E33/365 -> 0.0036 | F36: =F27*Pressupostos!$C$65*F33/365 -> 0.0018 | G36: =G27*Pressupostos!$C$65*G33/365 -> 0.0012 | H36: h_seg
A37: Análises (testes de qualidade) | B37: €/kg | C37: =Pressupostos!$C$40*Pressupostos!$C$66/(Pressupostos!$C$39*1000) -> 0.03 | D37: =Pressupostos!$C$40*Pressupostos!$C$66/(Pressupostos!$C$39*1000) -> 0.03 | E37: =Pressupostos!$C$40*Pressupostos!$C$66/(Pressupostos!$C$39*1000) -> 0.03 | F37: =Pressupostos!$C$40*Pressupostos!$C$66/(Pressupostos!$C$39*1000) -> 0.03 | G37: =Pressupostos!$C$40*Pressupostos!$C$66/(Pressupostos!$C$39*1000) -> 0.03 | H37: h_anal
A38: Perdas físicas | B38: €/kg | C38: =Pressupostos!$C$67*C27 -> 0.01825 | D38: =Pressupostos!$C$67*D27 -> 0.01825 | E38: =Pressupostos!$C$67*E27 -> 0.01825 | F38: =Pressupostos!$C$67*F27 -> 0.01825 | G38: =Pressupostos!$C$67*G27 -> 0.01825 | H38: h_perdas
A39: Desclassificação esperada | B39: €/kg | C39: =Pressupostos!$C$68*Pressupostos!$C$69*C33/90 -> 0.018 | D39: =Pressupostos!$C$68*Pressupostos!$C$69*D33/90 -> 0.018 | E39: =Pressupostos!$C$68*Pressupostos!$C$69*E33/90 -> 0.018 | F39: =Pressupostos!$C$68*Pressupostos!$C$69*F33/90 -> 0.009 | G39: =Pressupostos!$C$68*Pressupostos!$C$69*G33/90 -> 0.006 | H39: h_descl
A40: Custódia (collateral manager) | B40: €/kg | C40: =Pressupostos!$C$41/(Pressupostos!$C$39*1000) -> 0.1 | D40: =Pressupostos!$C$41/(Pressupostos!$C$39*1000) -> 0.1 | E40: =Pressupostos!$C$41/(Pressupostos!$C$39*1000) -> 0.1 | F40: =Pressupostos!$C$41/(Pressupostos!$C$39*1000) -> 0.1 | G40: =Pressupostos!$C$41/(Pressupostos!$C$39*1000) -> 0.1 | H40: h_cust
A41: Pagamentos bancários | B41: €/kg | C41: =Pressupostos!$C$42 -> 0.01 | D41: =Pressupostos!$C$42 -> 0.01 | E41: =Pressupostos!$C$42 -> 0.01 | F41: =Pressupostos!$C$42 -> 0.01 | G41: =Pressupostos!$C$42 -> 0.01 | H41: h_pag
A42: Provisão de crédito | B42: €/kg | C42: =Pressupostos!$C$18*C29 -> 0.03888 | D42: =Pressupostos!$C$18*D29 -> 0.03888 | E42: =Pressupostos!$C$18*E29 -> 0.03888 | F42: =Pressupostos!$C$18*F29 -> 0.03888 | G42: =Pressupostos!$C$18*G29 -> 0.03888 | H42: h_prov
A43: Cobertura de preço explícita (sem futuros de azeite) | B43: €/kg | C43: =Pressupostos!$C$71*C29 -> 0 | D43: =Pressupostos!$C$71*D29 -> 0 | E43: =Pressupostos!$C$71*E29 -> 0 | F43: =Pressupostos!$C$71*F29 -> 0 | G43: =Pressupostos!$C$71*G29 -> 0 | H43: h_hedge
A44: Cupão das obrigações (financiamento do stock) | B44: €/kg | C44: =Pressupostos!$C$282*(C27+C30)*(C33+C34-Pressupostos!$C$70)/365*Pressupostos!$C$276/Pressupostos!$C$31 -> 0 | D44: =Pressupostos!$D$282*(D27+D30)*(D33+D34-Pressupostos!$C$70)/365*Pressupostos!$D$276/Pressupostos!$C$31 -> 0.24521918 | E44: =Pressupostos!$E$282*(E27+E30)*(E33+E34-Pressupostos!$C$70)/365*Pressupostos!$E$276/Pressupostos!$C$31 -> 0.24521918 | F44: =Pressupostos!$F$282*(F27+F30)*(F33+F34-Pressupostos!$C$70)/365*Pressupostos!$F$276/Pressupostos!$C$31 -> 0.1320411 | G44: =Pressupostos!$G$282*(G27+G30)*(G33+G34-Pressupostos!$C$70)/365*Pressupostos!$G$276/Pressupostos!$C$31 -> 0.094315068 | H44: h_cupao
A45: Custo direto total | B45: €/kg | C45: =C27+C30+C31+C32+C35+C36+C37+C38+C39+C40+C41+C42+C43+C44 -> 4.82273 | D45: =D27+D30+D31+D32+D35+D36+D37+D38+D39+D40+D41+D42+D43+D44 -> 5.0679492 | E45: =E27+E30+E31+E32+E35+E36+E37+E38+E39+E40+E41+E42+E43+E44 -> 5.0579492 | F45: =F27+F30+F31+F32+F35+F36+F37+F38+F39+F40+F41+F42+F43+F44 -> 4.9219711 | G45: =G27+G30+G31+G32+G35+G36+G37+G38+G39+G40+G41+G42+G43+G44 -> 4.8666451 | H45: h_custo
A46: Margem de contribuição | B46: €/kg | C46: =C29-C45 -> 0.03727 | D46: =D29-D45 -> -0.20794918 | E46: =E29-E45 -> -0.19794918 | F46: =F29-F45 -> -0.061971096 | G46: =G29-G45 -> -0.0066450685 | H46: h_margem
A47: Margem de contribuição em % do preço | B47: % | C47: =IF(C29>0,C46/C29,0) -> 0.0076687243 | D47: =IF(D29>0,D46/D29,0) -> -0.042787897 | E47: =IF(E29>0,E46/E29,0) -> -0.040730284 | F47: =IF(F29>0,F46/F29,0) -> -0.012751254 | G47: =IF(G29>0,G46/G29,0) -> -0.001367298 | H47: h_margem_pct
A48: Capital de giro por kg vendido | B48: €/kg | C48: =(C27+C30)*(C33-Pressupostos!$C$70)/365+C29*C34/365 -> 2.3252055 | D48: =(D27+D30)*(D33-Pressupostos!$C$70)/365+D29*D34/365 -> 2.3252055 | E48: =(E27+E30)*(E33-Pressupostos!$C$70)/365+E29*E34/365 -> 2.3252055 | F48: =(F27+F30)*(F33-Pressupostos!$C$70)/365+F29*F34/365 -> 1.289589 | G48: =(G27+G30)*(G33-Pressupostos!$C$70)/365+G29*G34/365 -> 0.94438356 | H48: h_cg
A49: Custos · Economia por kg: distribuidores/exportação
A50: Preço ao produtor (índice + prémio de origem) | B50: €/kg | C50: =Pressupostos!$C$10+Pressupostos!$C$12 -> 3.65 | D50: =Pressupostos!$C$10+Pressupostos!$C$12 -> 3.65 | E50: =Pressupostos!$C$10+Pressupostos!$C$12 -> 3.65 | F50: =Pressupostos!$C$10+Pressupostos!$C$12 -> 3.65 | G50: =Pressupostos!$C$10+Pressupostos!$C$12 -> 3.65 | H50: d_gr
A51: Preço de referência do comprador | B51: €/kg | C51: =Pressupostos!$C$20+Pressupostos!$C$21 -> 4.2 | D51: =Pressupostos!$C$20+Pressupostos!$C$21 -> 4.2 | E51: =Pressupostos!$C$20+Pressupostos!$C$21 -> 4.2 | F51: =Pressupostos!$C$20+Pressupostos!$C$21 -> 4.2 | G51: =Pressupostos!$C$20+Pressupostos!$C$21 -> 4.2 | H51: d_ref
A52: Preço de venda Sprout (referência − desconto) | B52: €/kg | C52: =C51*(1-Pressupostos!$C$22) -> 4.2 | D52: =D51*(1-Pressupostos!$C$22) -> 4.2 | E52: =E51*(1-Pressupostos!$C$22) -> 4.2 | F52: =F51*(1-Pressupostos!$C$22) -> 4.2 | G52: =G51*(1-Pressupostos!$C$22) -> 4.2 | H52: d_price
A53: Embalamento | B53: €/kg | C53: =Pressupostos!$C$44 -> 0.45 | D53: =Pressupostos!$C$44 -> 0.45 | E53: =Pressupostos!$C$44 -> 0.45 | F53: =Pressupostos!$C$44 -> 0.45 | G53: =Pressupostos!$C$44 -> 0.45 | H53: d_emb
A54: Logística | B54: €/kg | C54: =Pressupostos!$C$244 -> 0.11 | D54: =Pressupostos!$D$244 -> 0.11 | E54: =Pressupostos!$E$244 -> 0.11 | F54: =Pressupostos!$F$244 -> 0.11 | G54: =Pressupostos!$G$244 -> 0.11 | H54: d_log
A55: Armazém logístico (3PL) e picking | B55: €/kg | C55: =Pressupostos!$C$45 -> 0 | D55: =Pressupostos!$C$45 -> 0 | E55: =Pressupostos!$C$45 -> 0 | F55: =Pressupostos!$C$45 -> 0 | G55: =Pressupostos!$C$45 -> 0 | H55: d_3pl
A56: Stock médio | B56: dias | C56: =Pressupostos!$C$23 -> 35 | D56: =Pressupostos!$C$23 -> 35 | E56: =Pressupostos!$C$23 -> 35 | F56: =Pressupostos!$C$23 -> 35 | G56: =Pressupostos!$C$23 -> 35 | H56: d_ds
A57: Prazo médio de recebimento | B57: dias | C57: =Pressupostos!$C$24 -> 55 | D57: =Pressupostos!$C$24 -> 55 | E57: =Pressupostos!$C$24 -> 55 | F57: =Pressupostos!$C$24 -> 55 | G57: =Pressupostos!$C$24 -> 55 | H57: d_dr
A58: Armazenagem | B58: €/kg | C58: =Pressupostos!$C$64*C56/30/1000 -> 0.0046666667 | D58: =Pressupostos!$C$64*D56/30/1000 -> 0.0046666667 | E58: =Pressupostos!$C$64*E56/30/1000 -> 0.0046666667 | F58: =Pressupostos!$C$64*F56/30/1000 -> 0.0046666667 | G58: =Pressupostos!$C$64*G56/30/1000 -> 0.0046666667 | H58: d_arm
A59: Seguro do stock | B59: €/kg | C59: =C50*Pressupostos!$C$65*C56/365 -> 0.0007 | D59: =D50*Pressupostos!$C$65*D56/365 -> 0.0007 | E59: =E50*Pressupostos!$C$65*E56/365 -> 0.0007 | F59: =F50*Pressupostos!$C$65*F56/365 -> 0.0007 | G59: =G50*Pressupostos!$C$65*G56/365 -> 0.0007 | H59: d_seg
A60: Análises (testes de qualidade) | B60: €/kg | C60: =Pressupostos!$C$47*Pressupostos!$C$66/(Pressupostos!$C$46*1000) -> 0.02 | D60: =Pressupostos!$C$47*Pressupostos!$C$66/(Pressupostos!$C$46*1000) -> 0.02 | E60: =Pressupostos!$C$47*Pressupostos!$C$66/(Pressupostos!$C$46*1000) -> 0.02 | F60: =Pressupostos!$C$47*Pressupostos!$C$66/(Pressupostos!$C$46*1000) -> 0.02 | G60: =Pressupostos!$C$47*Pressupostos!$C$66/(Pressupostos!$C$46*1000) -> 0.02 | H60: d_anal
A61: Perdas físicas | B61: €/kg | C61: =Pressupostos!$C$67*C50 -> 0.01825 | D61: =Pressupostos!$C$67*D50 -> 0.01825 | E61: =Pressupostos!$C$67*E50 -> 0.01825 | F61: =Pressupostos!$C$67*F50 -> 0.01825 | G61: =Pressupostos!$C$67*G50 -> 0.01825 | H61: d_perdas
A62: Desclassificação esperada | B62: €/kg | C62: =Pressupostos!$C$68*Pressupostos!$C$69*C56/90 -> 0.0035 | D62: =Pressupostos!$C$68*Pressupostos!$C$69*D56/90 -> 0.0035 | E62: =Pressupostos!$C$68*Pressupostos!$C$69*E56/90 -> 0.0035 | F62: =Pressupostos!$C$68*Pressupostos!$C$69*F56/90 -> 0.0035 | G62: =Pressupostos!$C$68*Pressupostos!$C$69*G56/90 -> 0.0035 | H62: d_descl
A63: Custódia (collateral manager) | B63: €/kg | C63: =Pressupostos!$C$48/(Pressupostos!$C$46*1000) -> 0.04 | D63: =Pressupostos!$C$48/(Pressupostos!$C$46*1000) -> 0.04 | E63: =Pressupostos!$C$48/(Pressupostos!$C$46*1000) -> 0.04 | F63: =Pressupostos!$C$48/(Pressupostos!$C$46*1000) -> 0.04 | G63: =Pressupostos!$C$48/(Pressupostos!$C$46*1000) -> 0.04 | H63: d_cust
A64: Pagamentos bancários | B64: €/kg | C64: =Pressupostos!$C$49 -> 0.005 | D64: =Pressupostos!$C$49 -> 0.005 | E64: =Pressupostos!$C$49 -> 0.005 | F64: =Pressupostos!$C$49 -> 0.005 | G64: =Pressupostos!$C$49 -> 0.005 | H64: d_pag
A65: Provisão de crédito | B65: €/kg | C65: =Pressupostos!$C$25*C52 -> 0.021 | D65: =Pressupostos!$C$25*D52 -> 0.021 | E65: =Pressupostos!$C$25*E52 -> 0.021 | F65: =Pressupostos!$C$25*F52 -> 0.021 | G65: =Pressupostos!$C$25*G52 -> 0.021 | H65: d_prov
A66: Cobertura de preço explícita (sem futuros de azeite) | B66: €/kg | C66: =Pressupostos!$C$71*C52 -> 0 | D66: =Pressupostos!$C$71*D52 -> 0 | E66: =Pressupostos!$C$71*E52 -> 0 | F66: =Pressupostos!$C$71*F52 -> 0 | G66: =Pressupostos!$C$71*G52 -> 0 | H66: d_hedge
A67: Cupão das obrigações (financiamento do stock) | B67: €/kg | C67: =Pressupostos!$C$282*(C50+C53)*(C56+C57-Pressupostos!$C$70)/365*Pressupostos!$C$276/Pressupostos!$C$31 -> 0 | D67: =Pressupostos!$D$282*(D50+D53)*(D56+D57-Pressupostos!$C$70)/365*Pressupostos!$D$276/Pressupostos!$C$31 -> 0.073655577 | E67: =Pressupostos!$E$282*(E50+E53)*(E56+E57-Pressupostos!$C$70)/365*Pressupostos!$E$276/Pressupostos!$C$31 -> 0.073655577 | F67: =Pressupostos!$F$282*(F50+F53)*(F56+F57-Pressupostos!$C$70)/365*Pressupostos!$F$276/Pressupostos!$C$31 -> 0.073655577 | G67: =Pressupostos!$G$282*(G50+G53)*(G56+G57-Pressupostos!$C$70)/365*Pressupostos!$G$276/Pressupostos!$C$31 -> 0.073655577 | H67: d_cupao
A68: Custo direto total | B68: €/kg | C68: =C50+C53+C54+C55+C58+C59+C60+C61+C62+C63+C64+C65+C66+C67 -> 4.3231167 | D68: =D50+D53+D54+D55+D58+D59+D60+D61+D62+D63+D64+D65+D66+D67 -> 4.3967722 | E68: =E50+E53+E54+E55+E58+E59+E60+E61+E62+E63+E64+E65+E66+E67 -> 4.3967722 | F68: =F50+F53+F54+F55+F58+F59+F60+F61+F62+F63+F64+F65+F66+F67 -> 4.3967722 | G68: =G50+G53+G54+G55+G58+G59+G60+G61+G62+G63+G64+G65+G66+G67 -> 4.3967722 | H68: d_custo
A69: Margem de contribuição | B69: €/kg | C69: =C52-C68 -> -0.12311667 | D69: =D52-D68 -> -0.19677224 | E69: =E52-E68 -> -0.19677224 | F69: =F52-F68 -> -0.19677224 | G69: =G52-G68 -> -0.19677224 | H69: d_margem
A70: Margem de contribuição em % do preço | B70: % | C70: =IF(C52>0,C69/C52,0) -> -0.029313492 | D70: =IF(D52>0,D69/D52,0) -> -0.046850534 | E70: =IF(E52>0,E69/E52,0) -> -0.046850534 | F70: =IF(F52>0,F69/F52,0) -> -0.046850534 | G70: =IF(G52>0,G69/G52,0) -> -0.046850534 | H70: d_margem_pct
A71: Capital de giro por kg vendido | B71: €/kg | C71: =(C50+C53)*(C56-Pressupostos!$C$70)/365+C52*C57/365 -> 0.6890411 | D71: =(D50+D53)*(D56-Pressupostos!$C$70)/365+D52*D57/365 -> 0.6890411 | E71: =(E50+E53)*(E56-Pressupostos!$C$70)/365+E52*E57/365 -> 0.6890411 | F71: =(F50+F53)*(F56-Pressupostos!$C$70)/365+F52*F57/365 -> 0.6890411 | G71: =(G50+G53)*(G56-Pressupostos!$C$70)/365+G52*G57/365 -> 0.6890411 | H71: d_cg
A72: Custos · Economia por kg: granel certificado
A73: Preço ao produtor (índice + prémio de origem) | B73: €/kg | C73: =Pressupostos!$C$10+Pressupostos!$C$13 -> 3.5 | D73: =Pressupostos!$C$10+Pressupostos!$C$13 -> 3.5 | E73: =Pressupostos!$C$10+Pressupostos!$C$13 -> 3.5 | F73: =Pressupostos!$C$10+Pressupostos!$C$13 -> 3.5 | G73: =Pressupostos!$C$10+Pressupostos!$C$13 -> 3.5 | H73: g_gr
A74: Preço de referência do comprador | B74: €/kg | C74: =Pressupostos!$C$10+Pressupostos!$C$51 -> 3.65 | D74: =Pressupostos!$C$10+Pressupostos!$C$51 -> 3.65 | E74: =Pressupostos!$C$10+Pressupostos!$C$51 -> 3.65 | F74: =Pressupostos!$C$10+Pressupostos!$C$51 -> 3.65 | G74: =Pressupostos!$C$10+Pressupostos!$C$51 -> 3.65 | H74: g_ref
A75: Preço de venda Sprout (referência − desconto) | B75: €/kg | C75: =C74*(1-Pressupostos!$C$52) -> 3.65 | D75: =D74*(1-Pressupostos!$C$52) -> 3.65 | E75: =E74*(1-Pressupostos!$C$52) -> 3.65 | F75: =F74*(1-Pressupostos!$C$52) -> 3.65 | G75: =G74*(1-Pressupostos!$C$52) -> 3.65 | H75: g_price
A76: Embalamento | B76: €/kg | C76: =Pressupostos!$C$53 -> 0 | D76: =Pressupostos!$C$53 -> 0 | E76: =Pressupostos!$C$53 -> 0 | F76: =Pressupostos!$C$53 -> 0 | G76: =Pressupostos!$C$53 -> 0 | H76: g_emb
A77: Logística | B77: €/kg | C77: =Pressupostos!$C$54 -> 0.04 | D77: =Pressupostos!$C$54 -> 0.04 | E77: =Pressupostos!$C$54 -> 0.04 | F77: =Pressupostos!$C$54 -> 0.04 | G77: =Pressupostos!$C$54 -> 0.04 | H77: g_log
A78: Armazém logístico (3PL) e picking | B78: €/kg | C78: =Pressupostos!$C$55 -> 0 | D78: =Pressupostos!$C$55 -> 0 | E78: =Pressupostos!$C$55 -> 0 | F78: =Pressupostos!$C$55 -> 0 | G78: =Pressupostos!$C$55 -> 0 | H78: g_3pl
A79: Stock médio | B79: dias | C79: =Pressupostos!$C$56 -> 15 | D79: =Pressupostos!$C$56 -> 15 | E79: =Pressupostos!$C$56 -> 15 | F79: =Pressupostos!$C$56 -> 15 | G79: =Pressupostos!$C$56 -> 15 | H79: g_ds
A80: Prazo médio de recebimento | B80: dias | C80: =Pressupostos!$C$57 -> 45 | D80: =Pressupostos!$C$57 -> 45 | E80: =Pressupostos!$C$57 -> 45 | F80: =Pressupostos!$C$57 -> 45 | G80: =Pressupostos!$C$57 -> 45 | H80: g_dr
